{
  "title.dashboard": "ويفيرياضا ف واوف وااراروض ",
  "title.organizations": "يضضضوووييضضور ض رافا ضاواضرفا ",
  "title.datasets": "اضافوورو و ضفضا يوارافضر ",
  "title.installations": "ضفرواارافضوضض و وييو ويافيويي ",
  "title.nodes": "يوضفض ا يفضو ضيريوراو ",
  "title.users": "وفرار ا فوضو يفضيففرف ",
  "title.organization": "رضفففافرضايو ر واضض ضضييضيفو ",
  "title.dataset": "راافااي ض رضوض ضويارفاا ",
  "title.installation": "وضيوفوروفوفو ف ضفوو يوييريير ",
  "title.node": "فاضا ي ضيرض ارضيضيرض ",
  "title.user": "يضرض ا اضفض رضيرييفو ",
  "title.newOrganization": "ريو رريفاريووييف ر اضوف وضيوضففي ",
  "title.newDataset": "وور ييورريض و يافو واايضفوي ",
  "title.newInstallation": "ضرض ررروايررفريض ي اااي ارفضويور ",
  "title.collections": "يرراوارفاضر ر يضيف اضيفرفيا ",
  "title.persons": "وفضوضاف ي اوفر فاضااافي ",
  "title.institutions": "ااوفرفيضيياا ي ضضفا يراوفاري ",
  "title.collection": "ررفياوفضيا ي اااو ايفااضرف ",
  "title.person": "روفيور ض ضررر ففوضاوضر ",
  "title.institution": "ييففرورايير ف افوا افاضضوضي ",
  "title.newCollection": "راا اريضارضرضر ا ايفف يريففففا ",
  "title.newPerson": "راو فيفااف و ضررو ريضففارو ",
  "title.newInstitution": "وفا رووريوفيوضو و افوو ضاافاوفو ",
  "welcome": "اييرافوفف ",
  "title": "فوواو ",
  "dashboard.message1": "ضواا يفضضفا ويي روضضااضف واراي فضااوضو ار روي راروضضو ضرراض يض يففرضر راوضوو اض وفريو ضفض رريورففي رففرويي اوييوفاضضي ",
  "dashboard.message2": "اف ضيفيفو يا يف ضوضضا ضاضض رووو ا وفيفواييضي وفروضوض ييافرويييفاوا رويفففض وضروفاو يضفويضا ",
  "createNew": "ايوافف رضو ",
  "addNew": "واو وفف ",
  "create": "اروفوي ",
  "delete": "وريوفي ",
  "edit": "اضفف ",
  "view": "وافر ",
  "add": "اير ",
  "cancel": "وويفوف ",
  "createdByRow": "[[[!Created {date} by {author}!]]]",
  "noMachineTags": "اض فويضووض ايوض ",
  "createNewComment": "ضضييضر ي ففف فريريوف ",
  "content": "ففرفراض ",
  "supportedFormats": "ضوفا ايض يي يرريف فريو رض روايضرييي ر ضض اراو ففرض فضر ",
  "createNewContact": "روافرض ر واا ضايرواو ",
  "addNewContact": "ياو ف ويو ضرفيضيي ",
  "editFormInstructions": "ففواو ضفضرر يواضيو فضاضررافر رارضفر ضواوضا يرفوضوضو فرو رريضاضي ضيف فاايووورض فر ي ررف ضرو اوض فافضاوففا فض رفي ويراورضضوا ",
  "type": "فوار ",
  "select.type": "رفوفري و وضرض ",
  "select.country": "ضرييفو ض فييروضو ",
  "select.endorsingNode": "يففرور فف رراريضررا فضيا ",
  "select.language": "رووورر ض اوضرايرض ",
  "select.subtype": "ااريفض ا وفيضفضا ",
  "select.license": "فيارفر ا اررفافي ",
  "select.organization": "رافيوض فض ررضيفرايضضرر ",
  "select.installation": "ضارضاو رض ورضفوضيضوااا ",
  "select.updateFrequency": "واوضوض او ااوضيا رضيوضرورا ",
  "select.parentDataset": "ييفافف ضروفاض ضيااييي ",
  "select.duplicateDataset": "اارفيض ضفضريفروو اف ويافافض ",
  "select.status": "ريييوي ض وررووف ",
  "select.region": "ورارضا ا فيفففو ",
  "select.continent": "ضوفاار ر فياورووفر ",
  "select.institution": "اضارري رض ارضافضيرضوض ",
  "select.governance": "ضروفوا و يورروررفار ",
  "select.discipline": "فروفضا ف افضيفورفيف ",
  "select.number": "يويااا ا ففوارر ",
  "select.collection": "ضوفررا ي فواويففراي ",
  "select.person": "فارراا ا رووضار ",
  "primary": "يففرررو ",
  "firstName": "اضارا يريف ",
  "lastName": "رورو فوري ",
  "position": "اوضيوضيض ",
  "provide.position": "رافافف ففوضفاو ف ضارضريضا ",
  "provide.email": "ضوفضاف ررففضيو رض فوياض ",
  "provide.phone": "وورضرر يوففيضي ا ايييف ",
  "provide.homepage": "فاضاضف ضضضضفيف ف يفييرياو ",
  "provide.address": "رراارض روواووو فض ضوفرففو ",
  "provide.userId": "فوافضف وفووييو و وررو رض ",
  "provide.url": "فيفروي ضواووضا و وري ",
  "provide.identifier": "ضرااار ضرضايوا يا وفاوضويفوي ",
  "provide.namespace": "رضفاوا فاروفضف ي اييضااوري ",
  "provide.name": "اااوفي ايافووف ض يضفف ",
  "provide.value": "ايواضو وفضضيفف ي ريايو ",
  "provide.title": "ضيايضف روييويا و ييضاي ",
  "provide.endorsingNode": "يفاضوا وارايوا اي ضضارفوضاف فضرض ",
  "provide.type": "يايايو وضياضضر ا رضرا ",
  "provide.subtype": "افرراي ضرارارر ض يويااضا ",
  "provide.language": "فررضاو يفاررور ف وووارويو ",
  "provide.license": "وفواضو اضضرفضا ر واووارر ",
  "provide.firstName": "اوايوو فاضوضضض رضافا ضضار ",
  "provide.doi": "رضافاا يرييضاا ا افف ",
  "provide.organization": "اافرار يوافاري يو راياررياروفو ",
  "provide.installation": "رروضفي ياففيضر وا ايااييوواووي ",
  "provide.institution": "يوضضير رييفوضض فض فضيرفارياضف ",
  "provide.code": "وييضوا وضيرضرو ض رريض ",
  "provide.userName": "واايضا ضوضيي اويض فرضضورايي ",
  "provide.password": "ورفاور يوريض وضفا ضاواضوضفي ",
  "description": "يراورووفيفا ",
  "phone": "فراضا ",
  "homepage": "ارفوايور ",
  "organization": "وفاضافيفضويف ",
  "address": "افضفرفو ",
  "city": "يروف ",
  "province": "ررضريضفر ",
  "country": "فضريارر ",
  "postalCode": "ضواايض وضوي ",
  "userId": "يووا فا ",
  "createNewEndpoint": "ارفضري ا ضاي روفاوريو ",
  "url": "ففف ",
  "createNewIdentifier": "ضوواوف ض ضري اافاارروضي ",
  "identifier": "ضيافرووريو ",
  "createNewMachineTag": "ورافاو ض وفي رويضايف ضرو ",
  "namespace": "اريضفرريا ",
  "name": "ايفر ",
  "finishReason": "فويوير رفوروو ",
  "startedCrawling": "ررررضرر ورففضرور ",
  "finishedCrawling": "فيففوفوف ضروفايضض ",
  "value": "يضوير ",
  "createNewTag": "فيفرفو ي ييو ضوض ",
  "created": "فوضضرضض ",
  "createdBy": "راياياو يض ",
  "modified": "ضروففااي ",
  "modifiedBy": "يارففررر وف ",
  "userName": "ووضيييفا ",
  "email": "ييييي ",
  "overview": "فضياياضو ",
  "contacts": "يفررايوا ",
  "endpoints": "يضييررضضض ",
  "identifiers": "يضياايضرضضا ",
  "dataset": "ارااضيف ",
  "node": "فاضف ",
  "person": "وفوياو ",
  "collection": "ويفراريروا ",
  "institution": "اررااراضووي ",
  "tags": "اضرض ",
  "machineTags": "ضفضرااا يضفف ",
  "comments": "ضاضرضوفر ",
  "publishedDataset": "يفضايضراا فضوايفف ",
  "publishedDatasets": "ريييضفواض وايضفاار ",
  "hostedDataset": "فرضاوف ييياراف ",
  "hostedDatasets": "رضفووي رياافففف ",
  "installations": "ضيفضورووضضيفا ",
  "abbreviation": "يررضيففففرضض ",
  "endorsingNode": "فووافففيف فاوي ",
  "approved": "يرفويووا ",
  "awaitingApproval": "ييفضففيض يضوويوضا ",
  "logoUrl": "اضوا يور ",
  "logo": "وييي ",
  "language": "ورضرفارر ",
  "latitude": "وضضروضاي ",
  "longitude": "وروواراضو ",
  "crawl": "ااضفض ",
  "endorsementApproved": "اوروفرايضوو يضافرفار ",
  "menu.organization": "يوضضيرضاوضييف ",
  "menu.organization.search": "فررفضض ررورضيفضروراض ",
  "menu.dataset.search": "فضفضفر ويايففضا ",
  "menu.installation.search": "اوضفضف ضضوارضوارويوض ",
  "menu.organization.deleted": "رااوااف ضريضضفضاافوضا ",
  "menu.dataset.deleted": "ضفففضار فيضووضاف ",
  "menu.installation.deleted": "وضييراض اضضريييوراراو ",
  "menu.organization.pending": "يضورضيي فضضفضوايااضفا ",
  "menu.organization.nonPublishing": "يفو ضارييرضضور ضضضاوففياووضو ",
  "menu.dataset": "ايارياوا ",
  "menu.dataset.duplicate": "يريضوريضري يو وورفافري ",
  "menu.dataset.constituent": "يفاوضايفايف ورضافروف ",
  "menu.dataset.withNoEndpoint": "ايضوااوو اوضر اض رااضروفف ",
  "menu.installation": "يوضيضفيضضرااا ",
  "menu.installation.empty": "فواوض يارااارفاففضر ",
  "menu.collection": "ضررافايروور ",
  "menu.collection.search": "ضضواار ييورييورضار ",
  "menu.collection.deleted": "ضافضضيو فروافاررضير ",
  "menu.institution": "ضايوافيوضواض ",
  "menu.institution.search": "راااور ااورضيوفوضرف ",
  "menu.institution.deleted": "ووضفيير اارراضييضفيي ",
  "menu.grbioPerson": "اروضض افرضي ",
  "menu.grbioPerson.search": "واروي اافضا اوووري ",
  "menu.grbioPerson.deleted": "ضويور رييوا ورضرضفر ",
  "menu.node": "ضفوفف ",
  "menu.user": "يرضاا ",
  "menu.monitoring": "يرورراواوف ",
  "menu.monitoring.ingestion": "فضضففضا فاافروورضي ",
  "menu.monitoring.overingested": "فيفاضوفاضررفف يااويضرر ",
  "submenu.contact": "ياراورفي ",
  "submenu.identifier": "ايضضفيضراور ",
  "submenu.endpoint": "ورضواواار ",
  "submenu.tag": "وفيا ",
  "submenu.machineTag": "فواااير ضيوو ",
  "submenu.comment": "يضضارررر ",
  "submenu.constituents": "ويضرفيضاروو راواارفر ",
  "submenu.publishedDataset": "ضاريياواو رفيررريا ",
  "submenu.hostedDataset": "رواوري فوفيوورا ",
  "submenu.installation": "ررويووااريووض ",
  "submenu.synchronizationHistory": "ففيفافريففاوايا فايففاا ",
  "submenu.servedDatasets": "يررفضا ضوااايرا ",
  "submenu.pending": "راارفار ويضاااضوضووي ",
  "submenu.organization": "روواارضف وضرففافرضااضو ",
  "submenu.dataset": "فواورفوي ضراضفرفض ",
  "submenu.collection": "ييياوويوافض ",
  "submenu.institution": "ضاضاريارفافض ",
  "submenu.process": "ررضوضففيا ",
  "submenu.download": "رايرفريي ",
  "listType.search": "ضرايير ",
  "listType.deleted": "اررووضي ",
  "listType.pending": "وضيوضوي ",
  "listType.nonPublishingOrganizations": "ضوايضاي ",
  "listType.duplicate": "ضففضفيراف ",
  "listType.constituent": "اوففضرفيايو ",
  "listType.withNoEndpoint": "رايض ري يوافضيري ",
  "listType.servingNoDatasets": "يضفضريف اف ضيرروضرا ",
  "placeholder.username": "ااووفييا ",
  "placeholder.password": "افافاواض ",
  "rememberMe": "ففففافاي ضا ",
  "logIn": "يوا ضف ",
  "login": "ورااو ",
  "logout": "فريضرا ",
  "country.AD": "ويفيريو ",
  "country.AE": "فويايف ويضر ضايفرايف ",
  "country.AF": "ويرييووايفو ",
  "country.AG": "فايرويا وضو ييضفففر ",
  "country.AI": "فوفريييو ",
  "country.AL": "يرضضراا ",
  "country.AM": "ارريضفف ",
  "country.AO": "روويضي ",
  "country.AQ": "رورراايضفر ",
  "country.AR": "ضضضوضضاضو ",
  "country.AS": "رووفيايف ورروي ",
  "country.AT": "وفراروا ",
  "country.AU": "ورفضفوفرو ",
  "country.AW": "رارور ",
  "country.AX": "ووفوض فوضرضير ",
  "country.AZ": "وفضضويضفيا ",
  "country.BA": "ووضوفا ضرر فيضضفاواوفا ",
  "country.BB": "روضرفويف ",
  "country.BD": "وروضفاضرضف ",
  "country.BE": "ياوورفو ",
  "country.BF": "فواضوير يااض ",
  "country.BG": "ارويررضف ",
  "country.BH": "اوافرفو ",
  "country.BI": "رااافوض ",
  "country.BJ": "فروفو ",
  "country.BL": "يويوض ضاضاييضارر ",
  "country.BM": "ففافرير ",
  "country.BN": "ضضررفض ضضضضيوضويي ",
  "country.BO": "رضيفوضوض ايوايوضاضوايي ضرارا يو ",
  "country.BQ": "يفايضووي ضففي رررافاوفض ورا يافا ",
  "country.BR": "اضفضاف ",
  "country.BS": "اضضيوضا ",
  "country.BT": "ييوويو ",
  "country.BV": "فيافار ضفضويف ",
  "country.BW": "ففاضوويا ",
  "country.BY": "ضيارضفف ",
  "country.BZ": "يضيفيض ",
  "country.CA": "وفييرف ",
  "country.CC": "ضوضيض (ففورضرف) ضاافورف ",
  "country.CD": "ريوضاض فاو يوضررافورر فيوفورير يي يرر ",
  "country.CF": "ويراضفف واارريو وفافضضار ",
  "country.CG": "ضضيرض ",
  "country.CH": "ياضيوافففوا ",
  "country.CI": "ويضي يواياويض ",
  "country.CK": "اوري يوضرضوو ",
  "country.CL": "ييضفف ",
  "country.CM": "رافووضوي ",
  "country.CN": "فضورا ",
  "country.CO": "اروييافر ",
  "country.CR": "فاففف اييو ",
  "country.CU": "ااوا ",
  "country.CV": "ويفض ضرورو ",
  "country.CW": "ويييففا ",
  "country.CX": "ضياويرياف فاياوا ",
  "country.CY": "اضففاا ",
  "country.CZ": "اويرض ضفاويفوو ",
  "country.DE": "واييضاا ",
  "country.DJ": "اويفضفرو ",
  "country.DK": "ياضييفض ",
  "country.DM": "اضيفااوو ",
  "country.DO": "ووضريايرض يوضوفضوف ",
  "country.DZ": "فياوضرو ",
  "country.EC": "ييضرضيف ",
  "country.EE": "ضاويفاض ",
  "country.EG": "يفضوا ",
  "country.EH": "افففروف ريويضا ",
  "country.ER": "افريررر ",
  "country.ES": "رفااو ",
  "country.ET": "ررفضضرير ",
  "country.FI": "فيارايي ",
  "country.FJ": "يففو ",
  "country.FK": "رفيضييضض افضريور (ووففضراي) ",
  "country.FM": "ضريفرااضفاض اواضراواا اضضيضي ار ",
  "country.FO": "واضضو ضيارضوف ",
  "country.FR": "وضرضاض ",
  "country.GA": "يياوض ",
  "country.GB": "اوففرف ضضفيضوي ",
  "country.GD": "ففااااو ",
  "country.GE": "ضضاياار ",
  "country.GF": "يوفرضي ضويررف ",
  "country.GG": "رضايضوري ",
  "country.GH": "يضورف ",
  "country.GI": "يورضيايير ",
  "country.GL": "فاوااويفض ",
  "country.GM": "ااضياو ",
  "country.GN": "يورفوو ",
  "country.GP": "وضيفايييرر ",
  "country.GQ": "ففريرفايرض ااضروي ",
  "country.GR": "واوفضض ",
  "country.GS": "ايريف اضيواور ااي ورف ضيرضو يضرييووف اوورفضر ",
  "country.GT": "يراررويفو ",
  "country.GU": "افاا ",
  "country.GW": "ضرراايراورضفا ",
  "country.GY": "يضفوفا ",
  "country.HK": "ضفاف ففضا ",
  "country.HM": "فاييو ورايضا فور فافييضرف يروضروا ",
  "country.HN": "ضافضضويو ",
  "country.HR": "ضضاواضو ",
  "country.HT": "فضضاف ",
  "country.HU": "ضوفويرف ",
  "country.ID": "ففضراييوو ",
  "country.IE": "ضريرواف ",
  "country.IL": "ضرضروا ",
  "country.IM": "فضرض ضا واو ",
  "country.IN": "ييراا ",
  "country.IO": "وففيااو فااريا ايافر رياوففويض ",
  "country.IQ": "فضوي ",
  "country.IR": "وفيرا يوففضوا يييرروور ضا ",
  "country.IS": "ضايفاضو ",
  "country.IT": "ووضيا ",
  "country.JE": "ريرواي ",
  "country.JM": "وضفضضفر ",
  "country.JO": "يضضرضي ",
  "country.JP": "فضراي ",
  "country.KE": "فيضوو ",
  "country.KG": "فوفضيروفور ",
  "country.KH": "رضضييافف ",
  "country.KI": "ضفضوضريو ",
  "country.KM": "وضفيييي ",
  "country.KN": "رضضار اضضرض ضيي يريوي ",
  "country.KP": "اضضضاض يياوروضراو وضيررضضف ضايياوفا يا ",
  "country.KR": "ضيوارض فضوواووا را ",
  "country.KW": "فروضاض ",
  "country.KY": "افيضيي ويضافير ",
  "country.KZ": "يرافيايفرا ",
  "country.LA": "ورض ضاوضافيض ييفاييضاري اافارضيي ",
  "country.LB": "رارفريي ",
  "country.LC": "يافوي ييضوا ",
  "country.LI": "روروورييضوضري ",
  "country.LK": "ررض ضيضاا ",
  "country.LR": "ررريااو ",
  "country.LS": "ضوضوويي ",
  "country.LT": "ضايويضوضو ",
  "country.LU": "ويييففااوا ",
  "country.LV": "رفيافر ",
  "country.LY": "ررايف ",
  "country.MA": "ضففضفاا ",
  "country.MC": "ييفاوف ",
  "country.MD": "ضاريفضيف اضضوضراف اا ",
  "country.ME": "ضااويفضضري ",
  "country.MF": "رارضر فووافف (ضااووي يفضف) ",
  "country.MG": "فوضييففضوي ",
  "country.MH": "ررففضرضي ففيضضضو ",
  "country.MK": "فاضييففففف يفي اياضاو ضضيضاراي اضيواااو ور ",
  "country.ML": "فااف ",
  "country.MM": "ضاضروار ",
  "country.MN": "يرفرضضضو ",
  "country.MO": "اضيضو ",
  "country.MP": "ررففيياو ضوررضيي فاريرفف ",
  "country.MQ": "رررواررفيا ",
  "country.MR": "ووفاضضوررض ",
  "country.MS": "ياففيففويا ",
  "country.MT": "ضيوفي ",
  "country.MU": "ريفايضيضض ",
  "country.MV": "يوضضففوا ",
  "country.MW": "يويضاا ",
  "country.MX": "يارفيي ",
  "country.MY": "ضافيروفو ",
  "country.MZ": "اضريفايفيض ",
  "country.NA": "يضيفففر ",
  "country.NC": "يفر ضرفايضواي ",
  "country.NE": "اوففر ",
  "country.NF": "رورففاي يرارير ",
  "country.NG": "وفضرراا ",
  "country.NI": "واوااضيفا ",
  "country.NL": "ورفررريروير ",
  "country.NO": "ضواويي ",
  "country.NP": "ييافف ",
  "country.NR": "ويفضا ",
  "country.NU": "رففو ",
  "country.NZ": "فاي ياضروضا ",
  "country.OM": "يافف ",
  "country.PA": "اوففير ",
  "country.PE": "يضوي ",
  "country.PF": "ياضااف فاضاضفرور ",
  "country.PG": "رفررا فرض واضياي ",
  "country.PH": "رررواايويوف ",
  "country.PK": "اايرضاضا ",
  "country.PL": "يضيارا ",
  "country.PM": "ارضرر يضرواا يرف وويفافوي ",
  "country.PN": "يووراروي ",
  "country.PR": "وضرارض رااي ",
  "country.PS": "ورضيييضيفر ياضاض رض ",
  "country.PT": "رفواوضفو ",
  "country.PW": "افااي ",
  "country.PY": "ايافضرفض ",
  "country.QA": "فياير ",
  "country.RE": "راضيراا ",
  "country.RO": "ضاياضاض ",
  "country.RS": "ضوضاضف ",
  "country.RU": "ريفييار يضوايوويضف ",
  "country.RW": "وفررفض ",
  "country.SA": "اافرض ورضررض ",
  "country.SB": "يضضاضفي ااووراو ",
  "country.SC": "اضويوضاضور ",
  "country.SD": "فضرري ",
  "country.SE": "يورضضي ",
  "country.SG": "رضيارارضو ",
  "country.SH": "ضووفف رايراضو يضررااضاض اوو ضروواوي وي ويضاا ",
  "country.SI": "اوووفوور ",
  "country.SJ": "فاضيضفيو افض افض وييرض ",
  "country.SK": "ضضضفايضض ",
  "country.SL": "ووفاري ضيارو ",
  "country.SM": "رور يضوررف ",
  "country.SN": "ضفضرفير ",
  "country.SO": "فويضوفف ",
  "country.SR": "ااضاوييا ",
  "country.SS": "اوياض واضاض ",
  "country.ST": "ررض فيرض يرض فيووييفا ",
  "country.SV": "ضو ضيروويري ",
  "country.SX": "ااضا وويفواض (اوافف اضار) ",
  "country.SY": "ضضوضضف وواا ضفضييضرض ",
  "country.SZ": "يفوفضوورض ",
  "country.TC": "يااضض فري رووففر وافضيرض ",
  "country.TD": "ورفو ",
  "country.TF": "رااوفا ضضيفوضري وفووضفوفاضف ",
  "country.TG": "اياض ",
  "country.TH": "فيففافري ",
  "country.TJ": "ارضضاراوضر ",
  "country.TK": "يضفوفار ",
  "country.TL": "وضفضضفرضفري ",
  "country.TM": "ريففرواضضضرف ",
  "country.TN": "فضواياي ",
  "country.TO": "رررفف ",
  "country.TR": "ضرفررف ",
  "country.TT": "وووفوارا ريف يوويرف ",
  "country.TV": "ييوااض ",
  "country.TW": "فاافضضا اايرفو ",
  "country.TZ": "يورففضاضر رضروضي يورروفاض يا ",
  "country.UA": "راافضري ",
  "country.UG": "ضضفريو ",
  "country.UM": "اووفضف فففريا ضاضوو فراايفير فاوويرض ",
  "country.US": "وووروا رييففف ",
  "country.UY": "اريضرضر ",
  "country.UZ": "ويورفافرضض ",
  "country.VA": "ييوا ضوي (يفاضضفو وورو رفاري) ",
  "country.VC": "افوير اضارضفو ورا روو ريضروايااو ",
  "country.VE": "ضيايايفضار ررضاااروور افييييوض ضي ",
  "country.VG": "فافرفر يفففرواا اورضوري ",
  "country.VI": "اوفروي ضفاييواا ياار ",
  "country.VN": "ويوا ضضر ",
  "country.VU": "فضررافي ",
  "country.WF": "فضرياا ضرر اااوير ",
  "country.WS": "ضيرفا ",
  "country.YE": "رريرا ",
  "country.YT": "رضوافري ",
  "country.ZA": "ضرريا ضاوفري ",
  "country.ZM": "يضااور ",
  "country.AA": "ضايي اروفضضف ",
  "country.XZ": "رافاويريرضريا يضروضر ",
  "country.QO": "اروفضري ",
  "country.ZZ": "ايفاياض ير ارويففض (وفوا ضفيووضيافو وا فضوف فضض رضرا يااف) ",
  "country.ZW": "ريرياضيض ",
  "country.XK": "اررضوض ",
  "language.aar": "فارر ",
  "language.abk": "اررفاضاضف ",
  "language.ace": "روفويواض ",
  "language.ach": "راضرا ",
  "language.ada": "فيفوضرر ",
  "language.ady": "ضررففر ",
  "language.afa": "اياضيافضووفض ضروفضفيضض ",
  "language.afh": "وافرفااي ",
  "language.afr": "يرااوايفو ",
  "language.ain": "ففير ",
  "language.aka": "ورضي ",
  "language.akk": "فاوضفاوض ",
  "language.ale": "فضففض ",
  "language.alg": "ضضاضوايويف رفرضوضفضر ",
  "language.alt": "يرضفرضرو فضراي ",
  "language.amh": "ياوروور ",
  "language.ang": "ررروييضا ووض (اواراياريوو) ",
  "language.anp": "ضففضور ",
  "language.apa": "رريضري ووايضفضوو ",
  "language.ara": "رييفرض ",
  "language.arc": "اايايضفر ضيورفضي (يضضضفيض وار) ",
  "language.arg": "ضوياضروضف ",
  "language.arn": "اايرفاضيضو ",
  "language.arp": "يوااضاا ",
  "language.art": "فراضافروضر فضيوراياا ",
  "language.arw": "واوويو ",
  "language.asm": "ورروضضير ",
  "language.ast": "فضفريوي ",
  "language.ath": "فيويفضرويو فووييفضاا ",
  "language.aus": "يفرفاضضراض اورافرفرر ",
  "language.ava": "ريضارا ",
  "language.ave": "ورضييفا ",
  "language.awa": "ايفويو ",
  "language.aym": "اوايفر ",
  "language.aze": "ضضيضوافارفو ",
  "language.bad": "وراوي ييرضواافض ",
  "language.bai": "اارففورف ضارريفرضي ",
  "language.bak": "يرضفراو ",
  "language.bal": "ضوفرضاض ",
  "language.bam": "وضااضرا ",
  "language.ban": "رفضافايا ",
  "language.bas": "ررضر ",
  "language.bat": "ايفضفا ييرفاوفرر ",
  "language.bej": "يافر ",
  "language.bel": "وضفوررضييو ",
  "language.bem": "ففضار ",
  "language.ben": "ضروضروو ",
  "language.ber": "ضضوراف ايوورروفض ",
  "language.bho": "ااوضاضيا ",
  "language.bih": "يروضاي ااايوضفوا ",
  "language.bik": "ضاااو ",
  "language.bin": "راف ",
  "language.bis": "وفضفريا ",
  "language.bla": "ااضفيفض ",
  "language.bnt": "وريفو يررضراررض ",
  "language.bod": "فيراضضر ",
  "language.bos": "ايفرراف ",
  "language.bra": "وضضي ",
  "language.bre": "ويررضف ",
  "language.btk": "ووروض ضافافضايي ",
  "language.bua": "وفووفي ",
  "language.bug": "ايفارواف ",
  "language.bul": "فافففيافا ",
  "language.byn": "ياضا ",
  "language.cad": "يفيرو ",
  "language.cai": "رررريور يوضيوففف ياضفرض رراوضضضفف ",
  "language.car": "ويافوو فيافر ",
  "language.cat": "رضفضاضورفضووضفييض ",
  "language.cau": "ضوفيويوور اافضررفور ",
  "language.ceb": "فياضفيض ",
  "language.cel": "واررور ضفييفضراا ",
  "language.ces": "اضيضا ",
  "language.cha": "رضاييوضر ",
  "language.chb": "ايوايرض ",
  "language.che": "رراايرف ",
  "language.chg": "ففضروفاي ",
  "language.chk": "واوراضوا ",
  "language.chm": "رضرو ",
  "language.chn": "واريوضي اففاري ",
  "language.cho": "يفاضورف ",
  "language.chp": "ووفض ووفررو ",
  "language.chr": "وفضضاريا ",
  "language.chu": "فضا ريورففاو ",
  "language.chv": "رفروضيو ",
  "language.chy": "وايواييي ",
  "language.cmc": "اضاايف وايريويار ",
  "language.cop": "وووضفو ",
  "language.cor": "ضضويارف ",
  "language.cos": "ضضاوروفر ",
  "language.cpe": "رضووفاو ايو وياضيفور ضرفوفضرففيويف ",
  "language.cpf": "ضافافرف افو ضفيضفاضا ضوضوففرفاااا ",
  "language.cpp": "فيوضويي روا فيفروفضف افوفاففوييوفافرف ",
  "language.cre": "ضضفض ",
  "language.crh": "اييفضفي فضايضرر ",
  "language.crp": "فوفضفيو اار ضريرييي ",
  "language.csb": "يافضروياا ",
  "language.cus": "فوضفويرو وفريووفضف ",
  "language.cym": "ورفاي ",
  "language.dak": "فيراار ",
  "language.dan": "ارفضفف ",
  "language.dar": "ارفيضا ",
  "language.day": "ضووو رافيي رضااويوور ",
  "language.del": "فضاييضيف ",
  "language.den": "ضاوار (فضيضضوضيفف) ",
  "language.deu": "رضضيوض ",
  "language.dgr": "رضيرفي ",
  "language.din": "وواضو ",
  "language.div": "وواايضرضا ",
  "language.doi": "ارفوي ",
  "language.dra": "يفرفريافف وفضارفياا ",
  "language.dsb": "ويواف واففاوو ",
  "language.dua": "يرضرر ",
  "language.dum": "اروروو يرريار (وييضفضيضوضور) ",
  "language.dyu": "فااضا ",
  "language.dzo": "فضايرافف ",
  "language.efi": "اياف ",
  "language.egy": "ووارضفيض (فرااياا) ",
  "language.eka": "روفضاا ",
  "language.ell": "رضضضرض وررضفا (ووفوا) ",
  "language.elx": "ايراييو ",
  "language.eng": "فضورييا ",
  "language.enm": "واراياوض ضضاررو (اريووضايي) ",
  "language.epo": "رفويففيفر ",
  "language.est": "اففروررا ",
  "language.eus": "يرييور ",
  "language.ewe": "يار ",
  "language.ewo": "ارفررف ",
  "language.fan": "وفرض ",
  "language.fao": "فريففرف ",
  "language.fas": "رففارير ",
  "language.fat": "فيفيا ",
  "language.fij": "اريفيض ",
  "language.fil": "فوضراففا ",
  "language.fin": "ريوضاوو ",
  "language.fiu": "ضضيايفافضيوو اريوافييف ",
  "language.fon": "راض ",
  "language.fra": "ايفياي ",
  "language.frm": "واييواا وضيووف (فويرارفضضايي) ",
  "language.fro": "فضوووضو يوا (ياررورفيضرر) ",
  "language.frr": "ففاضااير فاياروض ",
  "language.frs": "ضرااافف اافايضا ",
  "language.fry": "ضفوييرف فويوريي ",
  "language.ful": "ويويض ",
  "language.fur": "رررضيضرو ",
  "language.gaa": "او ",
  "language.gay": "ياوض ",
  "language.gba": "رفيور ",
  "language.gem": "يرفووفرر ررفضروورا ",
  "language.gez": "ففاي ",
  "language.gil": "رريوفرفضاو ",
  "language.gla": "ياضفرضاي يراضاو ",
  "language.gle": "ضوففر ",
  "language.glg": "يوفاووري ",
  "language.glv": "وووي ",
  "language.gmh": "وراوففف فوروضف رفيي (يياضفوضويوفو) ",
  "language.goh": "وروضفار اضر وايض (ييفاورضوففي) ",
  "language.gon": "يرفيض ",
  "language.gor": "اضفوواريا ",
  "language.got": "فضفاار ",
  "language.grb": "فرييو ",
  "language.grc": "اضفضيف راويضفو (ضو رضضض) ",
  "language.grn": "ووفاافض ",
  "language.gsw": "اففضر واراوف ",
  "language.guj": "واررضيضض ",
  "language.gwi": "فرويفريض ",
  "language.hai": "رضفاي ",
  "language.hat": "اضوايضا فراارر ",
  "language.hau": "وضياف ",
  "language.haw": "اضفيرريا ",
  "language.heb": "اواارض ",
  "language.her": "ايضررا ",
  "language.hil": "وفراضضييرف ",
  "language.him": "ررفضفضو ويريير يوفضرفرفو ",
  "language.hin": "واضير ",
  "language.hit": "يوضريفا ",
  "language.hmn": "وياض ",
  "language.hmo": "اضرر ضوضو ",
  "language.hrv": "فوضوفاضض ",
  "language.hsb": "راوير وفراووي ",
  "language.hun": "اضاييافير ",
  "language.hup": "ااوو ",
  "language.hye": "اايضففوا ",
  "language.iba": "ووار ",
  "language.ibo": "يويي ",
  "language.ido": "وفض ",
  "language.iii": "افرايضر ري ",
  "language.ijo": "يوا فراووارري ",
  "language.iku": "رضيافاورف ",
  "language.ile": "ضيوففووفرف ",
  "language.ilo": "ففضفا ",
  "language.ina": "رفررايفضوري (فيريورافضاضرر ررررفرضيض ييوايرفض روضفيضضيضرض) ",
  "language.inc": "افورف وويويضفضض ",
  "language.ind": "رضفااروضيي ",
  "language.ine": "افااضيضوفضراا وفاففيرفي ",
  "language.inh": "ضيضرير ",
  "language.ipk": "ضوواييا ",
  "language.ira": "يضويضاو اياافرييض ",
  "language.iro": "فضضووففيو ففضويواضف ",
  "language.isl": "ايوضضضضرف ",
  "language.ita": "ففرضرضر ",
  "language.jav": "ضيفييضفي ",
  "language.jbo": "ياوافف ",
  "language.jpn": "اورضوايا ",
  "language.jpr": "رضفوايويفاضفر ",
  "language.jrb": "فااااوضضاااف ",
  "language.kaa": "ضففاييففضوو ",
  "language.kab": "يضوراف ",
  "language.kac": "فرضوضر ",
  "language.kal": "واايرفياضاا ",
  "language.kam": "فرييو ",
  "language.kan": "ضضوفيوف ",
  "language.kar": "رفواا فضوففروري ",
  "language.kas": "ورريارفو ",
  "language.kat": "ارواييوا ",
  "language.kau": "ارااير ",
  "language.kaw": "ففضا ",
  "language.kaz": "ياااضر ",
  "language.kbd": "راضوياريض ",
  "language.kha": "فررفف ",
  "language.khi": "فروارضا فووفضضوفر ",
  "language.khm": "اضفضيفض ففاور ",
  "language.kho": "ضايرو ",
  "language.kik": "وافيوا ",
  "language.kin": "رييرفففضييض ",
  "language.kir": "اضضياض ",
  "language.kmb": "ضييااضاي ",
  "language.kok": "وضضواري ",
  "language.kom": "فيضض ",
  "language.kon": "واريي ",
  "language.kor": "راضاضف ",
  "language.kos": "ضورراضيض ",
  "language.kpe": "اضوورض ",
  "language.krc": "ضرضيووووفووفررض ",
  "language.krl": "رفضفارار ",
  "language.kro": "وضي ففضوضفوضي ",
  "language.kru": "يضارفا ",
  "language.kua": "افرفضوفض ",
  "language.kum": "يااضا ",
  "language.kur": "فروضارا ",
  "language.kut": "يافيفضا ",
  "language.lad": "ايضرضي ",
  "language.lah": "ضاوااض ",
  "language.lam": "فوفار ",
  "language.lao": "فاف ",
  "language.lat": "اضيفر ",
  "language.lav": "ييضفارا ",
  "language.lez": "اوارييوي ",
  "language.lim": "يرفضفررااا ",
  "language.lin": "راففويو ",
  "language.lit": "ررارروضيضا ",
  "language.lol": "فاووف ",
  "language.loz": "وروض ",
  "language.ltz": "ضرييااففاريوف ",
  "language.lua": "وويرااضفرا ",
  "language.lub": "افاواضرايضرو ",
  "language.lug": "فففرا ",
  "language.lui": "ررضوارف ",
  "language.lun": "ووضوا ",
  "language.luo": "فيف (رراضض فور اضوفووضر) ",
  "language.lus": "يضفويو ",
  "language.mad": "اويافاوا ",
  "language.mag": "رفضاوض ",
  "language.mah": "ايريروييفيض ",
  "language.mai": "فويفوورو ",
  "language.mak": "يارورور ",
  "language.mal": "ضررضاراضر ",
  "language.man": "يرضوايضي ",
  "language.map": "افيوضفوفرافو اضيفرففرا ",
  "language.mar": "رروايوض ",
  "language.mas": "يففري ",
  "language.mdf": "يييرفي ",
  "language.mdr": "يضييفي ",
  "language.men": "افوفا ",
  "language.mga": "فففيرر ويرورر (وررفااضف) ",
  "language.mic": "فارارر ",
  "language.min": "فاففففضاضوف ",
  "language.mis": "رضافففي ايفراويار ",
  "language.mkd": "ويفووفيواا ",
  "language.mkh": "يويفورفاو ضررايروفو ",
  "language.mlg": "ااضووويو ",
  "language.mlt": "يرووفاي ",
  "language.mnc": "روافاض ",
  "language.mni": "ضفييررفر ",
  "language.mno": "رضافرا يففيواضرض ",
  "language.moh": "فريفري ",
  "language.mol": "وووييافضو ",
  "language.mon": "وضفيارفوو ",
  "language.mos": "يضرري ",
  "language.mot": "يضيرفضضفويو ",
  "language.mri": "فافضر ",
  "language.msa": "اضيضض ",
  "language.mul": "ضاضاورفا وروريضيرض ",
  "language.mun": "يافيو يرفيضرياو ",
  "language.mus": "ضررضو ",
  "language.mwl": "فيورواضوض ",
  "language.mwr": "ويروارر ",
  "language.mya": "ياوضواض ",
  "language.myn": "ويفيا وضايررووي ",
  "language.myv": "رفييف ",
  "language.nah": "يفاضضضي ضوواووايي ",
  "language.nai": "يضضوف فوفارفور ضضضرير وفياضيياض ",
  "language.nap": "وففرافضرير ",
  "language.nau": "ضووري ",
  "language.nav": "اروضيا ",
  "language.nbl": "وفايا اافضيضي ",
  "language.nde": "يضاوض يرروييي ",
  "language.ndo": "فرفضرر ",
  "language.nds": "ضفارفض ااو ",
  "language.nep": "فضوايي ",
  "language.new": "اضفافض ",
  "language.nia": "اففف ",
  "language.nic": "ررييرويضرروويضرضا ايايفرراض ",
  "language.niu": "ااضضفي ",
  "language.nld": "روييض ",
  "language.nno": "فيروررور فوفيايضير ",
  "language.nob": "ضضارففرير ضروفوو ",
  "language.nog": "فضفضف ",
  "language.non": "يرضفير وري ",
  "language.nor": "يويضفضففر ",
  "language.nqo": "ففوف ",
  "language.nso": "فووراض ضيفيفضرف ",
  "language.nub": "ضويرفي اوفيافررر ",
  "language.nwc": "وضو ضرفرفو ",
  "language.nya": "رروففر ",
  "language.nym": "يوواضاضي ",
  "language.nyn": "اييورفضض ",
  "language.nyo": "يفايا ",
  "language.nzi": "رضاوي ",
  "language.oci": "وضضوريض (وفضر فوير) ",
  "language.oji": "ررضرفر ",
  "language.ori": "اارفا ",
  "language.orm": "يراور ",
  "language.osa": "وااري ",
  "language.oss": "ايواضوي ",
  "language.ota": "يوافيرضي اريضفاي (فضفيفورار) ",
  "language.oto": "يضوفاوف يوريريروض ",
  "language.paa": "يااررا ويوريفووا ",
  "language.pag": "ضووضفياوير ",
  "language.pal": "فيااضيو ",
  "language.pam": "روفوضايو ",
  "language.pan": "اااوضيو ",
  "language.pap": "ورايوايافر ",
  "language.pau": "اوافييي ",
  "language.peo": "اضفوضويا يور (رضراوررفضي ضياض) ",
  "language.phi": "ويضفوضيفاي واويايوضي ",
  "language.phn": "ررضياروووي ",
  "language.pli": "ررفر ",
  "language.pol": "ضرافيو ",
  "language.pon": "رضوووفيير ",
  "language.por": "ضيوضضفيفضو ",
  "language.pra": "يفيوويف فايورووضي ",
  "language.pro": "ضفارريفواا فاض (ضف ضياف) ",
  "language.pus": "ياضيوا ",
  "language.que": "رفايفير ",
  "language.raj": "وايضيضضيوو ",
  "language.rap": "رضيضييو ",
  "language.rar": "ضيفراضضييو ",
  "language.roa": "رفراروو ررضضيضضاي ",
  "language.roh": "ضضروضضف ",
  "language.rom": "ففووضي ",
  "language.ron": "فضيففيفف ",
  "language.run": "ضضووو ",
  "language.rup": "فوضيفريررضاضايف ",
  "language.rus": "يضويييف ",
  "language.sad": "ضففوااا ",
  "language.sag": "رروفر ",
  "language.sah": "وررضف ",
  "language.sai": "ضضضاض اوفييرضي وايااو واففوافضف ",
  "language.sal": "ضويارفضض ارريفيضير ",
  "language.sam": "وففاوواضي فضففوضر ",
  "language.san": "وايفيورف ",
  "language.sas": "روروا ",
  "language.sat": "رييوفرر ",
  "language.scn": "وروفففضي ",
  "language.sco": "وضيوو ",
  "language.sel": "اووفرا ",
  "language.sem": "وروفيضر وروفضاريض ",
  "language.sga": "فرايوو فاو (وا ضضا) ",
  "language.sgn": "ويور ويففوراار ",
  "language.shn": "يضور ",
  "language.sid": "اواوضو ",
  "language.sin": "ضاوضرضيفض ",
  "language.sio": "ضيفواو رررفياروا ",
  "language.sit": "افافياريورفي يورففضاري ",
  "language.sla": "فرضريي ففضفويووي ",
  "language.slk": "اارريو ",
  "language.slv": "ايوفوفيضض ",
  "language.sma": "رضضييياو ضفاف ",
  "language.sme": "وارضوواف ضيضض ",
  "language.smi": "راضر ضريضضرويض ",
  "language.smj": "وضاف فورو ",
  "language.smn": "ااافر يضوو ",
  "language.smo": "ضياوفو ",
  "language.sms": "ياورا رفاو ",
  "language.sna": "رضفرا ",
  "language.snd": "ررضيضو ",
  "language.snk": "رروضفور ",
  "language.sog": "رفيوفضو ",
  "language.som": "ضفوضضر ",
  "language.son": "اضيفضفر ضضاووروفو ",
  "language.sot": "ويفيفي روفروفيو ",
  "language.spa": "ضفضضفاا ",
  "language.sqi": "ايضويارا ",
  "language.srd": "ويياافضضي ",
  "language.srn": "روييضو اواوا ",
  "language.srp": "ضايايوي ",
  "language.srr": "فرفاف ",
  "language.ssa": "يوضاواروويرا ضضوررريوض ",
  "language.ssw": "رضووي ",
  "language.suk": "افاافف ",
  "language.sun": "افضفراارض ",
  "language.sus": "ضيير ",
  "language.sux": "ضايضضفار ",
  "language.swa": "وررروفر ",
  "language.swe": "ووريووف ",
  "language.syc": "يرارضرفاض روضيفف ",
  "language.syr": "ضفييري ",
  "language.tah": "اوضيوورر ",
  "language.tai": "يضا ضافيوضرفي ",
  "language.tam": "ارررر ",
  "language.tat": "ايوري ",
  "language.tel": "رافروا ",
  "language.tem": "ياارو ",
  "language.ter": "وضاضاو ",
  "language.tet": "ضضااا ",
  "language.tgk": "رايفو ",
  "language.tgl": "ضياضاوف ",
  "language.tha": "يافض ",
  "language.tig": "ضرضضف ",
  "language.tir": "ريريضيوو ",
  "language.tiv": "يري ",
  "language.tkl": "ورراررف ",
  "language.tlh": "واافراوففيير ",
  "language.tli": "فيويافض ",
  "language.tmh": "ويوفرفيا ",
  "language.tog": "فضورا (فرضضف) ",
  "language.ton": "ضرفاي (فيورف ضريففضو) ",
  "language.tpi": "اير رضفوض ",
  "language.tsi": "ررضفويضيا ",
  "language.tsn": "ضواوفي ",
  "language.tso": "ضفورري ",
  "language.tuk": "وففرورا ",
  "language.tum": "رففواار ",
  "language.tup": "وااو ضياوففايض ",
  "language.tur": "يياوايض ",
  "language.tut": "ييفررا فررورايوي ",
  "language.tvl": "رفوضوض ",
  "language.twi": "ففض ",
  "language.tyv": "اوضرضرضو ",
  "language.udm": "ويوورف ",
  "language.uga": "رافرييري ",
  "language.uig": "ضضفضوض ",
  "language.ukr": "يرضارضافو ",
  "language.umb": "وايضووي ",
  "language.und": "وضض يريضفوافر ",
  "language.urd": "ويفض ",
  "language.uzb": "اضفوو ",
  "language.vai": "فيض ",
  "language.ven": "ييوضا ",
  "language.vie": "وضاريروضرض ",
  "language.vol": "اضراريا ",
  "language.vot": "فففضي ",
  "language.wak": "فياوفارو افييوضوضا ",
  "language.wal": "روفيففضر ",
  "language.war": "وايفف ",
  "language.was": "ياضفو ",
  "language.wen": "ريراوفف فااواضفير ",
  "language.wln": "رياضووي ",
  "language.wol": "وضوير ",
  "language.xal": "ايرضض ",
  "language.xho": "ويضاض ",
  "language.yao": "يوف ",
  "language.yap": "رويرضر ",
  "language.yid": "ضااررفي ",
  "language.yor": "افففاض ",
  "language.ypk": "يووار ويراراورا ",
  "language.zap": "اوضيايا ",
  "language.zbl": "رياففاضيوار ",
  "language.zen": "ضيافيف ",
  "language.zgh": "فويارياض ييويضفضي اضضرراورر ",
  "language.zha": "فضضوضض ",
  "language.zho": "يفررروا ",
  "language.znd": "يوياض وضضففوفرف ",
  "language.zul": "فرفض ",
  "language.zun": "ورضف ",
  "language.zxx": "وار ضفرففرضفاف ",
  "language.zza": "فيايوي ",
  "crawl.finishReason.NORMAL": "فوففاي ",
  "crawl.finishReason.ABORT": "ووضوف ",
  "crawl.finishReason.NOT_MODIFIED": "ضوو اوضضروفف ",
  "crawlAttemptX": "[[[!Crawl attempt {attemptNr}!]]]",
  "contactType.TECHNICAL_POINT_OF_CONTACT": "فضضيووياو ضافيف يض فووااضي ",
  "contactType.ADMINISTRATIVE_POINT_OF_CONTACT": "يرورضواورافروض فوووف يا فرضيروا ",
  "contactType.POINT_OF_CONTACT": "فاييض رف يضوييفض ",
  "contactType.ORIGINATOR": "رفاايضفريو ",
  "contactType.METADATA_AUTHOR": "روفضيفوا ياضرضف ",
  "contactType.PRINCIPAL_INVESTIGATOR": "ياوفيضضيا ضضضييرفورضضي ",
  "contactType.AUTHOR": "اففضيض ",
  "contactType.CONTENT_PROVIDER": "اايفضير يفيوضاضر ",
  "contactType.CUSTODIAN_STEWARD": "ضرفضفاريو ورورويو ",
  "contactType.DISTRIBUTOR": "ضيفففضفروور ",
  "contactType.EDITOR": "ااييضو ",
  "contactType.OWNER": "رويفي ",
  "contactType.PROCESSOR": "رايفاففضي ",
  "contactType.PUBLISHER": "ضيفضوفوفف ",
  "contactType.USER": "فرضي ",
  "contactType.PROGRAMMER": "فيييضاريري ",
  "contactType.CURATOR": "ييفضروا ",
  "contactType.DATA_ADMINISTRATOR": "ضررا ارضفرفففيوفاو ",
  "contactType.SYSTEM_ADMINISTRATOR": "فرراوض اففريايرورااف ",
  "contactType.TEMPORARY_HEAD_OF_DELEGATION": "فافضفضرضر ااضض رر يضضيويضوضف ",
  "contactType.TEMPORARY_DELEGATE": "واضافضضفر رافضايير ",
  "contactType.REGIONAL_NODE_REPRESENTATIVE": "ووفضرضضا ييرف ضويرويويوييررض ",
  "contactType.NODE_STAFF": "رفضض فضضفي ",
  "contactType.HEAD_OF_DELEGATION": "ضضضو را وفوفضرفاوا ",
  "contactType.NODE_MANAGER": "فضضا فارضيرض ",
  "contactType.ADDITIONAL_DELEGATE": "اراريافضاض ضفروفااو ",
  "details": "اضريفوو ",
  "contactDetails": "فيضوضاي وضضاضوي ",
  "commentDetails": "ضاياوفض وفاويفا ",
  "endpointDetails": "افرضورير ووضاضاو ",
  "identifierDetails": "ضايرضضرفوي فيضفروي ",
  "machineTagDetails": "يوفضوير رضر فيايرري ",
  "tagDetails": "يضف ويفواوا ",
  "newTag": "فاا راو ",
  "newAddress": "ااي وفوضووو ",
  "newEmail": "ارا اضفرر ",
  "newPhone": "يرر اوواا ",
  "newHomepage": "ويي ضضفارورف ",
  "newUserId": "ويي ريرر رف ",
  "newPosition": "ضفض ضضياوضضا ",
  "datasetType.OCCURRENCE": "راضرفاوضيو ",
  "datasetType.CHECKLIST": "اييفيويير ",
  "datasetType.SAMPLING_EVENT": "روريضيوو وايوي ",
  "datasetType.METADATA": "يوفضفااي ",
  "constituentsDatasets": "واضريفضيييا ريراياضي ",
  "error.message": "ويياا ",
  "error.description": "يي ررويي اافوااوو يضضيا ضفاااي اض فيضفااي فايض رضااوارو يضفررف ااضرضو فور ريرير يي ضضضفورضريضضووووضفرايضضفيفوضفواضضفضرااررفضضااوفيويا ",
  "error.contact.duplicate": "يري فوواا ضفف فيو راضا فاوورار رافرا ",
  "datasetConstituent": "اففضراييافض ايفوواضض ",
  "doi": "ضاررررض ررضففو رفراضوفييف ",
  "alias": "ضرضرف ",
  "publishingOrganization": "فضيروفرفضض وضروفيفواضيف ",
  "servingInstallation": "اوررارض ااااوفوفااار ",
  "citation": "وايايضير ",
  "rights": "فضاواي ",
  "updateFrequency": "ضوضضار يارضفاييض ",
  "subtype": "رفيوفضو ",
  "external": "رفرضييوا ",
  "license": "يااويرض ",
  "important": "افضفوايار ",
  "warning.datasetLicense": "يفووضويو وضرر يييض ارففور وور اريفافوييا يوويضار ",
  "warning.datasetAutoUpdate": "ففف راضر اواييور ي اضففضارض اضرفرضضاف ضفياارو ",
  "warning.datasetDOI": "رضاففاي رارففو رف اافي وراضافضافويفف ضوا ضياضضضفضفايو ",
  "warning.publishingOrganization": "يااييففا افرا فورض ايوضضف فوووروف فاياضوااضويي يو ضاا اروضيويضضر رووضورفر ",
  "warning.hostingOrganization": "اورافيضر يففو وفاي واففير ياواررو واروفروراررو را فضض افاارورروو ضريوففرا ",
  "warning.duplicateDataset": "اففضوريف رففض يافا وضضروا ااا يرضاضيضووا ضفضوفيف ",
  "warning.installationType": "راض يووفرفرررفو روضضيي او واايايرر ",
  "warning.endorsingNode": "اير فايي يوفي يور ضضوروووي ضرر فوياورريففار ضيضاوف روفياضض اضاضيرو ريضي ",
  "warning.endorsementApproved": "يفض وضر ضايضيروفرفي واوض يياراوووف ",
  "lockAutoUpdates": "ارضي وررر فضاوفور ",
  "installation": "ضفوارووفياضي ",
  "parentDataset": "روضرضي رويفاضي ",
  "duplicateDataset": "ففويرواري رو ضفضيضفا ",
  "citationIdentifier": "افيضافاا رضضرضياارو ",
  "yes": "ضوض ",
  "no": "اف ",
  "beenDeleted.contact": "وضاضفاو ريف ففوي ضريااري ",
  "beenDeleted.comment": "رضاواضا وضو ياضف يفوضافض ",
  "beenDeleted.endpoint": "اووووواي ريف ورفي فيافييي ",
  "beenDeleted.identifier": "فوويفيييضو رفض اوضي رريفرضر ",
  "beenDeleted.machineTag": "يوييففض رار يرا ررضا اووفضوو ",
  "beenDeleted.tag": "وفف وار رويف فااااضي ",
  "beenSaved.contact": "ضيرفورر ارض روضف ااووض ",
  "beenSaved.comment": "ضافورضا يفر وويا فرضرو ",
  "beenSaved.endpoint": "ضضريرررر ررو يررر ففضاي ",
  "beenSaved.identifier": "وايويارفرض رفف ويري اضضرر ",
  "beenSaved.machineTag": "ويوفاضا ضفو رور واوو افيوي ",
  "beenSaved.tag": "وفو يوا وووو ضريفا ",
  "installationType.BIOCASE_INSTALLATION": "يفيرويو ",
  "installationType.TAPIR_INSTALLATION": "وفاوض ",
  "installationType.HTTP_INSTALLATION": "ففاي ",
  "installationType.IPT_INSTALLATION": "راا ",
  "installationType.DIGIR_INSTALLATION": "ضاورض ",
  "installationType.SYMBIOTA_INSTALLATION": "يوواييرا ",
  "servedDatasets": "راضففا ااريروير ",
  "crawlHistory": "فضويضروفا ففوفريف ",
  "synchronizationHistory": "راراففوريضيضوضر وضاففير ",
  "synchronizeNow": "ضفرارفررررض ضور ",
  "synchronize": "ررررررررافا ",
  "installationOverviewInfo": "اضيو يفرياافاضيف ضيفيررض رو يضض رييفراوايففا ريروضفوو وضايوفرريفري ضفيضفف افيرضف وضياياضا ياض ارضرفضض ",
  "installationType": "يورافروراضوض ضرفو ",
  "disabled": "ضيوايايض ",
  "pendingEndorsements": "ضضيفايض ضرياااراوييض ",
  "endorsedOrganizations": "فضروضررف اضفايرفضوويفي ",
  "endorsedDatasets": "ريفااويو وافيوااو ",
  "participantStatus": "ياضاضفييوضو ريضياف ",
  "gbifRegion": "رضاا فياضضي ",
  "continent": "فايوففايض ",
  "participationStatus": "افافيفااووراي اضضفضا ",
  "nodeType.COUNTRY": "فيارفيف ",
  "nodeType.OTHER": "ضواضر ",
  "participationStatus.VOTING": "يفرضضي ",
  "participationStatus.ASSOCIATE": "افضوضيضضا ",
  "participationStatus.OBSERVER": "فرضفريفر ",
  "participationStatus.FORMER": "وضيفضر ",
  "participationStatus.AFFILIATE": "ضفوفضفضوض ",
  "region.AFRICA": "اضفواا ",
  "region.ASIA": "ويور ",
  "region.EUROPE": "رفارفا ",
  "region.NORTH_AMERICA": "وفايا يرافريض ",
  "region.OCEANIA": "ضضوييرف ",
  "region.LATIN_AMERICA": "ووياي ضييضرار ",
  "region.ANTARCTICA": "ويوورافرضو ",
  "continent.AFRICA": "يورضرض ",
  "continent.ASIA": "فضرر ",
  "continent.EUROPE": "وورريو ",
  "continent.NORTH_AMERICA": "اويفض ييضرورا ",
  "continent.OCEANIA": "يرضرررض ",
  "continent.SOUTH_AMERICA": "ففضاا فرووضفض ",
  "continent.ANTARCTICA": "فيرييفضافو ",
  "exception.description.403": "ضفافير واض ضيوفو يايض اايفضا ضف ييفر ارضفي ",
  "exception.description.404": "اياففف فضف يضوو روض فوويفيف ييوا فوف وراواف ",
  "exception.description.500": "راووضض ضفر اارروو رر وفضايفوضض ضا اورياو ",
  "exception.description.523": "ضضوورا ضفي يرضرفض ري ااضففرييفروو ففيفويوف ضفض وضض ضرضورااا ",
  "exception.back": "روضض فر فرضضيفاير ",
  "invalid.email": "رضرفوي اف ويووضضا ",
  "invalid.phone": "ضفافف رض اوااففو ",
  "invalid.homepage": "رريااووو فو ضرارورو ",
  "invalid.url": "يوي فا ضاايضرو ",
  "invalid.url.logo": "فيضف ياف ار ريرضرفض ",
  "invalid.credentials": "رفاوراا ضفيواضفي يف فضضارااض ",
  "invalid.doi": "ضريضفاض يرياار ضففوياورضر ضض يوضويفر ",
  "invalid.postalCode": "ضيييري ضرفض وو فرررضوض ",
  "error.title": "اض ارورو اافففاوض ",
  "organizations": "ضاضاراضفوفريف ",
  "datasets": "فررراااي ",
  "nodes": "يارضا ",
  "users": "ضضرضا ",
  "newOrganization": "ييو ورفيضففرررفر ",
  "newDataset": "ضفف وريفاير ",
  "newInstallation": "ففي رفريااااففوف ",
  "user": "وففض ",
  "lastLogin": "فياي ففيرر ",
  "settings": "اافضيضيو ",
  "systemSettings": "يوافوض ااووايرف ",
  "roles": "وييفي ",
  "success": "فيوارفو ",
  "error": "ضوريي ",
  "endorsed.crawl.message": "رفضف ررري ارارضوا ض فوييو رف اضف فوضفيييي ",
  "notEndorsed.crawl.message": "رضرض فيفاريارر ريضيريايوض رافوويفضاضرض ضو اوو ففضاروضي اضري ضرفر ضورف فضييوفر ر ياضضو رو ضرف اريرفروي ضاض ييففار اضاا اض رييا ضي و ضضايور وضافففضفيرر ",
  "info.crawling": "ورضيرفوف ار ضضرضضضوض ",
  "info.synchronizing": "ضورضييااروضيففا ير ضوفضرضيف ",
  "installation.sync.message": "وضاف يوضر فافرورا ض فيوررورفرواووفي ار وفا فضاضيوييضووضو ",
  "duplicate": "اايويرويا ",
  "constituent": "فواوافوويوا ",
  "withNoEndpoint": "ضفضض وا ضضارضرفا ",
  "institutions": "رضفيفيويضيضض ",
  "persons": "فرضاوفض ",
  "collections": "فايفضروفوفو ",
  "editContact": "افار ف فيرفاوو ",
  "newCollection": "يرض ضفوضرييفور ",
  "accessionStatus": "ضريفيايير ايرايا ",
  "active": "فويرفف ",
  "code": "ففيا ",
  "newInstitution": "واف روفرووريضفا ",
  "indexHerbariorumRecord": "وفففرضيريوي ضضويضا ",
  "institutionalGovernance": "فواضافافويوفو ضرضضضاايرا ",
  "catalogUrl": "ضرفياضو فرا ",
  "details.organization": "يفضريضفاوورض يوافضيف ",
  "details.dataset": "يفييواا فيففورر ",
  "details.installation": "يروفاوفويضور يوفيياف ",
  "details.user": "ضفوو فاضويضا ",
  "details.node": "وييي وفضرييو ",
  "details.collection": "فيرافرايير ووييفار ",
  "details.person": "يضيفاو فضففايو ",
  "details.institution": "يفضفرواياار ررضرفضر ",
  "details.contact": "ضفاايير واواااف ",
  "nResults": "[[[!{formattedNumber} {count, plural, zero {results} one {result} other {results}}!]]]",
  "forQuery": "[[[! for '{query}'!]]]",
  "ok": "ضا ",
  "close": "فاييو ",
  "viewOnGBIF": "رايي وف ضييفافار ",
  "noInformation": "وي وفوروفضيضاو ",
  "button.showMore": "ضييا يريي ",
  "button.showLess": "يوور رفيو ",
  "personalCollection": "فويفويفف اايارضاررا ",
  "accessionStatus.INSTITUTIONAL": "فروييوراارضفر ",
  "accessionStatus.PROJECT": "ررااريا ",
  "preservationType.NO_TREATMENT": "يا يفييضضضرر ",
  "preservationType.ALCOHOL": "رارررضف ",
  "preservationType.DEEP_FROZEN": "اضضي رروفوض ",
  "preservationType.DRIED": "يضااف ",
  "preservationType.DRIED_AND_PRESSED": "افااا رفر يايوضفض ",
  "preservationType.FORMALIN": "ييضوضفضض ",
  "preservationType.REFRIGERATED": "يااواريضويرض ",
  "preservationType.FREEZE_DRIED": "فففوضي اروفض ",
  "preservationType.GLYCERIN": "رايافووي ",
  "preservationType.GUM_ARABIC": "اضر ضوفاضض ",
  "preservationType.MICROSCOPIC_PREPARATION": "فففوففريوفو يرياففايروو ",
  "preservationType.MOUNTED": "فوضاضفي ",
  "preservationType.PINNED": "ضافوار ",
  "preservationType.OTHER": "رفووف ",
  "preservationType": "وفييرووواافض فضرو ",
  "apiUrl": "ارو افو ",
  "collectionContentType.ARCHAEOLOGICAL_OTHER": "وفرارضفررضوفري ض اراوف ",
  "collectionContentType.ARCHAEOLOGICAL_HUMAN_REMAINS": "ضيضارضففررففضض ف رضورا ررفريرا ",
  "collectionContentType.ARCHAEOLOGICAL_FAUNAL_REMAINS": "رافياوريوفوضضف ض رورايض وضفويوف ",
  "collectionContentType.ARCHAEOLOGICAL_FLORAL_REMAINS": "يرويضورراضرررض ض ففضوضف ارضفضضا ",
  "collectionContentType.ARCHAEOLOGICAL_C14": "ووييوياويرفرفف ف يفا ",
  "collectionContentType.ARCHAEOLOGICAL_COPROLITES": "وفرررضففورافاف ض ففففوففففر ",
  "collectionContentType.ARCHAEOLOGICAL_CERAMIC_ARTIFACTS": "يويضفريضفيضويي ض ايفرافف ورارضضوضي ",
  "collectionContentType.ARCHAEOLOGICAL_FAUNAL_ARTIFACTS": "اضفضروييفااياا ف ضفوريا يرايرضضري ",
  "collectionContentType.ARCHAEOLOGICAL_FLORAL_ARTIFACTS": "ضااوفرضففوضوري ي وفافضي فيايضفررا ",
  "collectionContentType.ARCHAEOLOGICAL_LITHIC_ARTIFACTS": "فيويضضيرروفضير و ضوافرر ايفيييضضض ",
  "collectionContentType.ARCHAEOLOGICAL_METAL_ARTIFACTS": "ريييروفضرفويفو ا ضيفيو ضضفيراووي ",
  "collectionContentType.ARCHAEOLOGICAL_TEXTILES_BASKETRY": "ضفويرروفيريويا ض يوضارففا ارضضضضوف ",
  "collectionContentType.ARCHAEOLOGICAL_TECHONOLOGICAL_PROCESSES_REMAINS": "ريفضرفيرفضييوي و يرضيففرييويفضض راافضافيا افاوواي ",
  "collectionContentType.ARCHAEOLOGICA_WOODEN_ARTIFACTS": "فويييفوضفاضفضا ر رويورر ضضضاضيورف ",
  "collectionContentType.ARCHAEOLOGICAL_WOODEN_ARTIFACTS": "ضوريرفوفافواضي ا فرااير واضرراضاو ",
  "collectionContentType.BIOLOGICAL_OTHER": "اضوفااويفو ض ضضيوا ",
  "collectionContentType.BIOLOGICAL_LIVING_ORGANISMS": "ييرفوياواو ا يااففي يضريوفضاي ",
  "collectionContentType.BIOLOGICAL_LIVING_CELL_OR_TISSUE_CULTURES": "وييرضاريوض ف ضررارف اراض وو وضوياف يفييووفف ",
  "collectionContentType.BIOLOGICAL_PRESERVED_ORGANISMS": "رضفوفوااضو ا ضاراووفيا ضفوررضيرو ",
  "collectionContentType.BIOLOGICAL_ANIMAL_BUILT_STRUCTURES": "ضوفيضيييوو ف اضيوضو ضايفا فييفضرايرض ",
  "collectionContentType.BIOLOGICAL_ANIMAL_DERIVED": "يضضاريفوفو ف رفرضاض فياوفضف ",
  "collectionContentType.BIOLOGICAL_BIOFLUIDS": "فضضراضضارض ي فوارضياوي ",
  "collectionContentType.BIOLOGICAL_CELLS_TISSUE": "فاضوضفضفيا ف فووضر اويرضا ",
  "collectionContentType.BIOLOGICAL_ENDOSKELETONS": "ضرااوفريضر ر اايافاوفوضيوف ",
  "collectionContentType.BIOLOGICAL_EXOSKELETONS": "واضرووفاضف ض رووفضااورفوي ",
  "collectionContentType.BIOLOGICAL_FECES": "يضضضاارروا ض يضضيا ",
  "collectionContentType.BIOLOGICAL_MOLECULAR_DERIVATES": "راضفرافضضر ض يريفرايضي يووييرورو ",
  "collectionContentType.BIOLOGICAL_PLANT_DERIVED": "فووفيرفيفر ض فورضف ياضيورر ",
  "collectionContentType.HUMAN_DERIVED_OTHER": "ضرروو اوراايض ا ررففر ",
  "collectionContentType.HUMAN_DERIVED_BIOFLUIDS_HUMAN": "ضضريا اواااضا ض ورضروففور وااوض ",
  "collectionContentType.HUMAN_DERIVED_BLOOD_HUMAN": "ضفويو اواواوي ي يضفوي يرريض ",
  "collectionContentType.HUMAN_DERIVED_CELLS_HUMAN": "واوفي وووايضض ض فيارو يضووا ",
  "collectionContentType.HUMAN_DERIVED_FECES_HUMAN": "يفضوي يفوففرو و ضوفيف ريفوي ",
  "collectionContentType.HUMAN_DERIVED_MOLECULAR_DERIVATIVES": "يييضا ضارييوي ي راواضرضوا ضوضضييرضياض ",
  "collectionContentType.HUMAN_DERIVED_TISSUE_HUMAN": "اوويض ويايييف ي يارراض فاييو ",
  "collectionContentType.EARTH_PLANETARY_OTHER": "رففرر فاضفوضضوض ي ضررار ",
  "collectionContentType.EARTH_PLANETARY_ASTEROIDS": "يوياا ريوارففضف ا فورضرضويف ",
  "collectionContentType.EARTH_PLANETARY_COMETS": "ففرفو راررضيايا و ضيوااي ",
  "collectionContentType.EARTH_PLANETARY_COSMIC_INTERPLANETARY_DUST": "وضيرو واارضيضضي ا ضاضييا يوضويضوضفويروض راوا ",
  "collectionContentType.EARTH_PLANETARY_GAS": "رافضي يواررواوض ي وضو ",
  "collectionContentType.EARTH_PLANETARY_GEMS": "يرياا ضفراييضرو ض اضفي ",
  "collectionContentType.EARTH_PLANETARY_ICE": "يففوا ورضضواواف ا يضض ",
  "collectionContentType.EARTH_PLANETARY_LUNAR_MATERIALS": "وريار ورففضريوو و راريو اضفياايفض ",
  "collectionContentType.EARTH_PLANETARY_METALS_ORES": "ويرري ضفاوووضضي ا يفووفو يورر ",
  "collectionContentType.EARTH_PLANETARY_METEORITES": "ااايف يرضرففااا ي وضفيااافضي ",
  "collectionContentType.EARTH_PLANETARY_MINERALS": "اييرض فووضاواضي ض روافضفيا ",
  "collectionContentType.EARTH_PLANETARY_ROCKS": "ضيفرف ضيوففرضفر ا فاضيو ",
  "collectionContentType.EARTH_PLANETARY_SEDIMENTS": "ايضاف فاررويضضا ا ورووففيوض ",
  "collectionContentType.EARTH_PLANETARY_SOILS": "رارفف ررضرضافرف و فرضاف ",
  "collectionContentType.EARTH_PLANETARY_SPACE_EXPOSED_MATERIALS": "ضرفري وفواروورا ي ضوضيو ورفضوضو فرروويافف ",
  "collectionContentType.EARTH_PLANETARY_WATER": "يضضرض ضرفففرايف ض ويضفر ",
  "collectionContentType.PALEONTOLOGICAL_OTHER": "ريرواررفضارضوفض ف رضوري ",
  "collectionContentType.PALEONTOLOGICAL_CONODONTS": "يرفراوضوفررضضار ر افضواوفاف ",
  "collectionContentType.PALEONTOLOGICAL_INVERTEBRATE_FOSSILS": "رفضاضفيفيرضورضف ا اررفرياييضار يفضرياض ",
  "collectionContentType.PALEONTOLOGICAL_INVERTEBRATE_MICROFOSSILS": "فريارضرياايرواو ف ايفضرضرفيضاف ورييضضضيفاوا ",
  "collectionContentType.PALEONTOLOGICAL_PETRIFIED_WOOD": "ييررايوضفضرياار ا يووروايضض ضففض ",
  "collectionContentType.PALEONTOLOGICAL_PLANT_FOSSILS": "ووواافيراضياوضر ض يفاوف ررريراي ",
  "collectionContentType.PALEONTOLOGICAL_TRACE_FOSSILS": "اففيويوضضيريرضي ر وضايي وفيوووي ",
  "collectionContentType.PALEONTOLOGICAL_VERTEBRATE_FOSSILS": "ضوفضضضفرضورووضر ي فضوففففااض وفيوضيي ",
  "collectionContentType.RECORDS_OTHER": "اارااضو ر ضووري ",
  "collectionContentType.RECORDS_SEISMOGRAMS": "ريفرضاي ر ضوراوفضواور ",
  "collectionContentType.RECORDS_RADIOGRAPH": "ووضايضف و فياوفضرفاف ",
  "collectionContentType.RECORDS_IMAGES": "يضففوار ر فراضيض ",
  "collectionContentType.RECORDS_DOCUMENTS": "رفيضايف ي فروضضيييف ",
  "collectionContentType.RECORDS_DOCUMENTATION": "راواياا ر ضضضوارفاوضرضا ",
  "collectionContentType.RECORDS_DERIVED_DATA": "وفضرارو و ضواويور راضض ",
  "collectionContentType.RECORDS_ASSOCIATED_DATA": "فيياوفو و افرفوورواي ويفف ",
  "collectionContentType.RECORDS_MAPS": "ضيضضفوض ف ضوفض ",
  "collectionContentType.RECORDS_RECORDINGS": "ارايرفا ض يريارويرضا ",
  "contentTypes": "وضراويا ورفوو ",
  "institutionType.BIOMEDICAL_RESEARCH_INSTITUTE": "يضروضيفاضي افريراير اارورفوفي ",
  "institutionType.BOTANICAL_GARDEN": "اضوريراضو ييوروض ",
  "institutionType.HERBARIUM": "يافوافراض ",
  "institutionType.LIVING_ORGANISM_COLLECTION": "يارواي روواضرفر رروايضيييا ",
  "institutionType.MEDICAL_RESEARCH_INSTITUTE": "فيافوير ضضورففيف ووضاوففاا ",
  "institutionType.MUSEUM": "يضيضوض ",
  "institutionType.MUSEUM_HERBARIUM_PRIVATE_NON_PROFIT": "يضضاوض وضاوفايضف ورفففيو ارض ايييضض ",
  "institutionType.OTHER_INSTITUTIONAL_TYPE": "ضافيي رضايارفاضيررا ضووي ",
  "institutionType.OTHER_TYPE_RESEARCH_INSTITUTION_BIOREPOSITORY": "ضفضرف فافف وضضرريرض اورواضيرفاو روروفضوواوياض ",
  "institutionType.UNIVERSITY_COLLEGE": "يضيوضيافير ايووياو ",
  "institutionType.ZOO_AQUARIUM": "ضفف ضضفيوييض ",
  "institutionGovernance.ACADEMIC_FEDERAL": "وفيرراضف ضفورففف ",
  "institutionGovernance.ACADEMIC_FOR_PROFIT": "رضوااففي يضر فوويوا ",
  "institutionGovernance.ACADEMIC_LOCAL": "ضورضاارو ضضضوو ",
  "institutionGovernance.ACADEMIC_NON_PROFIT": "ارفيضضفض ارض رااررف ",
  "institutionGovernance.ACADEMIC_STATE": "وريضايضي يوضوف ",
  "institutionGovernance.FEDERAL": "رافياري ",
  "institutionGovernance.FOR_PROFIT": "فوف ررفافو ",
  "institutionGovernance.LOCAL": "وفااو ",
  "institutionGovernance.NON_PROFIT": "اوا ريرفضض ",
  "institutionGovernance.OTHER": "روففض ",
  "institutionGovernance.STATE": "فياير ",
  "discipline.ARCHAEOLOGY": "يرفرففاييار ",
  "discipline.ARCHAEOLOGY_PREHISTORIC": "ايفضاضيضراض ففيفضييييضر ",
  "discipline.ARCHAEOLOGY_HISTORIC": "فضروراريضرو ريفيرويي ",
  "discipline.ARCHAEOLOGY_UNDERWATER": "يوضيضيااااي رررفرفرضفو ",
  "discipline.ANTHROPOLOGY": "فضيوضفضرفرضي ",
  "discipline.ANTHROPOLOGY_BIOLOGICAL": "وفوضفافارضاا اافويااييا ",
  "discipline.ANTHROPOLOGY_CULTURAL": "روفاضافرفرضف ضريوضوفض ",
  "discipline.ANTHROPOLOGY_LINGUISTIC": "وايضضيضففيفي فضفارويايف ",
  "discipline.SPACE": "فيووا ",
  "discipline.SPACE_ASTRONOMY": "ااراف فيرووويور ",
  "discipline.SPACE_ASTROPHYSICS": "فضااي ضراروااووروض ",
  "discipline.SPACE_COSMOLOGY": "ففررو ايايضييضا ",
  "discipline.SPACE_PLANETARY_SCIENCE": "ووافو فضررضوووف ويرياضي ",
  "discipline.ATMOSPHERIC": "اوواييايضضض ",
  "discipline.ATMOSPHERIC_PHYSICS_DYNAMICS": "ضاوااافضيضض رففضارض وضريفيضض ",
  "discipline.ATMOSPHERIC_CLIMATOLOGY": "يووفرضضضفوض يواففرييرفي ",
  "discipline.ATMOSPHERIC_METEOROLOGY": "فوراضررضرضي رافوريوضررف ",
  "discipline.CHEMICAL": "ضفضيضااا ",
  "discipline.CHEMICAL_ANALYTICAL": "ففايريضو ضاضرييضارا ",
  "discipline.CHEMICAL_ASTROCHEMISTRY": "ويفيفضوض فيوضضفضراوياوض ",
  "discipline.CHEMICAL_ATMOSPHERIC_CHEMISTRY": "اراويريي رفوضيضوفواي يواضوضارض ",
  "discipline.CHEMICAL_BIOCHEMISTRY": "فاييفيفف يضضيفاوضضافض ",
  "discipline.CHEMICAL_BIOGEOCHEMISTRY": "ييراضضيي رضفيويفروفضياضا ",
  "discipline.CHEMICAL_COSMOCHEMISTRY": "ريفايضرف ارورريضضوضيريو ",
  "discipline.CHEMICAL_INORGANIC_CHEMISTRY": "فضضوفييو ضراوررووف يضووافررا ",
  "discipline.CHEMICAL_NUCLEAR_CHEMISTRY": "رضررفيفي فيضضواو يوضفففافض ",
  "discipline.CHEMICAL_ORGANIC_CHEMISTRY": "ضضفورورا اضريررو يورياررري ",
  "discipline.CHEMICAL_PHYSICAL_CHEMISTRY": "رايياففض اوافاضوا ضووياضيضف ",
  "discipline.GEOLOGICAL": "ضيفيرففرفف ",
  "discipline.GEOLOGICAL_ECONOMIC_GEOLOGY_MINERAL_RESOURCES": "يوضرضوافاي يفراورضا ضضريروف رضفاضضا رضفيوايضا ",
  "discipline.GEOLOGICAL_ENERGY_RESOURCE_GEOLOGY": "ااضرضرضوضو اروررف اراايوير فضفضاوا ",
  "discipline.GEOLOGICAL_GEOCHEMISTRY": "يويفضفيويو فواضاررففضفض ",
  "discipline.GEOLOGICAL_GEOLOGY": "يررفضيفارا ررفوارر ",
  "discipline.GEOLOGICAL_GEOPHYSICS_SEISMOLOGY": "يفيااضضافض رواييررفضر ييضراوايوض ",
  "discipline.GEOLOGICAL_HYDROLOGY_WATER_RESOURCES": "ضضاوضوضضرا فوواضفيضر ورويو ووووواضيف ",
  "discipline.GEOLOGICAL_MINERALOGY_PETROLOGY": "يرروفويفاي ضافضضرافضر ريريياووض ",
  "discipline.GEOLOGICAL_PALEONTOLOGY": "يروافيفااف رارافريففريا ",
  "discipline.GEOLOGICAL_VOLCANOLOGY": "ضفرااررورر فوففضورفافف ",
  "discipline.OCEAN": "ضيييو ",
  "discipline.OCEAN_MARINE_BIOLOGY_AND_BIOLOGICAL_OCEANOGRAPHY": "رافضي فيفضاف يرفافاض فوي فففيرضياار اايفيفارريرف ",
  "discipline.OCEAN_MARINE_GEOLOGY_AND_PALEOCEANOGRAPHY": "رووضف يااضور ايضيضيف ياف فضويفيايروويضاضي ",
  "discipline.OCEAN_OCEANOGRAPHY_CHEMICAL_PHYSICAL": "افيفي ررضواوايضروف ياييضضفض يضرااروو ",
  "discipline.PHYSICS": "افيروضا ",
  "discipline.PHYSICS_ACOUSTICS": "ااويرضر ضيفيرواوي ",
  "discipline.PHYSICS_APPLIED_PHYSICS": "ييفييرف رفضاففو ايفاضرا ",
  "discipline.PHYSICS_ATOMIC_MOLECULAR_CHEMICAL_PHYSICS": "ضووروفر اضضارر ضاضويضويي ييففرارر ضياوضار ",
  "discipline.PHYSICS_BIOPHYSICS": "افورايف رايوريااار ",
  "discipline.PHYSICS_MEDICAL_RADIOLOGICAL": "ضضاوضفر اضرفاضر فرراوااافااا ",
  "discipline.PHYSICS_NUCLEAR_PHYSICS": "ضررواار ييواضفي ضوايفوي ",
  "discipline.PHYSICS_OPTICS_PHOTONICS": "ريافررض اوررضر رفويواوضض ",
  "discipline.PHYSICS_PARTICLE_PHYSICS": "وففضففا ضفوفضيفو افررفضر ",
  "discipline.AGRICULTURAL": "يرففايفوورور ",
  "discipline.AGRICULTURAL_ANIMAL_SCIENCE": "ووراضضوفووفو اوضورا فففوورف ",
  "discipline.AGRICULTURAL_ANIMAL_SCIENCE_POULTRY": "وضوضاواورفيض ضياوفض فروااوا ضضياررا ",
  "discipline.AGRICULTURAL_AGRICULTURAL_ANIMAL_BREEDING": "ااوايرروضيور ففافافايففرض فييفاف يايوضففض ",
  "discipline.AGRICULTURAL_AGRICULTURAL_HORTICULTURAL_PLANT_BREEDING": "اييفففريفوفض فضضاويياافاا ففيوووااريااو فياوف رارضييفف ",
  "discipline.AGRICULTURAL_AGRONOMY_CROP_SCIENCE": "ايافواففيضيي وضرررفيو ضضوا ضرواوضا ",
  "discipline.AGRICULTURAL_ENVIRONMENTAL_SCIENCE": "افيفافررضاوض ضواويفيارويار ااوفرفو ",
  "discipline.AGRICULTURAL_FISHING_FISHERIES_SCIENCE": "فاييواففراري يورريرر اياويوررض فضفايوض ",
  "discipline.AGRICULTURAL_FOOD_SCIENCE_AND_TECHNOLOGY": "اراررويوايور ضفيي ييووضيا ضرض ضاااوفروفر ",
  "discipline.AGRICULTURAL_FOREST_SCIENCES_AND_FORESTRY": "يرايافافاورو ياضفاض فضفرضيوا ضاف رواضفااي ",
  "discipline.AGRICULTURAL_HORTICULTURAL_SCIENCE": "اورريووفضفضر ويفرضووويففيا ووضفواف ",
  "discipline.AGRICULTURAL_NATURAL_RESOURCES": "ضرضيفضرفاففا فرفضراض ضضضراروضر ",
  "discipline.AGRICULTURAL_PLANT_SCIENCES": "افيارفضاضررو ضفيرو رففويووا ",
  "discipline.AGRICULTURAL_SOIL_CHEMISTRY_MICROBIOLOGY": "ضيااورضررفوي اوفف راارويراو ضوفارراففرضو ",
  "discipline.AGRICULTURAL_SOIL_SCIENCES": "اضضوضضريضضيف ضضاض فوضايورر ",
  "discipline.AGRICULTURAL_WILDLIFE_RANGE_MANAGEMENT": "فيفافااضضاضض ضضاضضضفي ضرفرو رراايرضارض ",
  "discipline.AGRICULTURAL_WOOD_SCIENCE_AND_PULP_TECHNOLOGY": "ووروفضضاواوف ضاوا فيرضااو ففف فراا يرافايضووو ",
  "discipline.BIOLOGICAL": "ييضفوفووفض ",
  "discipline.BIOLOGICAL_ANATOMY_AND_PHYSIOLOGY": "فيافففاااف يوضارري وضا ضييوففويضف ",
  "discipline.BIOLOGICAL_CELLULAR_BIOLOGY_AND_HISTOLOGY": "ضضوريوضاضا يييويويف ياضوفضا واا وااففضرار ",
  "discipline.BIOLOGICAL_DEVELOPMENT_BIOLOGY_EMBRYOLOGY": "يرفاضيواضف فوروووضضوير افرايضو اضورضواافض ",
  "discipline.BIOLOGICAL_ECOLOGY": "فويافيوففف ياريييي ",
  "discipline.BIOLOGICAL_ENVIRONMENTAL_TOXICOLOGY": "رورريافووض ايضيفايافضياي واريوفوواا ",
  "discipline.BIOLOGICAL_EVOLUTIONARY_BIOLOGY": "وفيواوضروف وضرايفافيررو يافضفاا ",
  "discipline.BIOLOGICAL_GENETICS_GENOMICS": "فياضضواراف يييضروضف ويوفايضر ",
  "discipline.BIOLOGICAL_MICROBIOLOGY_BACTERIOLOGY_VIROLOGY": "رايفيواضوا رضرفرضوضرضرو ضارويضاايضوي وفيرريري ",
  "discipline.BIOLOGICAL_MOLECULAR_BIOLOGY": "ضيووفضرفاض ريفافضافو اضاففرا ",
  "discipline.BIOLOGICAL_NEUROSCIENCES_AND_NEUROBIOLOGY": "فوافويراضف رضفاورفوضفراو رفي فييواضضفوفيض ",
  "discipline.BIOLOGICAL_PARASITOLOGY": "ضييرفوياار ضيفاضيوفووفر ",
  "discipline.BIOLOGICAL_PATHOLOGY_ANIMAL_PLANT": "اوضفراضرار رضويررفضض يااضوي ورضفي ",
  "discipline.BIOLOGICAL_TAXONOMY": "فرارايضيضا ضفيرضفوا ",
  "discipline.BIOLOGICAL_ZOOLOGY": "ضرضييفضررو ضاضيفوف ",
  "discipline.HEALTH": "رارافض ",
  "discipline.HEALTH_BIOMEDICAL_SCIENCE": "ااضفضي ففرضاضضضيو ضوايرفو ",
  "discipline.HEALTH_ENVIRONMENTAL_HEALTH": "يويرضف وافيافوووراضا ضرضفضا ",
  "discipline.HEALTH_EPIDEMIOLOGY_PUBLIC_HEALTH": "فيففيو فضرافيرفاففف اافوفف فافوار ",
  "discipline.HEALTH_GENETICS_GENOMICS": "يفاررر رضرضوضور يفرييرضو ",
  "discipline.HEALTH_MICROBIOLOGY_BACTERIOLOGY_VIROLOGY": "ففوفاا وورضروفورايض يياررفضاضضضر اياوفييا ",
  "discipline.HEALTH_NEUROSCIENCES_AND_NEUROBIOLOGY": "افواضا ييرفوياارررضي يضي يفرفيوضفيارو ",
  "discipline.HEALTH_NUTRITION_SCIENCES": "اوافضو فوفضوياضي اضفضوففض ",
  "discipline.HEALTH_PATHOLOGY_HUMAN": "فرافاف راضايوراي اوويف ",
  "discipline.HEALTH_PHARMACEUTICAL_MEDICINAL_SCIENCES": "رضضريو وضيارضوريضواضا ضفرراوفوض ضاضيضفاف ",
  "discipline.HEALTH_PHARMACOLOGY_HUMAN_AND_ANIMAL": "ضوررور ضوفيضاييضضاض روواو ففو ضوضورو ",
  "discipline.HEALTH_TOXICOLOGY": "اويرضض افاويوورفو ",
  "discipline.HEALTH_VETERINARY_SCIENCES": "ضريضوف يارفضيضاضف فوايوويض ",
  "discipline.MATERIAL": "ضضفيرضوي ",
  "disciplines": "روورفووافضر ",
  "additionalNames": "ريرارضيضور وفضوف ",
  "foundingDate": "ويوايوفا وافف ",
  "geographicDescription": "رضفرففرويي فرضوروايايي ",
  "taxonomicDescription": "ضواييورضو وريضرييرافي ",
  "numberSpecimens": "وضرريي اويريضوضو ",
  "citesPermitNumber": "ررفيف ارافيف فراضوف ",
  "areaResponsibility": "فضفو ايضضيوفويوفافر ",
  "researchPursuits": "ااياففور رضيررريف ",
  "fax": "ضور ",
  "primaryInstitution": "اوضروفي رفياروفافوف ",
  "primaryCollection": "ضورضارو فضروفففاوي ",
  "syncDate": "فووا اوضر ",
  "result": "اريياو ",
  "dashboard.lastCreatedAgo": "[[[!Last created {timeAgo}!]]]",
  "dashboard.xInTotal": "[[[!{formattedNumber} in total!]]]",
  "dashboard.xPending": "[[[!{formattedNumber} pending!]]]",
  "dashboard.xWithoutEndpoint": "[[[!{formattedNumber} without {count, plural, zero {endpoints} one {endpoint} other {endpoints}}!]]]",
  "help.organization.nonPublishing": "ففووافييروفوض ييرض يرور يوض فرا يريفوفيفر اوض ووفرفااض ",
  "help.mailingAddress": "فيضار اي رارا فيرر ف ضي رو رفوففرور رواويرض يا فضارييرا ررير افرض يي وفيف فوو يرروروف وف فيف اوف فورضراف ",
  "help.physicalAddress": "رضيضر رو ففويا ",
  "help.commentContent": "[[[!Commentary should be written with consideration, using language suitable for any public forum and not containing sensitive details. {break}{bold}.!]]]",
  "help.identifier": "ورض فوضيف يرر يوا اريايرووفي (اوضف ياوافوواييضاييوض)ف ",
  "help.identifierType": "رفارضو ااض يفيف ير يضر واروارضوووف ",
  "help.mtNamespace": "رري واافففضفر يض ي يواواوفض ففض وفض ففوييفففضي روفف افرض رض ياو في فووا رو ضيورفاياضوض ضروضرريضا (ضياي يرويرويير ضضاضويضضيا) فر يف فيوضضوف ا اريو يواف واايويضضي (فوضر يار) ",
  "help.mtName": "ورف يايف راي ارر اضي (اضيف ضاووففيافافيوا فررف)ض ",
  "help.mtValue": "ووف فافضا يرف ورر ضفي (وفوف ارافرف ييفيفرضوا ضرايو)ي ",
  "help.tagValue": "ييف ضرضاو ييف يفف ضوو (وفار وياياورفو ويضيضفا يفوو)ف ",
  "help.orgTitle": "ياويو اف يرووففضض فيفاضايياضرف وضيفو يو اف فر فرار ور رارو فيي فففضضضف ",
  "help.reportingPurposes": "ييفض ضض ضايو ارر فوضضفرورف اافريفرر (رضار يوضفاييورض فرراري ضض فض ياو اوفررفرفر) ",
  "help.userName": "ضيض اوي ييي ري وفيفا ف ضفضافضوا را ور وضروي اضضضوايي ",
  "help.primaryCheckboxTip": "ييفريرويي ررفر فوف وويورضض اي يري يويففاا اويرافر ضيي فضض فضاوا يايض ",
  "help.tagValueExtra": "يضف يويوا فضي ضاف ضرو (اضفا وفرويييوف ياضيضضر روفو)و ",
  "help.externalTip": "ضيفرريفور يفرا اضي واضوررر رر وييور وووفيري ضيرفضاراضفا رارف رضضاارور ييرياضراا فرا ررر وضيرففريفف يفضوضراض ضرضو اروي ",
  "help.lockedForAutoUpdateTip": "وفاضاففف يويريضييضاي فور ورفيفووو افضيررفر ضاضفووراي فرففضضاض وفض ",
  "help.publishingOrg": "رر ضي فضوضفضفف فرفي وفاا وضا رف ريوريفو فاروفاضففرواو رفو رر وضرريوضي اا وضروراا فو فففر اوض ورفرورفري اي ضيارا ضيايفاويروي فافرضفيفرف ايو فيضيففففرر فوفيرريي وفايرضر ضوو يواي ",
  "help.installation": "وا ضو ضافاوااا ضايو ضوضض ضضف ار يفييضضا اوارايضضياضضي وور فف رورفاضير وو رضااروي رف ضوير ايا يررارضارف فض اياوف ييافرواوياض فاورواافيو ضفف ضافروياريف ايضوضرضر فاضواايف وضرضيض وفووفا يوو ففيرفوفي واا اي وفففضضاو يا ضضيفرض ",
  "help.parentDataset": "ففو اور اف روويضوررر ورفووور وففضفويروضففوي اريض وا يفف وفييرفويففا اضارض فا ااو ضورفيضااو رر يياي ",
  "help.duplicateDataset": "ضيفض ض فضضاففف فر ضاورو وا رو ي ضضايواواض فو ضفرورضضو افاض يو ففاوفا يا ضفافريوو فيرو ففوف يفافورضضييض وضيياضا ف وضضووفاض ضاييو رض ويض رفوض اي و يفوروفيفي في رفر رو ضيرض يضض ضراو اويي رف اري رفر اضضيضي ضوواضيف ضي يضضر يور يضاض فضيفواواروي ",
  "help.updateFrequency": "اوض وضيضاوورف يفضض يوويي روويفرر ارض فاضريرفرف رضض يضيي ",
  "help.instTitle": "فررضي ضا ييضاففيض ررووضراضضيور وففرر يو ير فض يراو او ريوو ضيا ففريافف ",
  "help.instDescription": "فاروضير ف فايرضورضوا ضرارففضاضضف ضض اوف فافواوضضويياو اي ي فففي اواض اضرياويضفو روار راو يييوواوووروو ياو ",
  "help.instPublishingOrg": "اض ضض اافورضفي رارض اضضف ضاا وا اضفااري وررضفوارافرضا ضفر ضو يوريوفوي وي اضورواف ضض يايض يرف اريوووورض ير يفيضو يضيوواويووو اووفواوضار يرر ضضضايضفافي رفررفايف ضفرضضوف ااا راضف ",
  "help.instType": "يضضو فااضضياض وضيوض ففااضي ايو افيضيرضي فوا ااوف راضررفو ضفر فاي اضراريييريفيف رير رفررر ضراضافف اضيضيوض ييفي ضاوففف يضر وو ريف رضيف فض ضووضار وراا فاوياض ورر ياضرفف رافورو ف يفض ضريوراوفضروا وف اير ويوروفض يفرير رفر اضففرفا ااضيوضارر ضاا ارير يرور ررووضرض ضيواووا ",
  "help.disabledCheckboxTip": "ضاوضويفوض رافي ضوو فويررفرففضاا او راورييور فاف فض رويفضفاف ور وافوايضا وو ضضرارافياا وفروووفا ااوا يارري ",
  "help.orgCommentsInfo": "ضضوواوير ضاراا روفوررررفاورري ضو ووويا ضضروضيو يوضاض وضففويفضاييريي يااض وضفرووضوضو فويي ",
  "help.orgMachineTagsInfo": "رضرورير اراو ففا فيرييفضي ضضر ويراويفافواض اض ورضفر فضففضففرواا يضييي يض يريفاوف و ررارضضو واي يض يففضضوافراا ر وفضيفراافا ررييا فافر ضا اراضارفريرف اف ض فضضضيضفضرف رار ر فاايي ووض فض ضضرا رض اضف فضفرضياوويا ضااف وضفر ",
  "help.orgOverviewInfo": "روفض وفضضيوروفري ضاضواضر ضر يضر اضففياضافوار رفويرافي فضيضرراوافيا وويضرا رضوضاا وضضيضورو ورر رااررفض ",
  "help.nodeOverviewInfo": "اافض ارفرررضياضر ريرييفي فر ضوي ضفاا فوارضييض ضوريروضافااي ااضاضي افيياض يوافاوضر ضرو ضيرفيضو ",
  "help.language": "ضير فرورفررر ضيفر ضرا فوو ضفريف را اوفروضوفوفيف يضااوواف فوض ",
  "physicalAddress": "اوفورضاو رايوروض ",
  "mailingAddress": "واوفضرف رضاوفرو ",
  "important.deleted.organization": "[[[!This organization was deleted {relativeTime} by {name}.!]]]",
  "important.deleted.dataset": "[[[!This dataset was deleted {relativeTime} by {name}.!]]]",
  "important.deleted.installation": "[[[!This installation was deleted {relativeTime} by {name}.!]]]",
  "important.deleted.collection": "[[[!This collection was deleted {relativeTime} by {name}.!]]]",
  "important.deleted.institution": "[[[!This institution was deleted {relativeTime} by {name}.!]]]",
  "important.deleted.person": "[[[!This person was deleted {relativeTime} by {name}.!]]]",
  "important.disabled.installation": "يووي ضرضيارفيافار فو ريوايضري ضفا ضف رروا فففففرا اوضف فووفو ",
  "restore.organization": "ويضيافا راوي وضيافيايررفض ",
  "restore.dataset": "ووففاوف اريو وايفيضف ",
  "restore.installation": "ضفااارر رروا فوفضافووورفض ",
  "restore.collection": "وضاوروا ييور فويفوفاضضض ",
  "restore.institution": "فرفرفوف فااا رورضوضوفارو ",
  "restore.person": "فضايضور يرضض ريرضفر ",
  "restore.confirmation": "ففضفاااار ف رريضيفوروو يفافياف ضضضويف ريفف رففضوض فوضررضر ضفويفرفضيضي ييففايففري ",
  "delete.confirmation.comment": "ففو ياض رارف ضض فاارور فراض ضايضرافو ",
  "delete.confirmation.contact": "ففف ااف فضري وا ضارفضو اافا ضواووضضي ",
  "delete.confirmation.endpoint": "ياف ااي اياا فف يفورضر يوفر اضضااايرا ",
  "delete.confirmation.identifier": "فوو راف اياي فر رفضيفي روار ررضراضرفيضا ",
  "delete.confirmation.machineTag": "ضضف يضي ييفف وض رفرفاف ففوا رووففرا وضضا ",
  "delete.confirmation.tag": "ياي ووا اييض وو ضارراا ضورض وورف ",
  "delete.confirmation.organization": "رفض روو ايوض يف يضفريف رياا فيرضرررفضرضضا ",
  "delete.confirmation.dataset": "رضض فرض وريا وف اففررر رياض يوواااوض ",
  "delete.confirmation.installation": "وري اضو ضففي فو ضرافري يفوف فارايضاورروفر ",
  "delete.confirmation.collection": "رير اوا وفيض اض ريايرف ضارا روااييوفايض ",
  "delete.confirmation.institution": "رير واا رففا يو فرفيضو رضضا ارضايوااييضض ",
  "delete.confirmation.person": "ضرو يرر ضفيي اض يرييير اافض ضواضرفف ",
  "delete.organization": "يفوضار اريو يضرضفضراضففي ",
  "delete.dataset": "ضيففرر وضوف فضايروض ",
  "delete.installation": "فيروضا ضييض فاايفضاضاروي ",
  "delete.person": "ريايفف يفضض ضووضير ",
  "delete.collection": "وفضروف ضرضف ااوررفرياف ",
  "delete.institution": "ضاافيا يواف ضفااضراااضض ",
  "organization.retrievePassword": "ارررايفف ويوففراض ",
  "organization.retrievePassword.message": "[[[!The password is only for use with the IPT (the GBRDS API), registering datasets using new API ({api}) requires a user with {role} permission and an entry in the {table} table. {password}!]]]",
  "notFound": "ففو اضياا ",
  "search": "وووضاف ",
  "query": "[[[! for '{query}'!]]]",
  "registryMeta": "فيففييضي اييضوضفا ",
  "download": "وضفررضوا ",
  "downloads": "ارويضفارض ",
  "status": "فضرفوف ",
  "contact": "يفرفضوو ",
  "copyrights": "ييفو رفضر وي واضوورورار وا يرفف ر اروايف ضرراضاوضيضضف ضضافيوضفيور ضاروضضوير ",
  "cookieAndPolicy": "رفيواو ورض يوررفور ويضففضض ",
  "githubRepo": "فرفيرض ررضفياضراو ",
  "issuesTracker": "فرضرضو ووووفاو "
}