{
  "title.dashboard": "[!!Ɖášħɓơãŕđ | ĜɃĬƑ Ʀȇġĭŝŧŕɏ!!]",
  "title.organizations": "[!!Őřğǻƞĭźäŧĩőŋś | ĢƁĨƑ Řėĝĭŝţřŷ!!]",
  "title.datasets": "[!!Ɗàŧàšęŧş | ĢʙĨƑ Ŕęĝįšţŗȳ!!]",
  "title.installations": "[!!Īƞśţãĺļáŧįōńş | ĠʙĪƑ Řĕģīśťřŷ!!]",
  "title.nodes": "[!!Ńŏđēş | ĞʙĪƑ Ʀȅģĭŝťŕŷ!!]",
  "title.users": "[!!Ůšȅřś | ĢƁĮƑ Řęğĭŝťřȳ!!]",
  "title.organization": "[!!Ōŕġäņĭƶăťīŏŉ | ĠɃĪƑ Řěġışţŗɏ!!]",
  "title.dataset": "[!!Ɖǻťȁśėť | ĢƁĪƑ Ŗěġĭśŧŕƴ!!]",
  "title.installation": "[!!Ĭňşŧåŀļãŧīőŋ | ĠɃĬƑ Ŕēģįşŧřɏ!!]",
  "title.node": "[!!Ňőďě | ĠɃĨƑ Ŕēĝĩšŧřɏ!!]",
  "title.user": "[!!Ūşȅŕ | ĢʙİƑ Řęģĩşŧřƴ!!]",
  "title.newOrganization": "[!!Ɲěŵ őŕĝâņĩƶăŧĩơņ | ĠßĮƑ Ŕȅğĩśŧřȳ!!]",
  "title.newDataset": "[!!Ɲȇŵ ďáŧášęţ | ĞɃĮƑ Ŗēğīşţŗȳ!!]",
  "title.newInstallation": "[!!Ŋēŵ ĩŋšťąľŀǻţĭơƞ | ĞʙİƑ Ŕęġįŝťŗŷ!!]",
  "title.collections": "[!!Ċőłĺĕĉţįőƞŝ | ĜßĮƑ Ŕēĝįśţřȳ!!]",
  "title.persons": "[!!Ƥȅŕšơŉś | ĢƁĨƑ Řęğįšťŗȳ!!]",
  "title.institutions": "[!!Ĩƞśŧĩŧŭŧįơńş | ĜßĨƑ Řěģĭŝťŗŷ!!]",
  "title.collection": "[!!Ĉŏłľęčţĭőŉ | ĢƁĮƑ Řęğĩşťřɏ!!]",
  "title.person": "[!!Ƥėřšōń | ĜʙĪƑ Řȅĝĭşŧřȳ!!]",
  "title.institution": "[!!İņšţĭŧűţĩőŋ | ĠʙĮƑ Ŗęģįŝŧŗɏ!!]",
  "title.newCollection": "[!!Ņęŵ čōłľȅĉťĩōƞ | ĜßİƑ Ŕęğīşťřȳ!!]",
  "title.newPerson": "[!!Ńȇŵ ƥęŗŝōŋ | ĜƁĨƑ Ʀĕĝĩśťŕɏ!!]",
  "title.newInstitution": "[!!Ńėŵ īňšŧĩţūţıōņ | ĠʙĬƑ Ʀēğĭśŧŗȳ!!]",
  "title.overingested": "[!!Ơvēŕ-īŋģėŝŧęđ đȃţȁśȅŧś | ĜßĨƑ Ŗȇğĭśţŗŷ!!]",
  "title.ingestion": "[!!Ʀųņƞĭńĝ ĭňģēŝţįőŉś | ĠɃĪƑ Řėĝıšţŕƴ!!]",
  "welcome": "[!!Ďȁŝħƅőāŕď!!]",
  "title": "[!!Ťīţĺė!!]",
  "dashboard.message1": "[!!Ŵħáţ ŝħōųľđ ţħȅ ĥŏmȅƿȃġė śħőŵ. Ƥȇřħäƿś äś ŧħĕ ĉŭŕŗȅŋţ ľĩŉĸş ŧơ ŝȇǻŕćĥ ťŷƿėš. Ŵě ĉơűłď ǻđď řėċȅňţļŷ vīŝīţęđ ŕěśőūŕĉēş.!!]",
  "dashboard.message2": "[!!Ĭƒ ŀŏğģȅď ıň īť ċŏŭĺď ǻļşŏ ŝĥőŵ ą đàśĥƀơäŕđ: mįšśĭƞĝ ěňđōŗśēmȅŋŧś. ƒâīłĩňģ đāţäśěţ ćřåŵŀş.!!]",
  "createNew": "[!!Čŗĕãťę ƞěŵ!!]",
  "addNew": "[!!Áđď ŋȅŵ!!]",
  "create": "[!!Ĉŗĕâťȅ!!]",
  "delete": "[!!Đȇĺėťȇ!!]",
  "edit": "[!!Ȇđįŧ!!]",
  "view": "[!!Vĭĕŵ!!]",
  "add": "[!!Ǻđď!!]",
  "cancel": "[!!Ĉáņćěŀ!!]",
  "save": "[!!Ŝȃvė!!]",
  "createdByRow": "[[[!Created {date} by {author}!]]]",
  "noMachineTags": "[!!Ňŏ mãĉĥĭŉę ŧȃĝš!!]",
  "createNewComment": "[!!Ćřȅăťė ǻ ŋȇŵ ĉŏmmȇŉţ!!]",
  "content": "[!!Čơņŧēňŧ!!]",
  "supportedFormats": "[!!Ơŋłŷ ŭşę őƒ ƥľǻıņ ťęxţ ĭś šũƿƥơŕťėđ - ƞō XMĿ, ĵŜŐŇ ęŧĉ!!]",
  "createNewContact": "[!!Ċřȇǻŧȅ ȁ ņęŵ ċơňŧāćŧ!!]",
  "createNewDefaultValue": "[!!Ċŗȅāţē ă ńĕŵ đěƒàũĺť våŀůę!!]",
  "addNewContact": "[!!Āďđ å ŉěŵ ĉōŉţåćŧ!!]",
  "editFormInstructions": "[!!Műłţį vǻļůė ƒīĕŀďş ƿőşĩţĭőņ, ȅmáĭļ, ƿĥơńę, ħōmĕƥåĝȅ āňđ áďďřĕŝŝ ăřĕ īŋďīčãţęď ɓƴ * ãńđ űšē ŧħȇ ŝȇmıćơŀơň ăš ţĥē đėłĭmīŧēŕ.!!]",
  "type": "[!!Ťŷƿė!!]",
  "select.type": "[!!Śėłęćţ å ţƴƥȇ!!]",
  "select.country": "[!!Śĕľēćţ à čơůńťŗƴ!!]",
  "select.endorsingNode": "[!!Šȇŀěċŧ ȁņ ȇńďōŗśĩńĝ ŉơđȇ!!]",
  "select.language": "[!!Śȅŀĕćŧ á łāŋģŭåĝĕ!!]",
  "select.subtype": "[!!Šęľěčŧ ă šųƅťɏƥĕ!!]",
  "select.license": "[!!Śěļĕĉŧ â ļıċȅƞšĕ!!]",
  "select.organization": "[!!Ŝęŀėčť ȁŉ ōřĝâņĩƶàţįŏń!!]",
  "select.installation": "[!!Šēľēĉŧ ãń ĭņšţǻłłȁţıőň!!]",
  "select.updateFrequency": "[!!Şĕłĕćť âƞ ũƥďáţė ƒŕēǫũȇŋćȳ!!]",
  "select.parentDataset": "[!!Śėŀȇčť ƿâřȇŋť ďâŧâŝȇŧ!!]",
  "select.duplicateDataset": "[!!Śęĺȇčţ ďűƿļıĉāŧĕ ơƒ ďǻţąśȇţ!!]",
  "select.status": "[!!Ŝĕłĕčť â ŝţäŧųš!!]",
  "select.region": "[!!Şēłęċţ â ŕēĝıőņ!!]",
  "select.continent": "[!!Šěłȇčţ ă ĉōŉţīŋėņţ!!]",
  "select.institution": "[!!Ŝėĺĕčţ äń ĭŋśťĭţũŧįőŉ!!]",
  "select.governance": "[!!Śȇļēčţ ǻ ğŏvėřŋȃňĉę!!]",
  "select.discipline": "[!!Šěĺȅčŧ ȃ ďĩşĉįƿľĭńę!!]",
  "select.number": "[!!Ŝěļȅćť ȃ ņūmƃěŗ!!]",
  "select.collection": "[!!Şęľĕćŧ à čōľľėĉťıőń!!]",
  "select.person": "[!!Şėłēćŧ ȁ ƥęŕŝőņ!!]",
  "select.node": "[!!Šȇĺĕċŧ ǻ ňŏđę!!]",
  "primary": "[!!Ƥřīmäŗȳ!!]",
  "firstName": "[!!Ƒıřśţ ńâmȅ!!]",
  "lastName": "[!!Łȃŝŧ ŉāmȇ!!]",
  "position": "[!!Ƥōśĩţīőŋ!!]",
  "provide.position": "[!!Ƥľȇáśě ƿřơvīđē å ƿőšıŧįőŉ!!]",
  "provide.email": "[!!Ƥľėȁŝē ƥŗơvįđę âŉ ěmãĩļ!!]",
  "provide.phone": "[!!Ƥľėăśě ƿŗŏvįďě ä ƿħơņȇ!!]",
  "provide.homepage": "[!!Ƥĺȅāśȇ ƥřŏvĭđȇ ȁ ĥŏmėƥāġę!!]",
  "provide.address": "[!!Ƥĺėāšȅ ƿřōvīďě ȁņ ȃďđŕȅśš!!]",
  "provide.userId": "[!!Ƥļȇåŝė ƥŗővįđě à ūşėŗ ĨƊ!!]",
  "provide.url": "[!!Ƥŀȅåšė ƿŗōvıďē å ŨƦĹ!!]",
  "provide.identifier": "[!!Ƥļĕãšę ƥŕővīđȇ åń īďȇŉţıƒĩĕř!!]",
  "provide.namespace": "[!!Ƥłęäśė ƥŕŏvĭđė ȃ ƞȁmēšƥâĉē!!]",
  "provide.name": "[!!Ƥłȅȁšȅ ƿŗŏvıďȇ ă ňâmȇ!!]",
  "provide.value": "[!!Ƥŀęǻśȅ ƥřővĩđę ǻ vāĺũě!!]",
  "provide.title": "[!!Ƥļȇăşě ƿřơvĭďę å ŧĩťŀĕ!!]",
  "provide.endorsingNode": "[!!Ƥĺěâśē ƥŗōvįďĕ ąŉ ęńđŏŗŝīŉġ ňŏďȇ!!]",
  "provide.type": "[!!Ƥľȅăšė ƥŕŏvĭďē ã ťȳƿȇ!!]",
  "provide.subtype": "[!!Ƥľēăşě ƥŗōvĭđȇ ȁ śűƅŧɏƥė!!]",
  "provide.language": "[!!Ƥłēąŝȅ ƿŕơvįđĕ ă ĺąňĝŭăģę!!]",
  "provide.license": "[!!Ƥłěâŝȇ ƿŕōvĭđě ą ľıčěŋšē!!]",
  "provide.firstName": "[!!Ƥŀĕąśȇ ƿŕōvĭđē ƒĭŕşť ƞàmė!!]",
  "provide.doi": "[!!Ƥĺěâśȅ ƿŕővīďě ǻ ƉŎĮ!!]",
  "provide.organization": "[!!Ƥŀĕȃşē ƿŕŏvįďė åŋ ŏřĝàŉıźåŧīőń!!]",
  "provide.installation": "[!!Ƥłěāśě ƿŗővįďȇ äń įńşťäŀľąťĭơƞ!!]",
  "provide.institution": "[!!Ƥľȇăšĕ ƥŕơvĩďĕ āŋ ĭŉşţīŧųŧįơņ!!]",
  "provide.code": "[!!Ƥłėȁśė ƿŕōvıđė á ĉőđĕ!!]",
  "provide.userName": "[!!Ƥłěāśē īŋƿūŧ ȳŏűř ųšȇřņămȅ!!!]",
  "provide.password": "[!!Ƥŀěãšě įňƥūŧ ȳŏūř Ƥąšśŵőŕđ!!!]",
  "description": "[!!Ɖěşčŕīƥţĭőŋ!!]",
  "phone": "[!!Ƥħơņȅ!!]",
  "homepage": "[!!Ħōměƥăğę!!]",
  "organization": "[!!Ơřģâŋıźąŧĭơƞ!!]",
  "address": "[!!Âđďřēŝś!!]",
  "city": "[!!Ćįŧȳ!!]",
  "province": "[!!Ƥŕơvįńĉę!!]",
  "country": "[!!Ċơũƞŧřɏ!!]",
  "postalCode": "[!!Ƥōŝťáļ ċōďȇ!!]",
  "userId": "[!!Ŭšȇř ĬĐ!!]",
  "createNewEndpoint": "[!!Ċřęâťė ȃ ňĕŵ ĕƞďƥŏĭƞţ!!]",
  "url": "[!!ŪŖĻ!!]",
  "createNewIdentifier": "[!!Ċřęȁťē ä ňēŵ īđĕŋŧĩƒıĕř!!]",
  "identifier": "[!!Įďȅŉŧĭƒįėř!!]",
  "createNewMachineTag": "[!!Ĉŕēȃţė á ŋȇŵ måćħĭňĕ ţǻġ!!]",
  "namespace": "[!!Ɲàmȇŝƿåċě!!]",
  "name": "[!!Ŋāmĕ!!]",
  "finishReason": "[!!Ƒīņĩšħ řęāşơŉ!!]",
  "startedCrawling": "[!!Ŝţàŗţȅđ ĉŕȁŵľįňġ!!]",
  "finishedCrawling": "[!!Ƒıňįŝĥėď ĉŗàŵŀĭŋğ!!]",
  "value": "[!!Vȃŀůĕ!!]",
  "createNewTag": "[!!Ċŕęáŧĕ ȃ ŋėŵ ťâĝ!!]",
  "created": "[!!Ćřȅåťȇď!!]",
  "createdBy": "[!!Ĉŕėăťěď Ƅȳ!!]",
  "modified": "[!!Mőďĩƒīěď!!]",
  "modifiedBy": "[!!Mōđįƒĩȇđ ƃȳ!!]",
  "userName": "[!!Ūśȇŕńámė!!]",
  "email": "[!!Ěmȃīŀ!!]",
  "overview": "[!!Ơvēŗvįȇŵ!!]",
  "contacts": "[!!Ćōņťâĉťš!!]",
  "endpoints": "[!!Ĕņđƥŏīňŧŝ!!]",
  "identifiers": "[!!Īđȇŉţĩƒįēŗş!!]",
  "defaultValues": "[!!Ɗȇƒǻũľť văľūěš!!]",
  "dataset": "[!!Ďȃťáşěţ!!]",
  "node": "[!!Ňōđȅ!!]",
  "person": "[!!Ƥȅŗśōŉ!!]",
  "collection": "[!!Ċőłľȇċŧįơň!!]",
  "institution": "[!!Ĭŉšţīŧůŧĩōň!!]",
  "tags": "[!!Ŧåĝś!!]",
  "machineTags": "[!!Mąċĥĭŉě Ťåĝš!!]",
  "comments": "[!!Ċơmměŋŧŝ!!]",
  "publishedDataset": "[!!Ƥűƀļĩŝĥȅđ Ďȁŧąŝěţ!!]",
  "publishedDatasets": "[!!Ƥűƀĺĭŝħęď ďàţåşěťŝ!!]",
  "hostedDataset": "[!!Ĥơśŧēď Ɖāŧȃŝěť!!]",
  "hostedDatasets": "[!!Ħŏšŧēď đàŧȃšęţŝ!!]",
  "installations": "[!!İńŝťàļŀâťĭōńş!!]",
  "abbreviation": "[!!ĀƄɓŗȅvīȁťĭőň!!]",
  "endorsingNode": "[!!Ĕŋđőŕşĭŋģ ƞőďę!!]",
  "approved": "[!!Äƥƿřővȇđ!!]",
  "awaitingApproval": "[!!Åŵȃĩťıńğ åƥƿŗơvǻľ!!]",
  "logoUrl": "[!!Ľŏğő ŲŔĹ!!]",
  "logo": "[!!Ĺơġő!!]",
  "language": "[!!Łàŉģűȃġē!!]",
  "latitude": "[!!Ľåŧıťųďě!!]",
  "longitude": "[!!Ĺơņğĩŧũđě!!]",
  "crawl": "[!!Čŗáŵľ!!]",
  "endorsementApproved": "[!!Ěńđőřşěmęňť âƥƥřővēď!!]",
  "menu.organization": "[!!Ŏŕģáņĩżãŧīōŉš!!]",
  "menu.organization.search": "[!!Şěȃŕčħ őŕġåŉīžȁťįơňš!!]",
  "menu.dataset.search": "[!!Šėâřćħ ďàţȁšȇŧş!!]",
  "menu.installation.search": "[!!Šȅäŗčħ įňşťâŀłȃŧıőňş!!]",
  "menu.organization.deleted": "[!!Ďěĺĕţēď ơŕġāńįżąťīơňś!!]",
  "menu.dataset.deleted": "[!!Ɗȇļĕŧĕđ ďàťåśęťś!!]",
  "menu.installation.deleted": "[!!Ɗȅłȅťėď īńśŧȃĺĺāţıōƞś!!]",
  "menu.organization.pending": "[!!Ƥěňđįňģ ŏŕģãŉīžãťĭŏƞś!!]",
  "menu.organization.nonPublishing": "[!!Ňŏņ ƥűƄŀĭśħįŉĝ őŕĝąňĭźǻťĩơŉş!!]",
  "menu.dataset": "[!!Ďàťȃŝěţš!!]",
  "menu.dataset.duplicate": "[!!Ɗũƿĺĩĉāţęŝ ŏƒ đȃťàšĕţš!!]",
  "menu.dataset.constituent": "[!!Ćōŋšťĩţūĕŋť đāţåşěţş!!]",
  "menu.dataset.withNoEndpoint": "[!!Ɗâŧȃśęŧŝ ŵīŧħ ŋō ȇŉďƿōĩŉŧ!!]",
  "menu.installation": "[!!Īŉšťåłĺāťįŏňś!!]",
  "menu.installation.empty": "[!!Ĕmƿţȳ ĩńşţâŀłȃťįōŋŝ!!]",
  "menu.collection": "[!!Ćőļļęĉŧĩŏƞš!!]",
  "menu.collection.search": "[!!Şėåŕĉħ ċơľŀěćţıơŉş!!]",
  "menu.collection.deleted": "[!!Ďėĺęţęđ ćōĺľěċŧīŏŉš!!]",
  "menu.institution": "[!!Ĭŋšţıŧűťıōŉś!!]",
  "menu.institution.search": "[!!Šȅâŕċĥ ĭńšťįţũŧįōņş!!]",
  "menu.institution.deleted": "[!!Đęľėŧȅď īņšţĭťůŧıŏňš!!]",
  "menu.grSciCollPerson": "[!!ĜřŠċĭĆơłŀ śţāƒƒ!!]",
  "menu.grSciCollPerson.search": "[!!ĞřŠčıĈŏľľ şŧȁƒƒ ŝȇåŗčĥ!!]",
  "menu.grSciCollPerson.deleted": "[!!ĞŗŜċīČőľĺ šťāƒƒ đěŀěťēď!!]",
  "menu.node": "[!!Ŋőđȅš!!]",
  "menu.user": "[!!Űšēŕş!!]",
  "menu.monitoring": "[!!Mơńĭţơřıńğ!!]",
  "menu.monitoring.ingestion": "[!!Ŕūŋŉıňģ īƞğēśťįơŉš!!]",
  "menu.monitoring.overingested": "[!!Ơvȇŗ-ĩņĝėşŧȅđ đăţáśěţś!!]",
  "submenu.contact": "[!!Čōņťåċŧş!!]",
  "submenu.identifier": "[!!Īđėŉťĩƒĭĕŗş!!]",
  "submenu.endpoint": "[!!Ĕņďƿŏĭņťś!!]",
  "submenu.tag": "[!!Ŧàğš!!]",
  "submenu.machineTag": "[!!Mãĉħįńę ţàģŝ!!]",
  "submenu.comment": "[!!Čơmmȅŉŧś!!]",
  "submenu.constituents": "[!!Ĉōŋŝţįţūēŉţ ďăŧǻşėťś!!]",
  "submenu.publishedDataset": "[!!ƤũƄłīŝħėđ đąţąŝĕŧş!!]",
  "submenu.hostedDataset": "[!!Ĥŏśťēđ ďǻţǻšĕţš!!]",
  "submenu.installation": "[!!Ĭņŝŧąľĺǻţĩơŉş!!]",
  "submenu.synchronizationHistory": "[!!Śȳņćħřŏńĩżāťĩōŉ ĥĩŝţơŕȳ!!]",
  "submenu.servedDatasets": "[!!Şĕŕvēđ ďăťåšȇŧŝ!!]",
  "submenu.pending": "[!!Ƥĕŋđĭŉĝ ęŋđőŕşȅmȇňŧś!!]",
  "submenu.organization": "[!!Ȇƞďŏŕšēď ōřğąňīžáţıőņś!!]",
  "submenu.dataset": "[!!Ęƞđőřŝȅđ đąŧāşĕťš!!]",
  "submenu.collection": "[!!Ċōłĺȇčŧĭōņş!!]",
  "submenu.institution": "[!!Ĩņŝŧıţůţĭőňś!!]",
  "submenu.process": "[!!Īňģĕšŧĩŏŉ!!]",
  "submenu.download": "[!!Đōŵňļơàđ!!]",
  "submenu.syncState": "[!!Śƴńċ şťáŧē!!]",
  "listType.search": "[!!Śęãŗċħ!!]",
  "listType.deleted": "[!!Ɖėĺĕťēđ!!]",
  "listType.pending": "[!!Ƥȅƞďīƞġ!!]",
  "listType.nonPublishingOrganizations": "[!!Ņōŉ ƿŭƄłĩŝħīŋģ ŏřğȁņįźāťīŏƞś!!]",
  "listType.duplicate": "[!!Ɖűƥļıčąţȇ!!]",
  "listType.constituent": "[!!Čőńšţīŧūȅŋť!!]",
  "listType.withNoEndpoint": "[!!Ŵıŧħ ŋō ėŉđƿơıńŧ!!]",
  "listType.servingNoDatasets": "[!!Şėŗvĩŋġ ƞő ďäťáŝēŧś!!]",
  "placeholder.username": "[!!Ūśėŕňąmę!!]",
  "placeholder.password": "[!!Ƥåššŵŏŗđ!!]",
  "logIn": "[!!Ľōģ ĭņ!!]",
  "login": "[!!Ľơġĭń!!]",
  "logout": "[!!Ŀŏģơűţ!!]",
  "country.AD": "[!!Äņďōŗŗā!!]",
  "country.AE": "[!!Ũŉīťěđ Åŕåƀ Ȇmīŕȃŧěš!!]",
  "country.AF": "[!!Ȃƒĝĥȃņįŝţàŉ!!]",
  "country.AG": "[!!Ăƞťįĝŭá ąŋđ ßāřƂũđǻ!!]",
  "country.AI": "[!!Ȃņğųīĺłą!!]",
  "country.AL": "[!!Ȁļƅãƞıȁ!!]",
  "country.AM": "[!!Åŕmȅŉıá!!]",
  "country.AO": "[!!Ǻńĝőľȃ!!]",
  "country.AQ": "[!!Ăŉťǻŕċţĭċâ!!]",
  "country.AR": "[!!Ãřğęŋťĩńȁ!!]",
  "country.AS": "[!!Ămĕřįĉàŉ Śǻmŏá!!]",
  "country.AT": "[!!Àųşťřĭą!!]",
  "country.AU": "[!!Ǻŭŝŧŗȁĺıá!!]",
  "country.AW": "[!!ĄřűƄâ!!]",
  "country.AX": "[!!Åĺāŉđ Īśľàŋđŝ!!]",
  "country.AZ": "[!!ĂżȇŕƃȁĩĴȃŉ!!]",
  "country.BA": "[!!ʙōşŉīå ãŋđ Ħȅŗƶěġővıŉā!!]",
  "country.BB": "[!!ßǻŗɓȃďŏś!!]",
  "country.BD": "[!!ʙąņġĺȁďȇŝĥ!!]",
  "country.BE": "[!!ʙēłğįūm!!]",
  "country.BF": "[!!ßūŕķįƞà Ƒäšō!!]",
  "country.BG": "[!!ʙŭŀģàŗıà!!]",
  "country.BH": "[!!Ƀáħŕáĩņ!!]",
  "country.BI": "[!!ʙŭŗűƞđį!!]",
  "country.BJ": "[!!ßĕŋĭņ!!]",
  "country.BL": "[!!Šàįŉť ʙãŗŧħéľȅmŷ!!]",
  "country.BM": "[!!Ƀĕŕmůđă!!]",
  "country.BN": "[!!Ƀŗŭňěī Ďâŕũšśăľǻm!!]",
  "country.BO": "[!!Ƀơļĭvıă, Ƥŀũřıňãţĩơŋąĺ Śţàŧė ơƒ!!]",
  "country.BQ": "[!!ʙơŉàĩŕė, Ŝıŉţ Ěūŝţãŧĭŭś ąņď ŜąƂȁ!!]",
  "country.BR": "[!!Ɓřâźĩł!!]",
  "country.BS": "[!!Ƀáħámãş!!]",
  "country.BT": "[!!Ɓĥůţàņ!!]",
  "country.BV": "[!!ßŏųvěţ Īśŀāŉď!!]",
  "country.BW": "[!!ßőţşŵăƞǻ!!]",
  "country.BY": "[!!ßȇĺȁŕŭś!!]",
  "country.BZ": "[!!Ƀėŀıžė!!]",
  "country.CA": "[!!Ċáƞáďă!!]",
  "country.CC": "[!!Ćōčőş (Ƙĕėľıŋģ) Ĩśĺȃŉďš!!]",
  "country.CD": "[!!Čōŉģơ, ŧĥė Đėmơčŕȃţĭć Ʀėƥůƀŀĭĉ ōƒ ťĥē!!]",
  "country.CF": "[!!Ĉėňţŗąĺ Ȃƒŕīċâƞ Řėƿűƀľįč!!]",
  "country.CG": "[!!Ĉōƞĝő!!]",
  "country.CH": "[!!Ŝŵīťżȅŕŀȃņđ!!]",
  "country.CI": "[!!Ċôťē ď\"Ĩvŏĩŕĕ!!]",
  "country.CK": "[!!Ćōŏķ Īŝĺâƞđś!!]",
  "country.CL": "[!!Čħıľě!!]",
  "country.CM": "[!!Ċȃměŗőōŉ!!]",
  "country.CN": "[!!Čħıńá!!]",
  "country.CO": "[!!Čơľőmƅįä!!]",
  "country.CR": "[!!Čŏŝţâ Řĭćå!!]",
  "country.CU": "[!!Čůƃá!!]",
  "country.CV": "[!!Ĉåƥě Vēŕďē!!]",
  "country.CW": "[!!Ćŭřāçàō!!]",
  "country.CX": "[!!Ċħřıŝťmȁš Īŝĺãŉď!!]",
  "country.CY": "[!!Ċŷƥŗųş!!]",
  "country.CZ": "[!!Ĉżěčħ Ŗēƥųɓľĩĉ!!]",
  "country.DE": "[!!Ĝęŕmȁŉȳ!!]",
  "country.DJ": "[!!ĎĴıƅőųţĩ!!]",
  "country.DK": "[!!Ɖȅŉmǻŕƙ!!]",
  "country.DM": "[!!Ɗőmīŉıčà!!]",
  "country.DO": "[!!Ɗơmĩŋĭĉąƞ ŖěƥŭƄłįć!!]",
  "country.DZ": "[!!Ąļģęŕĩă!!]",
  "country.EC": "[!!Ěċųåďŏŕ!!]",
  "country.EE": "[!!Ėšťōņĩȃ!!]",
  "country.EG": "[!!Ȅģƴƥţ!!]",
  "country.EH": "[!!Ŵėśťȇřƞ Şąħȃřȁ!!]",
  "country.ER": "[!!Ēŕįťřȅă!!]",
  "country.ES": "[!!Ŝƿâįƞ!!]",
  "country.ET": "[!!Ěŧĥīōƥįȁ!!]",
  "country.FI": "[!!Ƒıŉľàƞď!!]",
  "country.FJ": "[!!ƑįĴī!!]",
  "country.FK": "[!!Ƒãļķļāņď Ĭŝŀȃńđŝ (Màłvĭŋāş)!!]",
  "country.FM": "[!!Mįċŗőŉĕŝĭā, Ƒȅđȅŕāţēđ Śŧáŧȅś ơƒ!!]",
  "country.FO": "[!!Ƒǻřőě Īšĺȃƞďş!!]",
  "country.FR": "[!!Ƒřáņċē!!]",
  "country.GA": "[!!Ĝȁƀơņ!!]",
  "country.GB": "[!!Ųŉīťȇď Ƙĭňģđơm!!]",
  "country.GD": "[!!Ğŕȇňȁđȃ!!]",
  "country.GE": "[!!Ġȅơŗğįǻ!!]",
  "country.GF": "[!!Ƒŕėņċĥ Ğűīąńã!!]",
  "country.GG": "[!!Ĝųěřŉşȇŷ!!]",
  "country.GH": "[!!Ğħȃŋă!!]",
  "country.GI": "[!!ĢįƄŗäľťǻŕ!!]",
  "country.GL": "[!!Ģŗĕėņĺãƞđ!!]",
  "country.GM": "[!!ĢȃmƂĭǻ!!]",
  "country.GN": "[!!Ģűĭŋēā!!]",
  "country.GP": "[!!Ğũàďȇĺőůƿě!!]",
  "country.GQ": "[!!Ęɋűáŧŏŕīȁŀ Ģųıŋȅȁ!!]",
  "country.GR": "[!!Ğŕęěćȇ!!]",
  "country.GS": "[!!Šőũťĥ Ĝėōřĝīã ȃƞď ťħē Šŏűŧħ Śáŉđŵıċĥ İšĺȃŋđš!!]",
  "country.GT": "[!!Ġůāťĕmáľâ!!]",
  "country.GU": "[!!Ĝųám!!]",
  "country.GW": "[!!Ģűĭŋėȁ-ßīšśáų!!]",
  "country.GY": "[!!Ĝŭȳǻņą!!]",
  "country.HK": "[!!Ĥōńĝ Ķŏňģ!!]",
  "country.HM": "[!!Ĥěǻŗď Įŝļåňď áńď MćĐơňǻłď Ĭŝŀäƞđš!!]",
  "country.HN": "[!!Ĥőŉđůřáŝ!!]",
  "country.HR": "[!!Ĉŕŏȃţıă!!]",
  "country.HT": "[!!Ħāįťī!!]",
  "country.HU": "[!!Ĥűņģãŕƴ!!]",
  "country.ID": "[!!Īŉďŏƞēšıä!!]",
  "country.IE": "[!!Ĩřĕŀäŉđ!!]",
  "country.IL": "[!!Ĭśřȁȇŀ!!]",
  "country.IM": "[!!Įşŀě ōƒ Mâň!!]",
  "country.IN": "[!!Įņďįȁ!!]",
  "country.IO": "[!!ʙřĩťįŝħ Īńďįâņ Ŏċȅåŉ Ţȇŗřīţōŕɏ!!]",
  "country.IQ": "[!!İřáǫ!!]",
  "country.IR": "[!!Īŗáƞ, Ĭŝļāmīć Ŕȅƿųɓļıċ ŏƒ!!]",
  "country.IS": "[!!Ĩċȇŀǻƞđ!!]",
  "country.IT": "[!!İťāĺȳ!!]",
  "country.JE": "[!!ĵěŕśēȳ!!]",
  "country.JM": "[!!ĵāmȃıĉą!!]",
  "country.JO": "[!!ĵŏŗďåņ!!]",
  "country.JP": "[!!ĵáƿȁň!!]",
  "country.KE": "[!!Ķěńɏâ!!]",
  "country.KG": "[!!Ķŷřġȳżšţąŉ!!]",
  "country.KH": "[!!Ĉãmƅŏđĭȃ!!]",
  "country.KI": "[!!ĶĭŗīƄąţĭ!!]",
  "country.KM": "[!!Ċōmōŗőŝ!!]",
  "country.KN": "[!!Śǻıňŧ Ķīţťś ăňď Ņēvĩŝ!!]",
  "country.KP": "[!!Ƙōŗȅä, Ɖěmōĉŗǻţįč Ƥĕőƿłę\"ŝ ŔĕƥŭƂŀĩč ōƒ!!]",
  "country.KR": "[!!Ķŏřĕȃ, Ŗēƿůɓłĭĉ ōƒ!!]",
  "country.KW": "[!!Ķŭŵăīť!!]",
  "country.KY": "[!!Ĉąŷmáŉ İŝŀāńďş!!]",
  "country.KZ": "[!!Ƙãźãĸĥśţąŉ!!]",
  "country.LA": "[!!Ľãơ Ƥȇōƥļē\"ş Ɖȅmōĉřàťĩċ Ŗĕƥűɓļıċ!!]",
  "country.LB": "[!!Łėƅàņōŋ!!]",
  "country.LC": "[!!Śāįņŧ Ĺŭĉĭã!!]",
  "country.LI": "[!!Łįėčĥŧēńšťěīƞ!!]",
  "country.LK": "[!!Šŕĭ Łãņķǻ!!]",
  "country.LR": "[!!ĽıƂȇřĩå!!]",
  "country.LS": "[!!Łęšŏţĥō!!]",
  "country.LT": "[!!Ļıŧĥūåňįȃ!!]",
  "country.LU": "[!!ĿůxȅmƂŏūŗğ!!]",
  "country.LV": "[!!Ĺàŧvĭȁ!!]",
  "country.LY": "[!!ĿīƂŷå!!]",
  "country.MA": "[!!Mơŗŏččơ!!]",
  "country.MC": "[!!Mŏŋąčō!!]",
  "country.MD": "[!!Mōŀďơvä, Ʀĕƿűƀŀīć ōƒ!!]",
  "country.ME": "[!!Mŏƞţēŋȅĝřő!!]",
  "country.MF": "[!!Śàīňŧ Màŗťĩň (Ƒŕĕņćħ ƿářŧ)!!]",
  "country.MG": "[!!Máđáġäšċãř!!]",
  "country.MH": "[!!Màřŝĥâĺŀ Įšļȃƞđş!!]",
  "country.MK": "[!!Mȃĉēđŏńįä, ŧĥē ƒōŗmȅŕ Ƴųģơšŀāv ƦȅƥūƂļīĉ őƒ!!]",
  "country.ML": "[!!Măļį!!]",
  "country.MM": "[!!Mƴąňmâŗ!!]",
  "country.MN": "[!!Mŏňğőĺıā!!]",
  "country.MO": "[!!Måĉąō!!]",
  "country.MP": "[!!Ɲŏŗŧĥȅŗń Mâřĭāƞá Įšłǻŋďš!!]",
  "country.MQ": "[!!Mȃŗŧıńīǫůē!!]",
  "country.MR": "[!!Mȃűŗįŧäŉįã!!]",
  "country.MS": "[!!Mōńťšĕŕŗåţ!!]",
  "country.MT": "[!!Mȃļŧą!!]",
  "country.MU": "[!!Mäũŕīŧĩŭś!!]",
  "country.MV": "[!!Mǻłďįvĕş!!]",
  "country.MW": "[!!Mãĺąŵĭ!!]",
  "country.MX": "[!!Mȅxĭĉō!!]",
  "country.MY": "[!!Máļãŷŝĭă!!]",
  "country.MZ": "[!!MŏƶāmƂıǭũē!!]",
  "country.NA": "[!!ŅǻmıƂıā!!]",
  "country.NC": "[!!Ŋēŵ Ćȃŀĕđőƞıà!!]",
  "country.NE": "[!!Ņĩġĕř!!]",
  "country.NF": "[!!Ŋơŗƒŏļƙ Īşłăńď!!]",
  "country.NG": "[!!Ńīĝėřĭā!!]",
  "country.NI": "[!!Ɲĩċāŕȃġŭâ!!]",
  "country.NL": "[!!Ɲȇŧħęŗľāŋďś!!]",
  "country.NO": "[!!Ɲŏřŵäƴ!!]",
  "country.NP": "[!!Ɲĕƥȃľ!!]",
  "country.NR": "[!!Ŋåųŗū!!]",
  "country.NU": "[!!Ɲįũė!!]",
  "country.NZ": "[!!Ńęŵ Žĕãľąƞď!!]",
  "country.OM": "[!!Ōmăň!!]",
  "country.PA": "[!!Ƥȁŋâmȃ!!]",
  "country.PE": "[!!Ƥęŕŭ!!]",
  "country.PF": "[!!Ƒřȇņĉħ Ƥơľŷƞȇşıǻ!!]",
  "country.PG": "[!!Ƥàƥũă Ņěŵ Ĝūīŋȇà!!]",
  "country.PH": "[!!Ƥħīĺįƥƥīƞēŝ!!]",
  "country.PK": "[!!Ƥăĸıśŧàň!!]",
  "country.PL": "[!!Ƥŏŀǻņđ!!]",
  "country.PM": "[!!Šȃıŋť Ƥıēŕřē åņď Mıɋŭēĺơƞ!!]",
  "country.PN": "[!!Ƥįţĉáĩŕƞ!!]",
  "country.PR": "[!!Ƥŭěŕţō Ŕĩĉŏ!!]",
  "country.PS": "[!!Ƥàļȇśŧĩňē, Ŝťāţȇ ơƒ!!]",
  "country.PT": "[!!Ƥŏřţŭĝäĺ!!]",
  "country.PW": "[!!Ƥàļǻŭ!!]",
  "country.PY": "[!!Ƥăřǻġŭäŷ!!]",
  "country.QA": "[!!Ǫàţȁř!!]",
  "country.RE": "[!!Řéũŉīŏŉ!!]",
  "country.RO": "[!!Ŗơmȁŋĩā!!]",
  "country.RS": "[!!Śėřƅĩà!!]",
  "country.RU": "[!!Ŗūśšĩȃŋ Ƒȇďęŗãŧīōƞ!!]",
  "country.RW": "[!!Ŗŵãŉđá!!]",
  "country.SA": "[!!Şãŭďį Āřăƅīâ!!]",
  "country.SB": "[!!Şőŀőmőń Ĩŝŀãƞđŝ!!]",
  "country.SC": "[!!Śęƴćħȇŀľȅŝ!!]",
  "country.SD": "[!!Ŝųďǻň!!]",
  "country.SE": "[!!Şŵȇďęŋ!!]",
  "country.SG": "[!!Ŝıņģăƿōŕē!!]",
  "country.SH": "[!!Śâīńŧ Ĥěľȅƞȁ, Āščęƞśĩōń åŋď Ťŗįŝţãŋ ďă Čŭńĥà!!]",
  "country.SI": "[!!Ŝļővėňīà!!]",
  "country.SJ": "[!!ŚvąŀƄȃřđ ȃńď ĵąƞ Mȃŷēƞ!!]",
  "country.SK": "[!!Śłŏvàķıå!!]",
  "country.SL": "[!!Śıȅŕŕä Ľȇơŋę!!]",
  "country.SM": "[!!Śȃŉ Máŕīŋō!!]",
  "country.SN": "[!!Şȅŉěĝäŀ!!]",
  "country.SO": "[!!Šőmǻŀįå!!]",
  "country.SR": "[!!Ŝűřīņǻmė!!]",
  "country.SS": "[!!Ŝōŭťĥ Ŝųďåƞ!!]",
  "country.ST": "[!!Šāő Ţőmě āńđ Ƥŕįƞčĩƿĕ!!]",
  "country.SV": "[!!Ęł Şǻłvăďōŗ!!]",
  "country.SX": "[!!Ŝĭňť Mäąřŧȅņ (Ďūŧĉĥ ƥȃŕť)!!]",
  "country.SY": "[!!Ŝɏŕįäň Áŕăƅ Ŗȇƥűƃĺįć!!]",
  "country.SZ": "[!!Ŝŵǻżıŀàńđ!!]",
  "country.TC": "[!!Ţůŕķš ăņď Ćâıċőś İšľâńďş!!]",
  "country.TD": "[!!Ćħäď!!]",
  "country.TF": "[!!Ƒřėňčĥ Šőũţħěŕņ Ťėŗŕīťőŗıĕš!!]",
  "country.TG": "[!!Ţőġő!!]",
  "country.TH": "[!!Ťħãĭľâŉď!!]",
  "country.TJ": "[!!ŤąĴīĸıŝŧāň!!]",
  "country.TK": "[!!Ŧŏķēłâű!!]",
  "country.TL": "[!!Ŧįmōŕ-Ļėşŧȇ!!]",
  "country.TM": "[!!Ťůřƙměńĩşŧȁŋ!!]",
  "country.TN": "[!!Ţŭŉıśįå!!]",
  "country.TO": "[!!Ţŏňğȃ!!]",
  "country.TR": "[!!Ŧųřĸĕɏ!!]",
  "country.TT": "[!!Ţŕĭńįďȃđ ąňď Ťōƃàģő!!]",
  "country.TV": "[!!Ŧųváļů!!]",
  "country.TW": "[!!Ćħĭňĕšĕ Ţãıƿěı!!]",
  "country.TZ": "[!!Ťäƞżäŉĭą, Ůňĩţĕđ ŘēƥũƂļīĉ ơƒ!!]",
  "country.UA": "[!!Ůĸřãıńė!!]",
  "country.UG": "[!!Ũġãŋďá!!]",
  "country.UM": "[!!Űŋįťȇđ Śţāťĕś Mįňōŕ Ōűťľɏīňĝ Ĩŝŀåņďş!!]",
  "country.US": "[!!Ůňįŧēď Şťǻţěš!!]",
  "country.UY": "[!!Ůŕũğűąȳ!!]",
  "country.UZ": "[!!ŲżƂėĸįŝťäƞ!!]",
  "country.VA": "[!!Ħōľɏ Śȇě (Vȁţıĉȁń Ćĩŧŷ Ŝťàťĕ)!!]",
  "country.VC": "[!!Šăĩňţ Vīńćěņţ ãƞď ťĥė Ĝřȅňąďĭņěŝ!!]",
  "country.VE": "[!!Vȅŉĕżųĕĺȃ, Ƀơľįvàřįąń ŖěƥũƂļĩć őƒ!!]",
  "country.VG": "[!!Vĭřĝĭŋ Īšļāňďş, Ɓŗĩţĩśħ!!]",
  "country.VI": "[!!Vįřğīń Įşłāƞďś, Ŭ.Š.!!]",
  "country.VN": "[!!Vĩěť Ňám!!]",
  "country.VU": "[!!Vàŋũåţů!!]",
  "country.WF": "[!!Ŵãłłĩŝ âŋđ Ƒűŧűńå!!]",
  "country.WS": "[!!Šåmŏȃ!!]",
  "country.YE": "[!!Ÿęmȇň!!]",
  "country.YT": "[!!Mǻƴơŧŧȇ!!]",
  "country.ZA": "[!!Ŝŏūŧħ Āƒŗıčȃ!!]",
  "country.ZM": "[!!Ƶâmƀĭå!!]",
  "country.AA": "[!!Ŭšěř ďĕƒıŋȅđ!!]",
  "country.XZ": "[!!Įŉŧȇřŋąťĩơņãĺ ŵäŧěŗŝ!!]",
  "country.QO": "[!!Őċęǻňīȁ!!]",
  "country.ZZ": "[!!Ŭŉĸƞơŵň ōř įňväļĭđ (ųŝėđ įŋťěŗńȁŀłɏ ȃť ĜƁĬƑ ƒŏŗ ĩńţ. ŏŕğŝ)!!]",
  "country.ZW": "[!!ƵĭmƄãɓŵȅ!!]",
  "country.XK": "[!!Ķơśơvō!!]",
  "language.aar": "[!!Āƒąŕ!!]",
  "language.abk": "[!!ÅƂĸĥàƶįáņ!!]",
  "language.ace": "[!!Ǻĉĥīńęŝē!!]",
  "language.ach": "[!!Ąċōĺī!!]",
  "language.ada": "[!!Āđàƞĝmę!!]",
  "language.ady": "[!!Ăďƴĝħȇ!!]",
  "language.afa": "[!!Ãƒŕŏ-Ąšĭåťĭċ łăņğũâģēš!!]",
  "language.afh": "[!!Ąƒŕīĥĩĺī!!]",
  "language.afr": "[!!Ȃƒřıķäǻƞŝ!!]",
  "language.ain": "[!!Àīƞŭ!!]",
  "language.aka": "[!!Ǻķàŋ!!]",
  "language.akk": "[!!Äķƙąďıǻŉ!!]",
  "language.ale": "[!!Àŀȅũŧ!!]",
  "language.alg": "[!!Ãłģōńǫŭīâŋ ŀáňģųȃĝēš!!]",
  "language.alt": "[!!Ŝōůŧĥęřŉ Ãļţàı!!]",
  "language.amh": "[!!Ámħãřīċ!!]",
  "language.ang": "[!!Ęŉğľıšħ, Ŏŀđ (ĉà.450-1100)!!]",
  "language.anp": "[!!Ãńġįƙȃ!!]",
  "language.apa": "[!!Àƥãćħȇ ŀáŉġűăĝēş!!]",
  "language.ara": "[!!Ăřäɓĭĉ!!]",
  "language.arc": "[!!Ŏƒƒĩćįâł Ȃŗàmȁĩċ (700-300 ʙĈĒ)!!]",
  "language.arg": "[!!Ǻŗąġőņėśȅ!!]",
  "language.arn": "[!!Måƥųďŭńġūņ!!]",
  "language.arp": "[!!Áŕȃƿäĥơ!!]",
  "language.art": "[!!Àřťıƒıčĭął ĺȃŉġũȃĝĕş!!]",
  "language.arw": "[!!Áŕáŵåķ!!]",
  "language.asm": "[!!Ãšşåmȇŝȅ!!]",
  "language.ast": "[!!Ĺěōŉȅŝę!!]",
  "language.ath": "[!!Âŧħàƿàŝĉăŉ łăńĝųāģěš!!]",
  "language.aus": "[!!Ȁųŝŧŕăľĭȁņ ļāņģŭáĝĕş!!]",
  "language.ava": "[!!Ävąŕĭĉ!!]",
  "language.ave": "[!!Ȃvėşŧȃń!!]",
  "language.awa": "[!!Ȃŵåďĥī!!]",
  "language.aym": "[!!Áƴmåŕȁ!!]",
  "language.aze": "[!!ȀźĕŕɓȁįĴȃƞī!!]",
  "language.bad": "[!!ßāƞđā ĺȁŋĝůãģěŝ!!]",
  "language.bai": "[!!Ɓămįļěƙȇ łàňġũȃġĕš!!]",
  "language.bak": "[!!ʙȁśħĸĭŗ!!]",
  "language.bal": "[!!ʙãŀűĉĥī!!]",
  "language.bam": "[!!ɃąmƂářă!!]",
  "language.ban": "[!!Ɓȃľįņĕšȅ!!]",
  "language.bas": "[!!Ɓâşã!!]",
  "language.bat": "[!!ʙǻłŧıć ŀăňģůąğęŝ!!]",
  "language.bej": "[!!ɃȇĴą!!]",
  "language.bel": "[!!Ƀēĺãŗůşıäņ!!]",
  "language.bem": "[!!ʙėmƄȁ!!]",
  "language.ben": "[!!Ɓȇňĝȁļĩ!!]",
  "language.ber": "[!!ʙēřƄėŕ ĺąŉğŭȃģȇś!!]",
  "language.bho": "[!!ɃħŏĴƥūŗĭ!!]",
  "language.bih": "[!!Ƀıĥáŗı ļàŋģűàģěŝ!!]",
  "language.bik": "[!!Ƀĩƙōŀ!!]",
  "language.bin": "[!!Ȅďő!!]",
  "language.bis": "[!!ßĭśłãmą!!]",
  "language.bla": "[!!Śĭƙšĩķȃ!!]",
  "language.bnt": "[!!Ɓãńŧŭ ľǻƞğŭäğȇš!!]",
  "language.bod": "[!!ŤīƂėťǻƞ!!]",
  "language.bos": "[!!ßơśņīăŉ!!]",
  "language.bra": "[!!ßŕąĴ!!]",
  "language.bre": "[!!Ɓŗȇŧŏń!!]",
  "language.btk": "[!!Ɓǻťàƙ ĺąŉğūâģėš!!]",
  "language.bua": "[!!Ƀűřĩāť!!]",
  "language.bug": "[!!Ƀūģĩŋěšė!!]",
  "language.bul": "[!!Ɓűļģǻŕĩáň!!]",
  "language.byn": "[!!Ɓļīŋ!!]",
  "language.cad": "[!!Ćāďđŏ!!]",
  "language.cai": "[!!Ĉęňťŗäŀ Āmēŕĭċȃŉ Ĩŉđįȁƞ ľǻňğųāĝȇş!!]",
  "language.car": "[!!ĞãłįƂį ČáŕĭƂ!!]",
  "language.cat": "[!!Čăťàļąň–Vâłěńċĩąŋ!!]",
  "language.cau": "[!!Čãūćǻśĩäň ĺăŋģůâğȇš!!]",
  "language.ceb": "[!!Ĉĕƀũąŉō!!]",
  "language.cel": "[!!Ćĕĺťīč ľãńġŭàģęŝ!!]",
  "language.ces": "[!!Ċżęċĥ!!]",
  "language.cha": "[!!Ćĥȁmōřŗơ!!]",
  "language.chb": "[!!ĈĥįƂċĥǻ!!]",
  "language.che": "[!!Čĥēčħĕņ!!]",
  "language.chg": "[!!Ĉĥȁġåťäĩ!!]",
  "language.chk": "[!!Ĉĥųũķěśȅ!!]",
  "language.chm": "[!!Māřĩ!!]",
  "language.chn": "[!!Čĥĩŉőőķ Ĵǻŕġōň!!]",
  "language.cho": "[!!Čĥōćŧăŵ!!]",
  "language.chp": "[!!Ďēŉĕ Šũĺĭńȇ!!]",
  "language.chr": "[!!Čħēŗŏķěȇ!!]",
  "language.chu": "[!!Őĺď Ŝŀăvŏŉĩċ!!]",
  "language.chv": "[!!Čĥųvàšħ!!]",
  "language.chy": "[!!Ćĥēƴēńƞĕ!!]",
  "language.cmc": "[!!Ćĥămıĉ ľȁńġũāģȇŝ!!]",
  "language.cop": "[!!Ćơƿťĭċ!!]",
  "language.cor": "[!!Čơŕňıśĥ!!]",
  "language.cos": "[!!Čŏŗşīĉáŉ!!]",
  "language.cpe": "[!!Ĉŕěơŀęŝ áƞď ƿıďğĩŋš, Ȇŋğłĭśħ-ƀàšěđ!!]",
  "language.cpf": "[!!Ĉŗēŏĺėš āŉď ƥįďġĭňŝ, Ƒřĕƞčħ-ƃǻŝėđ!!]",
  "language.cpp": "[!!Ćŗēơĺęş ȃňđ ƥıđģıŋş, Ƥōřţũĝũęšę-Ƃãşęđ!!]",
  "language.cre": "[!!Ćřĕě!!]",
  "language.crh": "[!!Ćŗįměȃŉ Ŧŭŗƙįşĥ!!]",
  "language.crp": "[!!Ĉŕĕơļȇŝ ăŋď ƥıđġĭņš!!]",
  "language.csb": "[!!Ƙáŝĥũƃīâń!!]",
  "language.cus": "[!!Čŭşħĭŧįč łàƞğūāģęş!!]",
  "language.cym": "[!!Ŵȇłśĥ!!]",
  "language.dak": "[!!Ɗâƙōťą!!]",
  "language.dan": "[!!Ɗȃŋįśħ!!]",
  "language.dar": "[!!Đâřġŵā!!]",
  "language.day": "[!!Łäňđ Ɗǻŷăĸ ļǻņğųàġėś!!]",
  "language.del": "[!!Ɖěļäŵàřē!!]",
  "language.den": "[!!Śłǻvě (Ȃťĥäƿâşćȁŉ)!!]",
  "language.deu": "[!!Ğĕŕmáń!!]",
  "language.dgr": "[!!Ďőġŕįƅ!!]",
  "language.din": "[!!Ďīňĸà!!]",
  "language.div": "[!!Mâłđıvĩàƞ!!]",
  "language.doi": "[!!Đōğŕĭ!!]",
  "language.dra": "[!!Ďŗȁvįđĭāŋ ĺàńģũáğēş!!]",
  "language.dsb": "[!!Ŀōŵȅř ŚōřƄıāń!!]",
  "language.dua": "[!!Ɗŭàļä!!]",
  "language.dum": "[!!Ɗųťčĥ, Mīďđľě (čă.1050-1350)!!]",
  "language.dyu": "[!!Ďƴũłä!!]",
  "language.dzo": "[!!Đźőŉġķħá!!]",
  "language.efi": "[!!Ȅƒįķ!!]",
  "language.egy": "[!!Ȅġŷƥťīåƞ (Âŋčįěƞŧ)!!]",
  "language.eka": "[!!ȄƙâĴųĸ!!]",
  "language.ell": "[!!Ĝŕęȅƙ, Mŏďęŗŉ (1453-)!!]",
  "language.elx": "[!!Ȅĺămīţē!!]",
  "language.eng": "[!!Ȅƞğĺĭšĥ!!]",
  "language.enm": "[!!Ȅŋġłįşĥ, Mįđđľȇ (1100-1500)!!]",
  "language.epo": "[!!Ȇšƿęřāƞťŏ!!]",
  "language.est": "[!!Ēşŧōńĩǻŋ!!]",
  "language.eus": "[!!Ɓąşɋűę!!]",
  "language.ewe": "[!!Ęŵė!!]",
  "language.ewo": "[!!Ȅŵŏņďơ!!]",
  "language.fan": "[!!Ƒăŋģ!!]",
  "language.fao": "[!!Ƒȃŕōȅśē!!]",
  "language.fas": "[!!Ƥēŕŝıåń!!]",
  "language.fat": "[!!Ƒàŉťĭ!!]",
  "language.fij": "[!!ƑįĴıâƞ!!]",
  "language.fil": "[!!Ƥıłıƥıňơ!!]",
  "language.fin": "[!!Ƒĭƞŋĭŝĥ!!]",
  "language.fiu": "[!!Ƒĩňňơ-Ųĝřĭäń ľȁňğūáģėš!!]",
  "language.fon": "[!!Ƒơŉ!!]",
  "language.fra": "[!!Ƒŗėņĉħ!!]",
  "language.frm": "[!!Ƒŕēņćħ, Mįđďŀė (čä.1400-1600)!!]",
  "language.fro": "[!!Ƒřėňĉħ, Ōĺđ (842-ĉǻ.1400)!!]",
  "language.frr": "[!!Ņơŕťĥȅŕƞ Ƒřĭşıȃƞ!!]",
  "language.frs": "[!!Ȇášťȅŗň Ƒŕįşĭäƞ!!]",
  "language.fry": "[!!Ŵĕšťȅŗŋ Ƒŗīŝıāŋ!!]",
  "language.ful": "[!!Ƒųŀäħ!!]",
  "language.fur": "[!!Ƒŗįūľĭȁň!!]",
  "language.gaa": "[!!Ğą!!]",
  "language.gay": "[!!Ġäƴŏ!!]",
  "language.gba": "[!!Ģɓåŷä!!]",
  "language.gem": "[!!Ğēŕmåŉīć ĺȃŋĝŭãğȇş!!]",
  "language.gez": "[!!Ġĕȅż!!]",
  "language.gil": "[!!Ĝīłƃȅŗťȇšė!!]",
  "language.gla": "[!!Śĉőŧţīŝħ Ĝãȇŀıč!!]",
  "language.gle": "[!!Ĭřĭšĥ!!]",
  "language.glg": "[!!Ğāĺĩćĭȁň!!]",
  "language.glv": "[!!Mȃņx!!]",
  "language.gmh": "[!!Ģėŕmȃŋ, Mĭďďŀȅ Ħĭġħ (ćǻ.1050-1500)!!]",
  "language.goh": "[!!Ģȅŗmäƞ, Ōļď Ĥīģħ (ĉă.750-1050)!!]",
  "language.gon": "[!!Ġơŋďī!!]",
  "language.gor": "[!!Ģơŕōŉťäĺơ!!]",
  "language.got": "[!!Ġơŧħīč!!]",
  "language.grb": "[!!ĜŕȇƄő!!]",
  "language.grc": "[!!Ğřėȇķ, Ãňĉĭęŉť (ţơ 1453)!!]",
  "language.grn": "[!!Ğūăřãŉĭ!!]",
  "language.gsw": "[!!Śŵīşś Ğēřmàń!!]",
  "language.guj": "[!!ĜũĴäŕäţĭ!!]",
  "language.gwi": "[!!Ğŵıċħ’ıň!!]",
  "language.hai": "[!!Ħąıđȁ!!]",
  "language.hat": "[!!Ĥȁıţįâņ Čřěơłȅ!!]",
  "language.hau": "[!!Ĥǻŭšā!!]",
  "language.haw": "[!!Ħâŵåĭĩäń!!]",
  "language.heb": "[!!Ĥȇƅŕȇŵ!!]",
  "language.her": "[!!Ħĕŕĕřơ!!]",
  "language.hil": "[!!Ĥĩľīģåŷŋōņ!!]",
  "language.him": "[!!Ŵėśţĕřņ Ƥãħãŕı ĺäƞģũăģėş!!]",
  "language.hin": "[!!Ħįŋďĭ!!]",
  "language.hit": "[!!Ħĩţťıţē!!]",
  "language.hmn": "[!!Mőŋģ!!]",
  "language.hmo": "[!!Ĥıŗĭ Mőţű!!]",
  "language.hrv": "[!!Ċŕơȃţįáƞ!!]",
  "language.hsb": "[!!Ũƿƿęŕ Şŏŕƀĭåń!!]",
  "language.hun": "[!!Ħũƞğąřĭȃŋ!!]",
  "language.hup": "[!!Ħŭƥǻ!!]",
  "language.hye": "[!!Ȁŕmęňįáŉ!!]",
  "language.iba": "[!!ĨƄàń!!]",
  "language.ibo": "[!!Īġƃō!!]",
  "language.ido": "[!!İđŏ!!]",
  "language.iii": "[!!Şĩĉħųąņ Ɏī!!]",
  "language.ijo": "[!!ĬĴơ łąƞğűàġėŝ!!]",
  "language.iku": "[!!Ĩńūķţīţųť!!]",
  "language.ile": "[!!Őččĭđȇńŧàŀ!!]",
  "language.ilo": "[!!Īļơƙơ!!]",
  "language.ina": "[!!Įňţěŕĺıņĝŭȁ (Īňţĕŗŉąţıōŋåŀ Ăųxıłĭąŗɏ Ĺàńģűȃğĕ Ãşśōċıǻţıơņ)!!]",
  "language.inc": "[!!Īńđįċ ļãƞģűąġĕş!!]",
  "language.ind": "[!!Īŋďőŉĕšīáƞ!!]",
  "language.ine": "[!!İńďŏ-Ěũŗŏƿěäń ĺáńģůãĝĕş!!]",
  "language.inh": "[!!Īńğůśĥ!!]",
  "language.ipk": "[!!Ĭŉűƥĩãǫ!!]",
  "language.ira": "[!!Ĩŕąŉĭǻň łąŉğųáġęš!!]",
  "language.iro": "[!!Ĩřŏǭŭōįăņ łǻŉğŭȁğęŝ!!]",
  "language.isl": "[!!Ĩčȇłâƞďĭċ!!]",
  "language.ita": "[!!Ĭţãłĩȃń!!]",
  "language.jav": "[!!ĵãvāńĕśē!!]",
  "language.jbo": "[!!ĻơĴɓąŋ!!]",
  "language.jpn": "[!!ĵâƥâŋēśĕ!!]",
  "language.jpr": "[!!ĵűđȅŏ-Ƥȇřśįåŋ!!]",
  "language.jrb": "[!!ĵųđĕơ-Ąŗäƀıć!!]",
  "language.kaa": "[!!Ƙąŗã-Ƙãľƥâĸ!!]",
  "language.kab": "[!!Ķàƀȳŀȇ!!]",
  "language.kac": "[!!Ķȃċħīŋ!!]",
  "language.kal": "[!!Ƙȁļāàľłĩśūŧ!!]",
  "language.kam": "[!!ƘǻmƄâ!!]",
  "language.kan": "[!!Ƙȁŉŉäđȃ!!]",
  "language.kar": "[!!Ƙăŗėň ŀāňġũâģěš!!]",
  "language.kas": "[!!Ķăşħmıŗı!!]",
  "language.kat": "[!!Ģȅơřġĩȃň!!]",
  "language.kau": "[!!Ķăŋųřı!!]",
  "language.kaw": "[!!Ƙäŵı!!]",
  "language.kaz": "[!!Ķåżäĸĥ!!]",
  "language.kbd": "[!!Ķāƅȁřďĩăƞ!!]",
  "language.kha": "[!!Ķĥăšī!!]",
  "language.khi": "[!!Ƙĥőĩŝâƞ ĺâŉĝűãğėş!!]",
  "language.khm": "[!!Ćĕńťŗâľ Ķħměŗ!!]",
  "language.kho": "[!!Şáĸăń!!]",
  "language.kik": "[!!Ƙĩķűŷũ!!]",
  "language.kin": "[!!Ķĭƞŷàřŵäňďā!!]",
  "language.kir": "[!!Ķŷřğŷƶ!!]",
  "language.kmb": "[!!Ķĩmɓůƞďū!!]",
  "language.kok": "[!!Ķơŋķāņĭ!!]",
  "language.kom": "[!!Ķőmī!!]",
  "language.kon": "[!!Ƙōňġơ!!]",
  "language.kor": "[!!Ķŏŗěȃņ!!]",
  "language.kos": "[!!Ƙōşŗāȅȃŉ!!]",
  "language.kpe": "[!!Ķƥęŀļē!!]",
  "language.krc": "[!!Ķąřàćħąƴ-ʙáĺĸăŗ!!]",
  "language.krl": "[!!Ƙąŗęľĭáň!!]",
  "language.kro": "[!!Ķŗű ŀáƞĝųàģȅś!!]",
  "language.kru": "[!!Ƙŭřůĸħ!!]",
  "language.kua": "[!!Ķŵąņɏāmă!!]",
  "language.kum": "[!!Ķűmȳĸ!!]",
  "language.kur": "[!!Ķŭřďĩşĥ!!]",
  "language.kut": "[!!Ƙųţēņȁı!!]",
  "language.lad": "[!!Ĺäďıńő!!]",
  "language.lah": "[!!Ľăħƞďǻ!!]",
  "language.lam": "[!!ĽȁmƄą!!]",
  "language.lao": "[!!Ŀȁō!!]",
  "language.lat": "[!!Łăŧıň!!]",
  "language.lav": "[!!Łąŧvįąň!!]",
  "language.lez": "[!!Ľėźģĥīȃŉ!!]",
  "language.lim": "[!!ĽĭmƂűřĝįŝħ!!]",
  "language.lin": "[!!Ļīňģåŀȃ!!]",
  "language.lit": "[!!Ŀıťĥŭáŉīâň!!]",
  "language.lol": "[!!Mŏƞġō!!]",
  "language.loz": "[!!Ļŏžĩ!!]",
  "language.ltz": "[!!ĽųxĕmƂơůřĝĩşĥ!!]",
  "language.lua": "[!!Ļũƀā-Ŀűľůâ!!]",
  "language.lub": "[!!Łŭƀä-Ƙăťȁŉģã!!]",
  "language.lug": "[!!Ğâƞďá!!]",
  "language.lui": "[!!Ļūĭşȅŋő!!]",
  "language.lun": "[!!Ļūńďȁ!!]",
  "language.luo": "[!!Ļŭő (Ķȅŉɏǻ āņđ Ţǻňźąŉĭà)!!]",
  "language.lus": "[!!Ĺũŝĥâĩ!!]",
  "language.mad": "[!!Måďũŕěŝȅ!!]",
  "language.mag": "[!!Màĝȃĥĩ!!]",
  "language.mah": "[!!Màŗšħäĺĺȇŝȅ!!]",
  "language.mai": "[!!Máīťĥįľĭ!!]",
  "language.mak": "[!!Máƙąśȃŕ!!]",
  "language.mal": "[!!Mâŀâŷäļăm!!]",
  "language.man": "[!!Màńđįƞğơ!!]",
  "language.map": "[!!Ąŭŝťřōńēŝıâň ŀăŉğūȁĝēŝ!!]",
  "language.mar": "[!!Mąŕàŧĥį!!]",
  "language.mas": "[!!Mãşâī!!]",
  "language.mdf": "[!!Mőƙşħá!!]",
  "language.mdr": "[!!Mąƞđãŕ!!]",
  "language.men": "[!!Mĕŉďĕ!!]",
  "language.mga": "[!!Ĩřĭśĥ, Mįđđŀȇ (900-1200)!!]",
  "language.mic": "[!!Mĭčmǻč!!]",
  "language.min": "[!!Mįňǻƞģķȁƃâũ!!]",
  "language.mis": "[!!Ūņċơďėđ ŀăņģũàğěş!!]",
  "language.mkd": "[!!Mâċėđơŉĭåń!!]",
  "language.mkh": "[!!Mőƞ-Ķĥmȇŕ ľȃŋģŭāĝěş!!]",
  "language.mlg": "[!!Måŀāģăśȳ!!]",
  "language.mlt": "[!!Mȁļţēŝę!!]",
  "language.mnc": "[!!Mǻŉčĥũ!!]",
  "language.mni": "[!!Mąňıƿũřı!!]",
  "language.mno": "[!!Mâņŏɓő łãŋġũâğȇŝ!!]",
  "language.moh": "[!!Mŏĥáŵƙ!!]",
  "language.mol": "[!!Mőŀđávįâŋ!!]",
  "language.mon": "[!!Mơŉĝơľĩȃň!!]",
  "language.mos": "[!!Mōŝśī!!]",
  "language.mot": "[!!Mơŋŧėŉȅĝŗĩň!!]",
  "language.mri": "[!!Mäơŗį!!]",
  "language.msa": "[!!Mãļȁƴ!!]",
  "language.mul": "[!!Műŀťīƿļĕ ĺäŉĝűåğěš!!]",
  "language.mun": "[!!Mūņđâ ŀàŉĝŭāģěŝ!!]",
  "language.mus": "[!!Ćŕēėķ!!]",
  "language.mwl": "[!!Mīřãŋďęŝē!!]",
  "language.mwr": "[!!Mǻŗŵąŕį!!]",
  "language.mya": "[!!Ɓųŕmȇşě!!]",
  "language.myn": "[!!Màɏãŉ ļǻƞĝųâĝēś!!]",
  "language.myv": "[!!Ėŗżȳå!!]",
  "language.nah": "[!!Ņàħūãţľ ĺäŋğŭȁğęŝ!!]",
  "language.nai": "[!!Ňŏŗŧħ Âmȇřĭċȁŉ Įŉđīǻƞ ĺāŉĝŭąğęŝ!!]",
  "language.nap": "[!!Ɲěâƿŏłĭţâň!!]",
  "language.nau": "[!!Ɲâůŕů!!]",
  "language.nav": "[!!ŇȁvåĴŏ!!]",
  "language.nbl": "[!!Şŏůŧĥ Ņďȇƃēľȇ!!]",
  "language.nde": "[!!Ņōřţħ ŃđęƄĕŀę!!]",
  "language.ndo": "[!!Ňďőňģã!!]",
  "language.nds": "[!!Śäxŏŋ, Ŀơŵ!!]",
  "language.nep": "[!!Ņėƥäŀı!!]",
  "language.new": "[!!Ňĕŵȃřĭ!!]",
  "language.nia": "[!!Ɲıȃŝ!!]",
  "language.nic": "[!!Ńĭğĕř-Ķōŗđōƒâņīāň łâņĝűăğěś!!]",
  "language.niu": "[!!Ŋĩůēȁņ!!]",
  "language.nld": "[!!Đųţċħ!!]",
  "language.nno": "[!!Ŋƴŋőřśĸ, Ŋŏŗŵēģīăŋ!!]",
  "language.nob": "[!!Ňơřŵĕģıȃņ Ɓőķmåľ!!]",
  "language.nog": "[!!Ņŏģáĩ!!]",
  "language.non": "[!!Ňőŗšě, Őŀđ!!]",
  "language.nor": "[!!Ņŏŕŵȇģįāŉ!!]",
  "language.nqo": "[!!Ň’Ķő!!]",
  "language.nso": "[!!Šŏťħŏ, Ŋōřţĥȅŗň!!]",
  "language.nub": "[!!Ňŭɓīȃŉ ŀäňğűāġĕŝ!!]",
  "language.nwc": "[!!Őļď Ŋēŵāŗĭ!!]",
  "language.nya": "[!!ŊɏȁƞĴá!!]",
  "language.nym": "[!!Ɲȳámŵȅźį!!]",
  "language.nyn": "[!!Ņɏãƞķōłĕ!!]",
  "language.nyo": "[!!Ɲƴőŕō!!]",
  "language.nzi": "[!!Ɲżĩmá!!]",
  "language.oci": "[!!Ơčćįťäņ (ƥōşť 1500)!!]",
  "language.oji": "[!!ƠĴĩƀŵâ!!]",
  "language.ori": "[!!Ơřĭŷā!!]",
  "language.orm": "[!!Őŕőmơ!!]",
  "language.osa": "[!!Ơśàġē!!]",
  "language.oss": "[!!Őşŝĕťįč!!]",
  "language.ota": "[!!Ŧůřĸįşĥ, Ơťŧőmåň (1500-1928)!!]",
  "language.oto": "[!!Ŏťōmīãň ľāŋģŭǻġȇš!!]",
  "language.paa": "[!!Ƥăƥųáņ ľǻŋģŭǻģęś!!]",
  "language.pag": "[!!Ƥăņġãŝıŋȃń!!]",
  "language.pal": "[!!Ƥåĥĺȁvī!!]",
  "language.pam": "[!!Ƥāmƿäŋġȁ!!]",
  "language.pan": "[!!ƤųňĴâƃĭ!!]",
  "language.pap": "[!!Ƥåƥįámĕņţŏ!!]",
  "language.pau": "[!!Ƥäľǻũãň!!]",
  "language.peo": "[!!Ƥėŗŝīåŋ, Ōļď (ćȁ.600-400 ʙ.Ć.)!!]",
  "language.phi": "[!!Ƥĥıŀıƿƥıƞě ĺȃńĝũāģęš!!]",
  "language.phn": "[!!Ƥħơȅņįčĭàň!!]",
  "language.pli": "[!!Ƥâłī!!]",
  "language.pol": "[!!Ƥŏĺĩśĥ!!]",
  "language.pon": "[!!Ƥŏħŋƿěįàņ!!]",
  "language.por": "[!!Ƥơŗţųğũĕśȅ!!]",
  "language.pra": "[!!Ƥŕâķřĭť ĺäńġűǻĝęš!!]",
  "language.pro": "[!!Ƥŕōvȅŉçął, Őļď (ţŏ 1500)!!]",
  "language.pus": "[!!Ƥůšħťő!!]",
  "language.que": "[!!Ǭůĕĉĥųă!!]",
  "language.raj": "[!!ƦãĴáśţħáŉį!!]",
  "language.rap": "[!!Ʀäƿâńůį!!]",
  "language.rar": "[!!Řáŗŏţōŋğàń!!]",
  "language.roa": "[!!Ʀơmăņċě ľăŋģũàĝėś!!]",
  "language.roh": "[!!Ŕōmǻŋśĥ!!]",
  "language.rom": "[!!Ʀőmâŉȳ!!]",
  "language.ron": "[!!Ʀŏmãŉīáņ!!]",
  "language.run": "[!!Ŗůńďĭ!!]",
  "language.rup": "[!!Māĉȅđō-Ŕŏmąńıàŋ!!]",
  "language.rus": "[!!Ŗŭşşĭȁŉ!!]",
  "language.sad": "[!!Śäńďäŵȅ!!]",
  "language.sag": "[!!Šåŉģŏ!!]",
  "language.sah": "[!!Ɏäƙũţ!!]",
  "language.sai": "[!!Ŝōůťħ Ãmēŕīċąŋ İŋđıȃņ łåńġűȁĝēš!!]",
  "language.sal": "[!!Śȃļıšħãň ļăŉğųăġĕş!!]",
  "language.sam": "[!!Śămąŗĭţáň Āŕǻmàĩć!!]",
  "language.san": "[!!Šȁŋśƙŕıţ!!]",
  "language.sas": "[!!Śȃšāĸ!!]",
  "language.sat": "[!!Ŝãŋţăĺĩ!!]",
  "language.scn": "[!!Śįčıľĩȁƞ!!]",
  "language.sco": "[!!Ŝĉōţş!!]",
  "language.sel": "[!!Šȅļĸůƥ!!]",
  "language.sem": "[!!Şĕmįŧįĉ ľȁŋğũâģěś!!]",
  "language.sga": "[!!Ĩŗĭšĥ, Ơŀď (ţō 900)!!]",
  "language.sgn": "[!!Ŝĭĝŋ Ĺăņģųăğēš!!]",
  "language.shn": "[!!Şħåŉ!!]",
  "language.sid": "[!!Ŝĩđāmơ!!]",
  "language.sin": "[!!Šīƞĥăłȅŝȇ!!]",
  "language.sio": "[!!Šīơūáƞ łâŋġŭåġěš!!]",
  "language.sit": "[!!Šįńő-ŤīƂĕťȃƞ ļáŉģűåġěś!!]",
  "language.sla": "[!!Ŝļȃvĭč ľǻňģűȁĝęš!!]",
  "language.slk": "[!!Ŝļŏvȁƙ!!]",
  "language.slv": "[!!Šľővěƞĩâņ!!]",
  "language.sma": "[!!Śŏűţħęŗń Ŝāmī!!]",
  "language.sme": "[!!Ňōŗţħȇřń Śąmı!!]",
  "language.smi": "[!!Ŝåmĩ ĺäŋğŭǻġȅŝ!!]",
  "language.smj": "[!!Ĺůļę Ŝämĩ!!]",
  "language.smn": "[!!Įƞąŗī Śámı!!]",
  "language.smo": "[!!Šàmŏȃń!!]",
  "language.sms": "[!!Ŝƙơŀť Ŝąmī!!]",
  "language.sna": "[!!Şĥōńȁ!!]",
  "language.snd": "[!!Ŝīŋďĥį!!]",
  "language.snk": "[!!Śőŉĩňĸē!!]",
  "language.sog": "[!!Šơĝďįȁń!!]",
  "language.som": "[!!Šơmǻłĭ!!]",
  "language.son": "[!!Śōńģħȁī ļąņĝűāğĕş!!]",
  "language.sot": "[!!Šŏŧħō, Şơūŧĥȅŕň!!]",
  "language.spa": "[!!Ŝƥåŉıŝĥ!!]",
  "language.sqi": "[!!Ãŀɓáņıąņ!!]",
  "language.srd": "[!!Śàŕďĩńįăņ!!]",
  "language.srn": "[!!Şŕàňåń Ţơńğơ!!]",
  "language.srp": "[!!Ŝēŕɓįȁň!!]",
  "language.srr": "[!!Şėřėŗ!!]",
  "language.ssa": "[!!Ŋįļō-Şāĥąŗáņ łǻƞĝūăġěş!!]",
  "language.ssw": "[!!Šŵãťĭ!!]",
  "language.suk": "[!!Ŝūķůmä!!]",
  "language.sun": "[!!Ŝũņđàņėŝĕ!!]",
  "language.sus": "[!!Śũšű!!]",
  "language.sux": "[!!Šűměŗĭáň!!]",
  "language.swa": "[!!Šŵȃĥĩŀī!!]",
  "language.swe": "[!!Šŵėďıśħ!!]",
  "language.syc": "[!!Ċļäŝşĩčȃĺ Ŝɏŗĩȁĉ!!]",
  "language.syr": "[!!Šȳřıâĉ!!]",
  "language.tah": "[!!Ŧâħįţĩȃƞ!!]",
  "language.tai": "[!!Ťãĭ ľáŉğűąĝęš!!]",
  "language.tam": "[!!Ťȁmıł!!]",
  "language.tat": "[!!Ťåŧäŗ!!]",
  "language.tel": "[!!Ťėļųğų!!]",
  "language.tem": "[!!Ŧĩmņē!!]",
  "language.ter": "[!!Ţȇŕȇńơ!!]",
  "language.tet": "[!!Ŧȅťūm!!]",
  "language.tgk": "[!!ŢăĴĩƙ!!]",
  "language.tgl": "[!!Ťȁġȁļőğ!!]",
  "language.tha": "[!!Ţĥâī!!]",
  "language.tig": "[!!Ŧįĝŕȇ!!]",
  "language.tir": "[!!Ţĩğŗīƞɏȃ!!]",
  "language.tiv": "[!!Ţĭv!!]",
  "language.tkl": "[!!Ťōķęľāū!!]",
  "language.tlh": "[!!ŢļħĬńğȃň-Ĥőŀ!!]",
  "language.tli": "[!!Ŧŀĭńģĩŧ!!]",
  "language.tmh": "[!!Ŧămáśħĕķ!!]",
  "language.tog": "[!!Ţơŋĝá (Ňƴâŝä)!!]",
  "language.ton": "[!!Ţőŋġà (Ţơńġǻ İšłàŋđś)!!]",
  "language.tpi": "[!!Ŧŏĸ Ƥışĩŉ!!]",
  "language.tsi": "[!!Ŧśĭmŝĥĭȃņ!!]",
  "language.tsn": "[!!Ţšŵăņá!!]",
  "language.tso": "[!!Ťŝőņĝȃ!!]",
  "language.tuk": "[!!Ţŭŗķmēň!!]",
  "language.tum": "[!!Ŧůmƀūƙą!!]",
  "language.tup": "[!!Ŧųƿī ŀãňğűâĝęš!!]",
  "language.tur": "[!!Ťŭŗĸĭşĥ!!]",
  "language.tut": "[!!Ǻļťąĭĉ ŀǻņģůàģēš!!]",
  "language.tvl": "[!!Ŧũväľū!!]",
  "language.twi": "[!!Ŧŵį!!]",
  "language.tyv": "[!!Ŧūvĭƞĩȁŉ!!]",
  "language.udm": "[!!Ůďmũŗţ!!]",
  "language.uga": "[!!Űġáŕıťĩċ!!]",
  "language.uig": "[!!Űƴģĥũŗ!!]",
  "language.ukr": "[!!Ūĸřãīŋīàń!!]",
  "language.umb": "[!!Ūmƅųņďŭ!!]",
  "language.und": "[!!Ņơŧ şƿěćıƒīēď!!]",
  "language.urd": "[!!Ųŕđū!!]",
  "language.uzb": "[!!Ųžƃěƙ!!]",
  "language.vai": "[!!Váĭ!!]",
  "language.ven": "[!!Vėŋďâ!!]",
  "language.vie": "[!!Vįėŧņāmėşĕ!!]",
  "language.vol": "[!!Vōļȃƥüƙ!!]",
  "language.vot": "[!!Vơťīċ!!]",
  "language.wak": "[!!Ŵäķǻşĥáń ļàńğųàģȅš!!]",
  "language.wal": "[!!Ŵŏĺąɏŧŧă!!]",
  "language.war": "[!!Ŵàřãƴ!!]",
  "language.was": "[!!Ŵäşĥō!!]",
  "language.wen": "[!!Śōŗƅīăń ļȃƞġűȃğęš!!]",
  "language.wln": "[!!Ŵȁłłơơŉ!!]",
  "language.wol": "[!!Ŵőĺơƒ!!]",
  "language.xal": "[!!Őıŕâţ!!]",
  "language.xho": "[!!Xĥơśą!!]",
  "language.yao": "[!!Ƴăő!!]",
  "language.yap": "[!!Ɏȁƥěśē!!]",
  "language.yid": "[!!Ÿįďđīŝħ!!]",
  "language.yor": "[!!ŸŏŗũƂā!!]",
  "language.ypk": "[!!Ƴųƥĭƙ ļăƞğŭåĝěš!!]",
  "language.zap": "[!!Żåƿơťȇč!!]",
  "language.zbl": "[!!ßľĩśşɏmƃōłš!!]",
  "language.zen": "[!!Źȅƞāġą!!]",
  "language.zgh": "[!!Šŧăńďȁŕđ Mōřōčćäň Ţȁmážīğĥť!!]",
  "language.zha": "[!!Ƶħūăŉġ!!]",
  "language.zho": "[!!Ċħįŋĕśē!!]",
  "language.znd": "[!!Žǻņđė ľȃŉĝŭǻģȅś!!]",
  "language.zul": "[!!Źũĺū!!]",
  "language.zun": "[!!Žũƞī!!]",
  "language.zxx": "[!!Ŋōţ àƥƥľıċäƀŀȇ!!]",
  "language.zza": "[!!Ƶãźȁķĩ!!]",
  "crawl.finishReason.NORMAL": "[!!Ɲōřmåľ!!]",
  "crawl.finishReason.ABORT": "[!!Ąƀŏŕť!!]",
  "crawl.finishReason.NOT_MODIFIED": "[!!Ɲơţ mōďĩƒįĕď!!]",
  "crawlAttemptX": "[[[!Crawl attempt {attemptNr}!]]]",
  "contactType.TECHNICAL_POINT_OF_CONTACT": "[!!Ŧęčĥņĩĉǻŀ ƥơįňŧ ōƒ ĉŏŉţăĉţ!!]",
  "contactType.ADMINISTRATIVE_POINT_OF_CONTACT": "[!!Ăďmĭņĩŝťřäţĭvē ƥőıńť ơƒ ĉŏƞŧǻčţ!!]",
  "contactType.POINT_OF_CONTACT": "[!!Ƥōĩņŧ ōƒ ćőňťàċţ!!]",
  "contactType.ORIGINATOR": "[!!Ơŗįĝıňāťŏŗ!!]",
  "contactType.METADATA_AUTHOR": "[!!Męţáđăţä ãűťħơŗ!!]",
  "contactType.PRINCIPAL_INVESTIGATOR": "[!!Ƥřīņċīƿȃŀ ĩņvēśţįġâťơř!!]",
  "contactType.AUTHOR": "[!!Ȁůŧĥőŗ!!]",
  "contactType.CONTENT_PROVIDER": "[!!Ćŏŋţȇŉţ ƥřōvıďȇř!!]",
  "contactType.CUSTODIAN_STEWARD": "[!!Ćůşŧŏđīȁŉ şŧěŵăŕď!!]",
  "contactType.DISTRIBUTOR": "[!!Ɖįśŧřįƅůťōř!!]",
  "contactType.EDITOR": "[!!Ȇđĭŧōŗ!!]",
  "contactType.OWNER": "[!!Ŏŵņēŗ!!]",
  "contactType.PROCESSOR": "[!!Ƥŗơćȇśşơŕ!!]",
  "contactType.PUBLISHER": "[!!Ƥűƅĺĭŝħęŗ!!]",
  "contactType.USER": "[!!Ůŝȅř!!]",
  "contactType.PROGRAMMER": "[!!Ƥřőĝŗàmmȇŕ!!]",
  "contactType.CURATOR": "[!!Ċūŗǻŧŏŕ!!]",
  "contactType.DATA_ADMINISTRATOR": "[!!Ɖǻŧä ȃđmįńışťřãŧōŗ!!]",
  "contactType.SYSTEM_ADMINISTRATOR": "[!!Śƴşŧēm ąđmīŉīśţŗåţŏř!!]",
  "contactType.TEMPORARY_HEAD_OF_DELEGATION": "[!!Ťȅmƿőŗăřŷ ħěǻđ őƒ đĕłēğąťīőŋ!!]",
  "contactType.TEMPORARY_DELEGATE": "[!!Ŧęmƥōŕãŕȳ ďěļėġăŧē!!]",
  "contactType.REGIONAL_NODE_REPRESENTATIVE": "[!!Ŕȇġĭōŋąľ ńơđē ŗęƿŕȇŝęńŧăţĭvȇ!!]",
  "contactType.NODE_STAFF": "[!!Ńōďė śŧâƒƒ!!]",
  "contactType.HEAD_OF_DELEGATION": "[!!Ħĕàđ ơƒ đėŀĕġąţĭŏń!!]",
  "contactType.NODE_MANAGER": "[!!Ńơđȇ mãńăĝȅř!!]",
  "contactType.ADDITIONAL_DELEGATE": "[!!Ąďďįţĩơŋáŀ ďěĺēĝàŧė!!]",
  "details": "[!!Đēťăĩłś!!]",
  "contactDetails": "[!!Čōņţȁćť đėţáĩľş!!]",
  "commentDetails": "[!!Ċőmmĕňţ ďȇţȁįľŝ!!]",
  "endpointDetails": "[!!Ēƞďƿōıņţ ďęţãįļś!!]",
  "identifierDetails": "[!!Ĭđěńťıƒıěř đēŧáĭŀš!!]",
  "machineTagDetails": "[!!Mȁćĥįňę ţȁĝ ďȇţâīŀş!!]",
  "tagDetails": "[!!Ţąģ đĕţăıŀś!!]",
  "newTag": "[!!Ŋęŵ ťǻġ!!]",
  "newAddress": "[!!Ɲȇŵ àđďŕȇśş!!]",
  "newEmail": "[!!Ńęŵ ěmăįł!!]",
  "newPhone": "[!!Ɲȅŵ ƥĥőņė!!]",
  "newHomepage": "[!!Ňęŵ ĥŏměƿäĝę!!]",
  "newUserId": "[!!Ńęŵ ůşēŗ ĨĐ!!]",
  "newPosition": "[!!Ŋěŵ ƿŏşīţıőň!!]",
  "datasetType.OCCURRENCE": "[!!Ŏĉĉųŕŗȅńċě!!]",
  "datasetType.CHECKLIST": "[!!Ćħėčƙļĭşţ!!]",
  "datasetType.SAMPLING_EVENT": "[!!Ŝãmƥľıńĝ ėvȅŋť!!]",
  "datasetType.METADATA": "[!!Mėţåđȃţȁ!!]",
  "constituentsDatasets": "[!!Ċőňšţįťŭȅŉţ đȃţȁşęťś!!]",
  "error.message": "[!!Ęŕŗơŗ!!]",
  "error.description": "[!!Ăƞ ęŕřơŕ ħȁƿƿěńȅď ŵħĩŀě ťŗɏıņģ ţơ ƿŗŏĉěšŝ ɏōůŕ ŗěǭŭęşţ. Ƥļěȁŝė ŗȅƥơřť ŧĥę ęŕŗőŗ ǻť ĥŧţƥś://ģįţĥųƂ.ĉŏm/ģƄıƒ/ƿōŕťáł-ƒȅěđɓãćĸ/īśşųěś/ŉȅŵ!!]",
  "error.description.syncState": "[!!Ŧĥĩş mīğĥť ħävȅ ƒáıľęď đůě ťŏ ĪƤŦ Ɓůģ 1344. Ƥľěǻšė ųƿġŗăďę ťơ ţħě ļáţĕśŧ İƤŢ ťō ūŝĕ ţĥıš ƒůňčŧįơņāļīŧŷ.!!]",
  "error.contact.duplicate": "[!!Ȳŏū ĉàň'ŧ åďď ţħĕ šȁmě čơŋţàćŧ ŧŵįĉȅ!!]",
  "datasetConstituent": "[!!Ċơňšţĭŧųěƞŧ ďáťàŝēţŝ!!]",
  "doi": "[!!Ďīğīťȃł ƠƅĴėćť İďęňťĩƒįēŗ!!]",
  "alias": "[!!Ăŀĩǻš!!]",
  "publishingOrganization": "[!!ƤůƄĺıśħįŉğ ōŗģǻņīžáŧĩőņ!!]",
  "servingInstallation": "[!!Şęŕvıńģ ĩňšťȃĺŀàŧĭōƞ!!]",
  "citation": "[!!Ċįţāťĩōň!!]",
  "rights": "[!!Řīģĥţš!!]",
  "updateFrequency": "[!!Ųƿđáţē ƒřȇǫũēņĉɏ!!]",
  "subtype": "[!!ŞůƄťƴƥę!!]",
  "external": "[!!Ęxŧȇŕňâł!!]",
  "license": "[!!Ľĭćĕňşȅ!!]",
  "important": "[!!Ĭmƥŏŗţāŋť!!]",
  "warning.datasetLicense": "[!!Ĉĥàņġıƞĝ ţħĩŝ ŵıłŀ ũƿđâţĕ àŀļ ŏċćũřřȇńćę ŕęĉőŕďŝ!!]",
  "warning.datasetAutoUpdate": "[!!Űśȇ ŵīťĥ ćáųŧįơņ - đīśãƅŀęś ăŭŧŏmàťȇđ ůƥđąŧēś!!]",
  "warning.datasetDOI": "[!!Ċħȁŉġȅś ŝħōůľď Ƃė máďě ųŉđěřśţåňđįŉģ ţĥĕ ċōņšėǫūȅňćěŝ!!]",
  "warning.publishingOrganization": "[!!Ĉĥâƞģįŉĝ ťħıś ŵĭĺľ ūƿđȃŧȅ ĥōšŧĭňğ őřĝáŋīƶǻťīōń ơƞ āĺł ơččũŗřēňčĕ ŗȅĉőŗđŝ.!!]",
  "warning.hostingOrganization": "[!!Ċħàŋġīňġ ŧħīś ŵīļľ ůƿďâţę ħơŝťĩŋğ ơŕġàƞīżȃŧıőņ őň åĺł ơċćųřřęńćē ŗĕċơřđş.!!]",
  "warning.duplicateDataset": "[!!Ċħǻńģĭňĝ ŧĥīŝ ŵįłŀ ĎĘĽĔŢĘ ǻľł ōĉĉűŕŗȅņčĕ ŗĕĉōŕďş!!]",
  "warning.installationType": "[!!Ĥåŝ śıġńĩƒĭčäņŧ ĩmƿăĉť ōŋ ćŕāŵŀęřŝ!!]",
  "warning.endorsingNode": "[!!Ŧħē ŋŏďĕ ţĥȁţ ĥăş vĕŕĭƒįȅđ ţĥĕ ōřğȁŉıƶāţįōň šħōűĺď ƥŭƃĺīšĥ ţĥŕơūģħ ĢƁİƑ!!]",
  "warning.endorsementApproved": "[!!Ĥåş ťĥė ȇņđőřśĕmȅŋţ ƀȇĕń ăƥƿŕŏvĕđ?!!]",
  "warning.ingestionFilters": "[!!Įƒ ȳơū ħávȇ ƒıļťėŕş ěŉåƂłēđ ŷōů mįğĥť ŉōţ śĕē àŋȳţĥīňģ!!]",
  "lockAutoUpdates": "[!!Ŀŏĉƙ ąůţŏ ūƿđäŧȇŝ!!]",
  "installation": "[!!Ĩńŝŧãļłăţįŏƞ!!]",
  "parentDataset": "[!!Ƥȁřěŉţ đàŧȁşȅť!!]",
  "duplicateDataset": "[!!Ɖũƥļīćȁŧė ơƒ Đàţàŝȇţ!!]",
  "citationIdentifier": "[!!Ċīťăŧįơƞ ĩďėńťīƒįėŗ!!]",
  "yes": "[!!Ɏȅš!!]",
  "no": "[!!Ɲő!!]",
  "beenDeleted.contact": "[!!Ċōŋţàċŧ ĥàś Ƃȅėń ďĕĺȅţȅď!!]",
  "beenDeleted.comment": "[!!Ċơmměƞť ĥåş ƅėęņ ďęĺȇŧȅđ!!]",
  "beenDeleted.endpoint": "[!!Ěńďƥŏĭƞť ĥąŝ ƃęėŋ đĕľėŧęď!!]",
  "beenDeleted.identifier": "[!!Ĩďȇŋŧıƒĩȅŕ ĥâş ƀěȅƞ đēĺēťĕđ!!]",
  "beenDeleted.machineTag": "[!!Măćħīňē ťâĝ ĥàş Ƅėęŉ đęļėťěď!!]",
  "beenDeleted.tag": "[!!Ťàĝ ĥäş ƅȇēņ ďěŀėŧĕď!!]",
  "beenDeleted.defaultValue": "[!!Đěƒãůŀŧ vȃŀųȇ ĥáš ƀĕēň đĕľěŧȇđ!!]",
  "beenSaved.contact": "[!!Ćŏňŧáćţ ĥåš Ƃęēƞ ŝȃvēď!!]",
  "beenSaved.comment": "[!!Ćōmmȅŋţ ħǻš ƅēěņ ŝȃvȇđ!!]",
  "beenSaved.endpoint": "[!!Ȅňďƥőıńť ĥāŝ ɓĕȇŋ śăvȅđ!!]",
  "beenSaved.identifier": "[!!İďęŉŧīƒıęŕ ĥăś Ƃěęŉ ŝãvēđ!!]",
  "beenSaved.machineTag": "[!!Måćĥīŋē ŧăģ ĥäŝ ɓėēŉ şȁvěđ!!]",
  "beenSaved.tag": "[!!Ţåģ ĥäŝ Ƅȅȇƞ śävȅď!!]",
  "beenSaved.defaultValue": "[!!Đȅƒàůłţ vȃłųȇ ĥāş ƀėĕŉ ŝãvȇđ!!]",
  "beenCreated.organization.title": "[!!Ŏŕģãƞĩƶăťīŏŋ ĥäś ƅěěŋ ċŕěåţēđ šŭċćȇśšƒūľļȳ!!!]",
  "beenCreated.dataset.title": "[!!Ɗãťäśęţ ħãş ƅėȅņ ċřėǻŧęđ ŝůčĉėšşƒųłľƴ!!!]",
  "beenCreated.dataset.message": "[!!Ĩŧ ćǻƞ ťăĸę 10 mįńųťėš ƒŏř ťħē đäŧäŝȇŧ ŧő śĥơŵ ōƞ ŧĥę ŵęƄšıťĕ. Ƥľėåšē ţäķȇ ĩńţő ãĉċơůņť ťħåŧ đäťâśěŧ ņȅėđš ŧō Ƃę ċŗȁŵŀĕđ ȃńđ ũƥďāţȅđ ŵĥȃţ ĉãņ ťáķē ĥōůŕŝ.!!]",
  "beenCreated.installation.title": "[!!Įŋśţáłĺȁťīőń ħăš ɓȇęƞ ċŕȇáţĕď şũċċēşşƒůłĺȳ!!!]",
  "beenCreated.collection.title": "[!!Ĉơļłȅĉťĩơň ħâŝ ɓȅėƞ ĉŗȅăťȅđ šũċčęšśƒūłļŷ!!!]",
  "beenCreated.institution.title": "[!!Ĭňşŧīţűťīŏƞ ĥåš ƅėęň ćŕȇâťĕď šũĉćȇŝŝƒūŀļŷ!!!]",
  "beenCreated.person.title": "[!!Ƥęřšŏņ ħąş ƀȅėŉ ćŕęáťĕđ ŝųćċęśŝƒūŀľƴ!!!]",
  "installationType.BIOCASE_INSTALLATION": "[!!ʙĭőĆĀŚē!!]",
  "installationType.TAPIR_INSTALLATION": "[!!ŦĂƤĬƦ!!]",
  "installationType.HTTP_INSTALLATION": "[!!ĦŤŢƤ!!]",
  "installationType.IPT_INSTALLATION": "[!!İƤŢ!!]",
  "installationType.DIGIR_INSTALLATION": "[!!ƉĭĠĪŘ!!]",
  "installationType.SYMBIOTA_INSTALLATION": "[!!Ŝȳmƅĭōťä!!]",
  "servedDatasets": "[!!Šĕřvȅď ďãŧąśȇţš!!]",
  "crawlHistory": "[!!İƞģěşŧĩŏŋ ĥīşţơŗŷ!!]",
  "synchronizationHistory": "[!!Ŝɏŋčĥŗōŉıƶǻţıōŋ ħĩśťōŗɏ!!]",
  "synchronizeNow": "[!!Şȳŉćħŗŏƞĭžę ņōŵ!!]",
  "synchronize": "[!!Šƴňćĥřőňıžē!!]",
  "installationOverviewInfo": "[!!Ŧĥĩş ĭńƒŏŕmäţıŏŋ ȁƿƥėǻřŝ ŏŋ ŧħę įƞśţăĺłãťĩŏŋ ƿŗőƒįłȅ, įńšťȁļŀǻŧĩőň ƥàğěş, şęāřĉħ ŗĕśūłŧş, āƞđ ƀȅƴőňď.!!]",
  "installationType": "[!!İńşŧāŀļăŧĩōŉ ťȳƥě!!]",
  "disabled": "[!!ĐīşȃƄľȇđ!!]",
  "pendingEndorsements": "[!!Ƥęňďıńĝ ȅňďŏŕšȅmēŋŧş!!]",
  "endorsedOrganizations": "[!!Ęŉđōŗśēđ ơŗğȃňıźȃŧĭơŉš!!]",
  "endorsedDatasets": "[!!Ěņďơŗşěđ ďąŧąšęťś!!]",
  "participantStatus": "[!!Ƥąřţĩċĩƥăŉť şţáţűş!!]",
  "gbifRegion": "[!!ĢʙĬƑ Ŗęģĭőņ!!]",
  "continent": "[!!Ćŏņţįŋěŋŧ!!]",
  "participationStatus": "[!!Ƥāŗťīćįƥàţĩōń Śţāţűś!!]",
  "nodeType.COUNTRY": "[!!Čōũƞţřŷ!!]",
  "nodeType.OTHER": "[!!Ŏţĥȅŗ!!]",
  "participationStatus.VOTING": "[!!Vőťīƞğ!!]",
  "participationStatus.ASSOCIATE": "[!!Ǻşŝōćīāťȅ!!]",
  "participationStatus.OBSERVER": "[!!Őƃŝęŕvėŕ!!]",
  "participationStatus.FORMER": "[!!Ƒōŕmėŕ!!]",
  "participationStatus.AFFILIATE": "[!!Ȁƒƒıļįăťȅ!!]",
  "region.AFRICA": "[!!Ǻƒřĩċă!!]",
  "region.ASIA": "[!!Äŝĩā!!]",
  "region.EUROPE": "[!!Ēůŗőƥē!!]",
  "region.NORTH_AMERICA": "[!!Ņőřţħ Ȁmėŗĩčã!!]",
  "region.OCEANIA": "[!!Ŏčĕąņĩá!!]",
  "region.LATIN_AMERICA": "[!!Łåťĭń Ąmēřĩćã!!]",
  "region.ANTARCTICA": "[!!Åņŧăřćťıĉà!!]",
  "continent.AFRICA": "[!!Áƒřıćå!!]",
  "continent.ASIA": "[!!Áŝĭà!!]",
  "continent.EUROPE": "[!!Ęųŗőƿĕ!!]",
  "continent.NORTH_AMERICA": "[!!Ŋōŕťĥ Ȁmēŕĭċǻ!!]",
  "continent.OCEANIA": "[!!Ŏčęąŉīą!!]",
  "continent.SOUTH_AMERICA": "[!!Šőůťħ Ãmęŕıčã!!]",
  "continent.ANTARCTICA": "[!!Áńťářčŧīćá!!]",
  "exception.description.403": "[!!Šơŕŗɏ, ƴōū đơŉ'ť ĥâvĕ áċčēŝŝ ťŏ ŧħıš ƿäġę.!!]",
  "exception.description.404": "[!!Śŏŕŕȳ, ţĥȇ ƥäğě ŷōų vĩśīťěď ďőėş ňőť ȅxĩśŧ.!!]",
  "exception.description.500": "[!!Śőŗřɏ, ŧĥė şȇŗvęŕ ĩś ŕȅƿơŗţįńģ ȃń ēŕŕơř.!!]",
  "exception.description.523": "[!!Şōřřŷ, ŧĥȇ šěřvȇŕ ıš ůŋřęåćħåƄľĕ. Ƥēřĥąƿś, ŷōů āřĕ ơƒƒłīńě.!!]",
  "exception.back": "[!!Ɓãĉƙ ţő ďāşħɓŏǻŗđ!!]",
  "invalid.email": "[!!Ĕmāĩŀš īş īŋvăŀīď!!]",
  "invalid.phone": "[!!Ƥĥőņě įŝ ıňvåłįđ!!]",
  "invalid.homepage": "[!!Ħŏmȇƿǻĝě įš ĩŋvǻľīđ!!]",
  "invalid.url": "[!!ŮŖŁ įş ıŋvãłīď!!]",
  "invalid.url.logo": "[!!Ļŏğō űřľ ĭš ĭňvȃļīď!!]",
  "invalid.credentials": "[!!Īƞvȁŀīđ ūśęřňąmĕ ōř ƥåśšŵơŕď!!]",
  "invalid.doi": "[!!Ďĩğĭţāľ ŎƃĴȅċţ Įđĕņŧĭƒĩēŗ īş įňváļĭđ!!]",
  "invalid.postalCode": "[!!Ƥōśţãľ ċŏđȅ īś īŋvȁļĩď!!]",
  "error.title": "[!!Åŉ ěŗřơŗ ơććųŗŗȅď!!]",
  "error.title.syncState": "[!!Ƒǻīĺēđ ţơ ġȅť ıŉvȅŋţơřɏ!!]",
  "organizations": "[!!Ơŗġāƞıźăţīőņŝ!!]",
  "datasets": "[!!Ďâŧąśěţš!!]",
  "nodes": "[!!Ńōďȇš!!]",
  "users": "[!!Ũšĕŕş!!]",
  "newOrganization": "[!!Ňęŵ őŕģȃňĭƶåťĭŏŉ!!]",
  "newDataset": "[!!Ɲėŵ ďåŧãšĕŧ!!]",
  "newInstallation": "[!!Ņėŵ īņśŧȃĺĺȃťįơņ!!]",
  "user": "[!!Űşȇŕ!!]",
  "lastLogin": "[!!Ľäşť ļōġįň!!]",
  "settings": "[!!Şėťťıňğŝ!!]",
  "systemSettings": "[!!Ŝɏŝţȇm śȅţŧĩňğš!!]",
  "roles": "[!!Ŗơĺĕś!!]",
  "success": "[!!Šŭččėŝş!!]",
  "error": "[!!Ěŕřơŗ!!]",
  "endorsed.crawl.message": "[!!Ţĥıŝ ŵĭļł ťŗıĝģĕř ā ĉŕãŵŀ őƒ ŧĥě ďåţáşēŧ.!!]",
  "notEndorsed.crawl.message": "[!!Ŧĥīś ďáťãśėţ'ś ƿũƅļışħĭƞğ ơŕĝǻńĩžãŧįŏň īŝ ƞőť ėńđơŕśȇď! Ĉŕàŵĺĭňĝ ţĥįś đãťāşȅŧ ŝĥőūļď ơńĺɏ ƀė ďơŋę ıń ä ťȅšŧ ěňvĩřŏńmȇƞţ.!!]",
  "info.crawling": "[!!Ćřáŵłįňğ įŉ ƿŕơĝŗĕŝś!!]",
  "info.synchronizing": "[!!Ŝƴŉĉħŗơņĭƶăťĭơŋ ĩŉ ƥŗơĝŕęšş!!]",
  "installation.sync.message": "[!!Ŧħĩş ŵĭļŀ ţŗįģģėř â šŷŋćĥŕŏƞīźáťīőņ ōƒ ŧĥē ĭňŝŧąłŀäţĩőŋ.!!]",
  "duplicate": "[!!Đŭƿĺīĉâŧę!!]",
  "constituent": "[!!Ĉőňśţıţűĕňť!!]",
  "withNoEndpoint": "[!!Ŵıŧĥ ŉő ēŋďƥŏĩŉţ!!]",
  "institutions": "[!!Īńşţįťũţıőńş!!]",
  "persons": "[!!Ƥȇŗšơƞŝ!!]",
  "collections": "[!!Čōłłēċŧįōƞŝ!!]",
  "editContact": "[!!Ȅđįţ ȁ ċơŋţǻčŧ!!]",
  "newCollection": "[!!Ɲēŵ ćŏļľĕćťīŏņ!!]",
  "accessionStatus": "[!!Ǻċčěşŝĩōƞ śŧăťųş!!]",
  "active": "[!!Äĉţįvē!!]",
  "code": "[!!Ĉơďė!!]",
  "newInstitution": "[!!Ňȇŵ ĩňšŧĭţųţıōŉ!!]",
  "indexHerbariorumRecord": "[!!Ħēřƀäŕįŏřům řėćơŕď!!]",
  "institutionalGovernance": "[!!Įņśťįťűţĩōŉȃł ğővȅŕŋäŉćȅ!!]",
  "catalogUrl": "[!!Čǻŧåľơġ ŰƦĹ!!]",
  "details.organization": "[!!Őŗġāŉĭźåťıŏƞ đěŧąįļş!!]",
  "details.dataset": "[!!Đåŧăśȇŧ đęťãįľş!!]",
  "details.installation": "[!!İńšţãĺłāťĭőŋ đĕŧàĩĺś!!]",
  "details.user": "[!!Ųşęŕ đēţäĩłş!!]",
  "details.node": "[!!Ņőďȇ đēťàīłś!!]",
  "details.collection": "[!!Čōŀľėćťĩơƞ ďěţăīľś!!]",
  "details.person": "[!!Ƥȅŕŝơŋ ďęŧăĭļş!!]",
  "details.institution": "[!!Įńşţĩŧűŧĩơņ đėţãıĺś!!]",
  "details.contact": "[!!Ćőņťâċţ đęťāıļś!!]",
  "nResults": "[[[!{formattedNumber} {count, plural, zero {results} one {result} other {results}}!]]]",
  "nPages": "[[[!page {current}/{total}!]]]",
  "forQuery": "[[[! for '{query}'!]]]",
  "ok": "[!!ŎƘ!!]",
  "close": "[!!Ċŀőşę!!]",
  "viewOnGBIF": "[!!Vįȇŵ őň ĜßĨƑ.őŕġ!!]",
  "noInformation": "[!!Ňō ıņƒŏŗmāţĭŏƞ!!]",
  "button.showMore": "[!!Ŝħơŵ mŏŕė!!]",
  "button.showLess": "[!!Šĥōŵ ĺēşš!!]",
  "button.about": "[!!ĀƂōųŧ!!]",
  "personalCollection": "[!!Ƥěřśơńāł ċōĺłĕćţĩōŉ!!]",
  "accessionStatus.INSTITUTIONAL": "[!!İŉšţĭťũŧĭōŋäĺ!!]",
  "accessionStatus.PROJECT": "[!!ƤŗơĴėćŧ!!]",
  "preservationType.NO_TREATMENT": "[!!Ŋō ţŗȇăţmĕŋţ!!]",
  "preservationType.ALCOHOL": "[!!Ăľĉŏħơŀ!!]",
  "preservationType.DEEP_FROZEN": "[!!Ďěĕƿ ƒŗōżěŉ!!]",
  "preservationType.DRIED": "[!!Đŕĩēđ!!]",
  "preservationType.DRIED_AND_PRESSED": "[!!Ɖŕĩęď ȁŉđ ƥŕěšŝĕđ!!]",
  "preservationType.FORMALIN": "[!!Ƒơŕmăŀıņ!!]",
  "preservationType.REFRIGERATED": "[!!Řėƒřįģěřáţȇď!!]",
  "preservationType.FREEZE_DRIED": "[!!Ƒŗėēžē ďŕĩėđ!!]",
  "preservationType.GLYCERIN": "[!!Ĝŀƴčȅŗıņ!!]",
  "preservationType.GUM_ARABIC": "[!!Ğūm ȃŕáɓīč!!]",
  "preservationType.MICROSCOPIC_PREPARATION": "[!!Mīčřōŝċōƿīċ ƥŕȇƿãŗàťıőņ!!]",
  "preservationType.MOUNTED": "[!!Mőůŉţęđ!!]",
  "preservationType.PINNED": "[!!Ƥıŉƞȇđ!!]",
  "preservationType.OTHER": "[!!Ŏťĥȅŗ!!]",
  "preservationType": "[!!Ƥŕęšęřvǻŧĭōń ŧƴƿĕ!!]",
  "apiUrl": "[!!ÀƤĪ ŨŘĹ!!]",
  "collectionContentType.ARCHAEOLOGICAL_OTHER": "[!!Ǻřċħāęơĺŏĝĩċåľ - ŏťħēŗ!!]",
  "collectionContentType.ARCHAEOLOGICAL_HUMAN_REMAINS": "[!!Ářĉħąēơļōĝĭċâŀ - ħūmǻƞ ŕȅmáĭņś!!]",
  "collectionContentType.ARCHAEOLOGICAL_FAUNAL_REMAINS": "[!!Ȃŗċħáȅōļŏğĩĉăŀ - ƒāųŋåľ ŕĕmäĩŋş!!]",
  "collectionContentType.ARCHAEOLOGICAL_FLORAL_REMAINS": "[!!Ȃŕćħȃȅōłơģĩčąľ - ƒļŏŗąľ ŗēmäĭŉŝ!!]",
  "collectionContentType.ARCHAEOLOGICAL_C14": "[!!Ǻŕčĥâȇōĺŏğĭčäļ - Ć14!!]",
  "collectionContentType.ARCHAEOLOGICAL_COPROLITES": "[!!Åŕćħǻęōľơģĭćåŀ - ćŏƿŕőŀīťȇŝ!!]",
  "collectionContentType.ARCHAEOLOGICAL_CERAMIC_ARTIFACTS": "[!!Ǻŗćħăȅơļōğĩćāł - ċėŗàmįċ āřŧīƒáćţš!!]",
  "collectionContentType.ARCHAEOLOGICAL_FAUNAL_ARTIFACTS": "[!!Ăřćĥāēơłőğĭčãŀ - ƒãųńäŀ âŕţĩƒäĉţş!!]",
  "collectionContentType.ARCHAEOLOGICAL_FLORAL_ARTIFACTS": "[!!Ăřĉĥãēơłŏģīčáĺ - ƒļơŗàŀ ąŗťĩƒâćťŝ!!]",
  "collectionContentType.ARCHAEOLOGICAL_LITHIC_ARTIFACTS": "[!!Äřćĥȃēōŀōģįčàł - łĩŧħīč åŕţīƒåčţŝ!!]",
  "collectionContentType.ARCHAEOLOGICAL_METAL_ARTIFACTS": "[!!Ãřċħȁęŏľŏĝıĉǻŀ - mĕŧåŀ äřťĭƒȁĉţş!!]",
  "collectionContentType.ARCHAEOLOGICAL_TEXTILES_BASKETRY": "[!!Âřčħǻȇŏļơĝĭĉȁł - ţęxţıļȇŝ ƅǻšĸėťŗȳ!!]",
  "collectionContentType.ARCHAEOLOGICAL_TECHONOLOGICAL_PROCESSES_REMAINS": "[!!Äŕćħąėōľōĝıćãł - ŧěĉĥŏŉōłōģīćăł ƿŕŏčēšŝėś ŕēmāĩŉś!!]",
  "collectionContentType.ARCHAEOLOGICA_WOODEN_ARTIFACTS": "[!!Ǻŗĉħȁėōľőĝĩĉȃł - ŵőōđĕń åŗţīƒȃćŧŝ!!]",
  "collectionContentType.ARCHAEOLOGICAL_WOODEN_ARTIFACTS": "[!!Ăřċĥȃęŏľőġīćãļ - ŵơōđěń ąŕţįƒáċţš!!]",
  "collectionContentType.BIOLOGICAL_OTHER": "[!!Ƀįőľōġįčàĺ - ơţĥēŗ!!]",
  "collectionContentType.BIOLOGICAL_LIVING_ORGANISMS": "[!!Ɓĭŏļőģĩčáł - ĺįvīŋğ ōřģäņĩśmš!!]",
  "collectionContentType.BIOLOGICAL_LIVING_CELL_OR_TISSUE_CULTURES": "[!!Ƀįōľōġıċąľ - łįvįŋğ ćȇļł ōř ťįşŝũę ċūĺţūřĕŝ!!]",
  "collectionContentType.BIOLOGICAL_PRESERVED_ORGANISMS": "[!!ʙįőľơġıĉåļ - ƥŕęŝȇŕvĕď ơŕġâňĭšmš!!]",
  "collectionContentType.BIOLOGICAL_ANIMAL_BUILT_STRUCTURES": "[!!ʙįőŀőğįćâŀ - åŋımáļ ƀũīłţ ŝţŕŭčţŭřȇś!!]",
  "collectionContentType.BIOLOGICAL_ANIMAL_DERIVED": "[!!ʙĩŏŀōğįċǻŀ - áńĭmȁł ďěřıvěď!!]",
  "collectionContentType.BIOLOGICAL_BIOFLUIDS": "[!!Ɓīōłŏģıċäŀ - Ƃĩơƒłůĩđş!!]",
  "collectionContentType.BIOLOGICAL_CELLS_TISSUE": "[!!Ƀıơļơĝįćăĺ - ċȅļĺş ťĭšşŭȇ!!]",
  "collectionContentType.BIOLOGICAL_ENDOSKELETONS": "[!!Ɓīőĺōğįčâł - ēňďơśƙȇļěŧŏņš!!]",
  "collectionContentType.BIOLOGICAL_EXOSKELETONS": "[!!ʙīőĺŏġĭćȁļ - ĕxŏŝƙėŀȅţơƞś!!]",
  "collectionContentType.BIOLOGICAL_FECES": "[!!Ɓįőļŏġįĉāł - ƒěćěş!!]",
  "collectionContentType.BIOLOGICAL_MOLECULAR_DERIVATES": "[!!ʙįŏľőġĩċăĺ - mŏĺěċūľâŗ ďēřıvăŧēŝ!!]",
  "collectionContentType.BIOLOGICAL_PLANT_DERIVED": "[!!ßįŏľōġıčǻŀ - ƿłâňŧ đęŗīvēđ!!]",
  "collectionContentType.HUMAN_DERIVED_OTHER": "[!!Ħŭmȁņ đěŗīvěđ - ŏţħēř!!]",
  "collectionContentType.HUMAN_DERIVED_BIOFLUIDS_HUMAN": "[!!Ħŭmăƞ đěŕıvĕđ - ƅĭōƒŀŭįđś ħŭmâŋ!!]",
  "collectionContentType.HUMAN_DERIVED_BLOOD_HUMAN": "[!!Ĥũmãƞ đēŗįvėđ - Ƃłőőď ħūmąń!!]",
  "collectionContentType.HUMAN_DERIVED_CELLS_HUMAN": "[!!Ĥŭmãŉ đȇŕĩvĕđ - čȅļłş ĥūmãƞ!!]",
  "collectionContentType.HUMAN_DERIVED_FECES_HUMAN": "[!!Ħųmäņ ďȅŕıvėđ - ƒėćėŝ ĥůmǻń!!]",
  "collectionContentType.HUMAN_DERIVED_MOLECULAR_DERIVATIVES": "[!!Ħųmàƞ đęŕįvėď - mŏļęčŭľȁŗ ďėŗĩvǻţĭvȅş!!]",
  "collectionContentType.HUMAN_DERIVED_TISSUE_HUMAN": "[!!Ĥųmǻŋ đēŕĭvėď - ţĩššŭě ĥũmâŋ!!]",
  "collectionContentType.EARTH_PLANETARY_OTHER": "[!!Ėåŕţħ ƿļǻŋȅţåŗɏ - ōťħėř!!]",
  "collectionContentType.EARTH_PLANETARY_ASTEROIDS": "[!!Ěȃřťĥ ƥŀȁŋęţâŗȳ - âşŧěŕơįđŝ!!]",
  "collectionContentType.EARTH_PLANETARY_COMETS": "[!!Ėãŕţħ ƥļäňȇţǻřɏ - čőmēŧş!!]",
  "collectionContentType.EARTH_PLANETARY_COSMIC_INTERPLANETARY_DUST": "[!!Ėăŗťĥ ƿļäňēťáŗȳ - čőšmĩĉ īƞŧęŗƿļȃňěťăřȳ đũşŧ!!]",
  "collectionContentType.EARTH_PLANETARY_GAS": "[!!Ȇàŗţħ ƿłáńȇŧàŗƴ - ġȃś!!]",
  "collectionContentType.EARTH_PLANETARY_GEMS": "[!!Ěǻŗŧĥ ƿļȃņȇŧäŗƴ - ĝĕmś!!]",
  "collectionContentType.EARTH_PLANETARY_ICE": "[!!Ěáŕŧĥ ƿłȁňęţǻřŷ - īċĕ!!]",
  "collectionContentType.EARTH_PLANETARY_LUNAR_MATERIALS": "[!!Ēářţĥ ƿĺȃŉėťąŕɏ - ľũńāŗ māţėŕīăļŝ!!]",
  "collectionContentType.EARTH_PLANETARY_METALS_ORES": "[!!Ȇǻŗţĥ ƥŀâńęţȁřŷ - mėŧȃłŝ ơřěş!!]",
  "collectionContentType.EARTH_PLANETARY_METEORITES": "[!!Ěåřťĥ ƿļäńȇťäřȳ - męŧȅŏŕīţęš!!]",
  "collectionContentType.EARTH_PLANETARY_MINERALS": "[!!Ȅáŗŧħ ƿłáņȅťäŗƴ - mīŉĕŗȁłś!!]",
  "collectionContentType.EARTH_PLANETARY_ROCKS": "[!!Ĕǻŗţĥ ƥľąňĕŧářȳ - ŕơčķŝ!!]",
  "collectionContentType.EARTH_PLANETARY_SEDIMENTS": "[!!Ēāřťĥ ƥľáńěťãŕɏ - şĕđĩměņŧŝ!!]",
  "collectionContentType.EARTH_PLANETARY_SOILS": "[!!Ȅăŗţĥ ƿľąƞĕŧǻřŷ - śōıŀş!!]",
  "collectionContentType.EARTH_PLANETARY_SPACE_EXPOSED_MATERIALS": "[!!Ēäŕţĥ ƿľąƞėţąŗƴ - šƥâćȇ ēxƿŏšȅď māţėŗĩąŀş!!]",
  "collectionContentType.EARTH_PLANETARY_WATER": "[!!Ȅȃŕťĥ ƥĺāŋěţåŕƴ - ŵàŧēř!!]",
  "collectionContentType.PALEONTOLOGICAL_OTHER": "[!!Ƥāłėōņţōľőģįćàł - ŏţĥȅř!!]",
  "collectionContentType.PALEONTOLOGICAL_CONODONTS": "[!!Ƥàłěőŉŧōŀōĝįćâľ - čőŉŏďŏƞŧš!!]",
  "collectionContentType.PALEONTOLOGICAL_INVERTEBRATE_FOSSILS": "[!!Ƥăľĕōŉťŏŀŏģįċàļ - ĩňvěřťēɓŗȃţė ƒőşšįľş!!]",
  "collectionContentType.PALEONTOLOGICAL_INVERTEBRATE_MICROFOSSILS": "[!!Ƥǻĺĕōńţōŀơğįċåľ - īńvĕŕţėƅřãŧě mīčŕōƒŏśşĩļš!!]",
  "collectionContentType.PALEONTOLOGICAL_PETRIFIED_WOOD": "[!!Ƥāŀěōŋţơĺōģīĉǻł - ƥęŧŗĩƒĩĕđ ŵōőď!!]",
  "collectionContentType.PALEONTOLOGICAL_PLANT_FOSSILS": "[!!Ƥȁłěŏŉťơŀŏğĩċȃĺ - ƿļăņŧ ƒơŝšīľś!!]",
  "collectionContentType.PALEONTOLOGICAL_TRACE_FOSSILS": "[!!Ƥàľėŏńťōŀơģĭčȃŀ - ţřȃčȅ ƒŏśšıŀš!!]",
  "collectionContentType.PALEONTOLOGICAL_VERTEBRATE_FOSSILS": "[!!Ƥàłėőňťơłơġįčàŀ - vȅřţėƃřâŧē ƒơşśīłŝ!!]",
  "collectionContentType.RECORDS_OTHER": "[!!Řȅćơŗđś - őťĥęř!!]",
  "collectionContentType.RECORDS_SEISMOGRAMS": "[!!Ʀēćơŗđš - šȇįşmōġŕāmš!!]",
  "collectionContentType.RECORDS_RADIOGRAPH": "[!!Ʀěċōřđŝ - ŕąđĩŏĝŗǻƿĥ!!]",
  "collectionContentType.RECORDS_IMAGES": "[!!Ŗēĉŏŕďş - įmáģęş!!]",
  "collectionContentType.RECORDS_DOCUMENTS": "[!!Ʀȇčŏřđś - ďơĉųměƞţś!!]",
  "collectionContentType.RECORDS_DOCUMENTATION": "[!!Ʀĕćơŗďś - đőćůměņŧąŧįơņ!!]",
  "collectionContentType.RECORDS_DERIVED_DATA": "[!!Ŕěĉőŗďš - đěŕįvěđ ďâŧã!!]",
  "collectionContentType.RECORDS_ASSOCIATED_DATA": "[!!Ʀēċōŗđŝ - áššōċĩáţėđ đǻŧã!!]",
  "collectionContentType.RECORDS_MAPS": "[!!Ŗĕċơŕďš - mȁƥş!!]",
  "collectionContentType.RECORDS_RECORDINGS": "[!!Ŗęćōŕđŝ - ŕȇċōřďıŋĝś!!]",
  "contentTypes": "[!!Ćŏńťēŋţ Ťƴƥēš!!]",
  "institutionType.BIOMEDICAL_RESEARCH_INSTITUTE": "[!!Ɓıŏmėďĭċǻĺ ŕȅŝēȁŗćħ įŋśťıŧűţȇ!!]",
  "institutionType.BOTANICAL_GARDEN": "[!!ʙŏťȁňĩĉåļ ğåŕđěŋ!!]",
  "institutionType.HERBARIUM": "[!!Ħěřƀåŗīŭm!!]",
  "institutionType.LIVING_ORGANISM_COLLECTION": "[!!Ļıvıƞĝ ōřĝāŋįşm čŏľłĕćŧįơŋ!!]",
  "institutionType.MEDICAL_RESEARCH_INSTITUTE": "[!!Mėďīċāŀ ŗȇšēȁŕčħ īňşŧįţůťę!!]",
  "institutionType.MUSEUM": "[!!Mŭşĕűm!!]",
  "institutionType.MUSEUM_HERBARIUM_PRIVATE_NON_PROFIT": "[!!Mŭšėũm ħėřƄȁŗĩűm ƿŗıvåţȅ ŉơň ƥŕōƒįŧ!!]",
  "institutionType.OTHER_INSTITUTIONAL_TYPE": "[!!Ơťĥěŕ ĭňšŧĭţůŧĩŏńàľ ŧȳƥę!!]",
  "institutionType.OTHER_TYPE_RESEARCH_INSTITUTION_BIOREPOSITORY": "[!!Ơŧħȅř ŧƴƥę ŕēşēãŗćĥ ıńšťįťųţıōņ ƃıőŗȇƿŏşıţōřȳ!!]",
  "institutionType.UNIVERSITY_COLLEGE": "[!!Ũňĩvēŗŝĭţȳ čŏļłēĝȇ!!]",
  "institutionType.ZOO_AQUARIUM": "[!!Ƶōŏ åɋųǻŕīūm!!]",
  "institutionGovernance.ACADEMIC_FEDERAL": "[!!Ȁĉâďėmįĉ ƒęďėŗǻĺ!!]",
  "institutionGovernance.ACADEMIC_FOR_PROFIT": "[!!Ãčȃďėmĩĉ ƒōŕ ƿŗŏƒĭŧ!!]",
  "institutionGovernance.ACADEMIC_LOCAL": "[!!Ăċąđēmīċ łōčäŀ!!]",
  "institutionGovernance.ACADEMIC_NON_PROFIT": "[!!Ãćāďȅmĭč ŉőƞ ƥŗőƒıť!!]",
  "institutionGovernance.ACADEMIC_STATE": "[!!Ȁčäđĕmīć şťãťȇ!!]",
  "institutionGovernance.FEDERAL": "[!!Ƒęďȇŗãĺ!!]",
  "institutionGovernance.FOR_PROFIT": "[!!Ƒŏŕ ƥŕŏƒīť!!]",
  "institutionGovernance.LOCAL": "[!!Łŏčāļ!!]",
  "institutionGovernance.NON_PROFIT": "[!!Ńơŋ ƥŕŏƒĩŧ!!]",
  "institutionGovernance.OTHER": "[!!Ōŧĥēŕ!!]",
  "institutionGovernance.STATE": "[!!Šţàŧě!!]",
  "discipline.ARCHAEOLOGY": "[!!Ǻŕĉħāēōŀőģŷ!!]",
  "discipline.ARCHAEOLOGY_PREHISTORIC": "[!!Åřĉĥǻęōłơģŷ ƥŕȅħīšţőŕįč!!]",
  "discipline.ARCHAEOLOGY_HISTORIC": "[!!Àŗćĥąėŏĺőğɏ ħīšţơŕįċ!!]",
  "discipline.ARCHAEOLOGY_UNDERWATER": "[!!Âŗćĥąȅőļőğŷ ũňďȇŗŵåŧĕŗ!!]",
  "discipline.ANTHROPOLOGY": "[!!Äńţĥŕŏƥơłŏğȳ!!]",
  "discipline.ANTHROPOLOGY_BIOLOGICAL": "[!!Áņţĥřōƥŏłōğŷ Ƅıơĺơġįčął!!]",
  "discipline.ANTHROPOLOGY_CULTURAL": "[!!Ȃƞŧħŗōƥőľơġȳ ċųłťůŕął!!]",
  "discipline.ANTHROPOLOGY_LINGUISTIC": "[!!Ãńţħŗơƿőłơģɏ ľıńĝųĩşţĩč!!]",
  "discipline.SPACE": "[!!Śƥàćę!!]",
  "discipline.SPACE_ASTRONOMY": "[!!Śƥȃċě ášŧřơņŏmŷ!!]",
  "discipline.SPACE_ASTROPHYSICS": "[!!Śƿàċę āšţřŏƥħƴŝıĉş!!]",
  "discipline.SPACE_COSMOLOGY": "[!!Śƿáċĕ čŏśmōľőģŷ!!]",
  "discipline.SPACE_PLANETARY_SCIENCE": "[!!Śƿäĉė ƿľâŉęţăŕɏ šċıȅŋćē!!]",
  "discipline.ATMOSPHERIC": "[!!Ȃţmōšƿħȅŗĩĉ!!]",
  "discipline.ATMOSPHERIC_PHYSICS_DYNAMICS": "[!!Âťmơşƥħēřīć ƿĥɏśĭĉš ďƴņåmīčŝ!!]",
  "discipline.ATMOSPHERIC_CLIMATOLOGY": "[!!Ȁŧmőŝƿĥėŕįċ ćľĩmȃťōĺŏġƴ!!]",
  "discipline.ATMOSPHERIC_METEOROLOGY": "[!!Âŧmőšƿħȅřĩć mėŧēōŗŏłōġȳ!!]",
  "discipline.CHEMICAL": "[!!Ċħėmĭĉȃļ!!]",
  "discipline.CHEMICAL_ANALYTICAL": "[!!Čĥĕmĩćȁŀ ȃńáļȳŧĩċąļ!!]",
  "discipline.CHEMICAL_ASTROCHEMISTRY": "[!!Ĉĥęmīčàŀ ąşŧŕŏċħȅmīŝţŗȳ!!]",
  "discipline.CHEMICAL_ATMOSPHERIC_CHEMISTRY": "[!!Ċĥěmįčãļ âţmŏśƿĥėřīċ ĉħēmįŝťŕŷ!!]",
  "discipline.CHEMICAL_BIOCHEMISTRY": "[!!Ćħęmįĉǻĺ ƅįŏćħěmįšŧŗɏ!!]",
  "discipline.CHEMICAL_BIOGEOCHEMISTRY": "[!!Ċĥĕmĩĉȁľ Ƃįőġĕơčħȇmĩšťŕȳ!!]",
  "discipline.CHEMICAL_COSMOCHEMISTRY": "[!!Ĉĥĕmįĉãļ čŏšmơćħĕmıšťŕƴ!!]",
  "discipline.CHEMICAL_INORGANIC_CHEMISTRY": "[!!Ćħęmĭčǻł ĩńōŕģâŉīċ ćħȇmīśťŗɏ!!]",
  "discipline.CHEMICAL_NUCLEAR_CHEMISTRY": "[!!Čĥȅmīċâĺ ņũčľěāř ĉĥēmīŝťŕŷ!!]",
  "discipline.CHEMICAL_ORGANIC_CHEMISTRY": "[!!Ċĥēmĩčãł ơřġăƞīć ćħėmīŝŧŕŷ!!]",
  "discipline.CHEMICAL_PHYSICAL_CHEMISTRY": "[!!Ĉĥēmĭčȁĺ ƥĥƴšĩċȃĺ ĉĥěmįšťŕƴ!!]",
  "discipline.GEOLOGICAL": "[!!Ġēơłơġīĉäļ!!]",
  "discipline.GEOLOGICAL_ECONOMIC_GEOLOGY_MINERAL_RESOURCES": "[!!Ġēŏŀŏģıčäŀ ėċơƞőmĩč ģȇơłōĝƴ mįŉěŗåŀ ŗĕŝŏųŕċēş!!]",
  "discipline.GEOLOGICAL_ENERGY_RESOURCE_GEOLOGY": "[!!Ĝėŏľŏģĩĉąľ ȅŉȅŕģȳ ŕěśơųŗċē ġėŏłơğƴ!!]",
  "discipline.GEOLOGICAL_GEOCHEMISTRY": "[!!Ģȅőłōģĭĉàĺ ġěơćĥȇmįŝŧřŷ!!]",
  "discipline.GEOLOGICAL_GEOLOGY": "[!!Ĝėơľőĝĩčàŀ ġęơĺōġƴ!!]",
  "discipline.GEOLOGICAL_GEOPHYSICS_SEISMOLOGY": "[!!Ğěŏľōğĩčāľ ĝęŏƿĥȳšĭćş şēįśmőļŏģƴ!!]",
  "discipline.GEOLOGICAL_HYDROLOGY_WATER_RESOURCES": "[!!Ğēŏłŏġĭčăļ ĥŷđŕōŀőğȳ ŵãŧęŕ řęśōŭŕćȅš!!]",
  "discipline.GEOLOGICAL_MINERALOGY_PETROLOGY": "[!!Ģėőłŏġĭĉäľ mīňȅŗãŀōġȳ ƿěţřơŀŏğɏ!!]",
  "discipline.GEOLOGICAL_PALEONTOLOGY": "[!!Ģěōĺơğīċäŀ ƿäŀȅŏņŧơĺơġȳ!!]",
  "discipline.GEOLOGICAL_VOLCANOLOGY": "[!!Ğȅőľơģıċàľ vőŀćȁńōĺőġɏ!!]",
  "discipline.OCEAN": "[!!Ŏčĕâń!!]",
  "discipline.OCEAN_MARINE_BIOLOGY_AND_BIOLOGICAL_OCEANOGRAPHY": "[!!Ŏĉĕăņ mȁŗīŉė Ƃıōŀōģɏ ąŉđ Ƃįōĺōĝıĉȁŀ ōćȅȁňōğŗǻƿħŷ!!]",
  "discipline.OCEAN_MARINE_GEOLOGY_AND_PALEOCEANOGRAPHY": "[!!Ŏćĕąŋ mäŕĩňĕ ğȅơłōğȳ ąŋď ƿáļȇőĉēäňŏĝřâƿĥŷ!!]",
  "discipline.OCEAN_OCEANOGRAPHY_CHEMICAL_PHYSICAL": "[!!Ŏčęáƞ ōċȇâňŏğřãƿĥȳ ćħȅmıċāŀ ƿħŷşĭćăļ!!]",
  "discipline.PHYSICS": "[!!Ƥħƴšįĉś!!]",
  "discipline.PHYSICS_ACOUSTICS": "[!!Ƥħƴŝıċş ȁĉōűşŧĩċš!!]",
  "discipline.PHYSICS_APPLIED_PHYSICS": "[!!Ƥħŷŝĩċŝ ǻƿƿľįēď ƿĥȳśĩćš!!]",
  "discipline.PHYSICS_ATOMIC_MOLECULAR_CHEMICAL_PHYSICS": "[!!Ƥħɏşīĉş āťōmįć mőĺėćūľäŗ ĉĥĕmīćȃł ƥĥɏşīćş!!]",
  "discipline.PHYSICS_BIOPHYSICS": "[!!Ƥĥŷŝĩćş Ƅĩőƿĥȳşīćś!!]",
  "discipline.PHYSICS_MEDICAL_RADIOLOGICAL": "[!!Ƥħɏśįĉş mēďĩĉȁľ ŗãďıőŀőġıċáľ!!]",
  "discipline.PHYSICS_NUCLEAR_PHYSICS": "[!!Ƥĥɏşįĉś ňųċļėâř ƿħɏšıċś!!]",
  "discipline.PHYSICS_OPTICS_PHOTONICS": "[!!Ƥħŷšĭĉŝ ōƥŧįĉš ƥħőťơŉıćś!!]",
  "discipline.PHYSICS_PARTICLE_PHYSICS": "[!!Ƥħȳŝıčś ƥąŕţĭčļĕ ƥħȳŝįčŝ!!]",
  "discipline.AGRICULTURAL": "[!!Ãġřĭčųļţůŕȁł!!]",
  "discipline.AGRICULTURAL_ANIMAL_SCIENCE": "[!!Âģŗıćűľťŭŗȃļ ãŉįmãł ŝćĩēŋćȅ!!]",
  "discipline.AGRICULTURAL_ANIMAL_SCIENCE_POULTRY": "[!!Åģřīćūŀţųŕāľ ăńĩmȁļ šĉīȇňčĕ ƿőūļŧŕɏ!!]",
  "discipline.AGRICULTURAL_AGRICULTURAL_ANIMAL_BREEDING": "[!!Ȃĝŕĩčůŀťůŕáļ äğŗīĉűłťűŕȃŀ ăƞįmȃŀ Ƃřęȅđĭŋĝ!!]",
  "discipline.AGRICULTURAL_AGRICULTURAL_HORTICULTURAL_PLANT_BREEDING": "[!!Ąğŕıĉůļťųŕȁĺ åģŕįčűļţūřăŀ ĥŏřţĩċŭĺťūŗăł ƿłàņţ ƀŗēȅďĩŉğ!!]",
  "discipline.AGRICULTURAL_AGRONOMY_CROP_SCIENCE": "[!!Äģřįĉūŀŧŭřäł ȃğŕŏņőmŷ ċřŏƥ şčĩěńĉȇ!!]",
  "discipline.AGRICULTURAL_ENVIRONMENTAL_SCIENCE": "[!!Ãğŗįčůŀţųŕàļ ĕňvıŗŏŉměņţăŀ şĉįěńčę!!]",
  "discipline.AGRICULTURAL_FISHING_FISHERIES_SCIENCE": "[!!Âĝŗĩčűŀţũřåł ƒıśħīņĝ ƒīšħĕŕıȇş şċįȇņċē!!]",
  "discipline.AGRICULTURAL_FOOD_SCIENCE_AND_TECHNOLOGY": "[!!Ąġŕīčűłŧũŗåľ ƒơőđ śćīĕňčȇ ãŋď ţĕčħńőļơğɏ!!]",
  "discipline.AGRICULTURAL_FOREST_SCIENCES_AND_FORESTRY": "[!!Áġŕīćůłťŭřáĺ ƒőŕěśţ şćīȇňċēş āƞđ ƒơřěšŧŕŷ!!]",
  "discipline.AGRICULTURAL_HORTICULTURAL_SCIENCE": "[!!Âġŗıćũľŧůřåĺ ħőŗťīčűľŧūřȃļ şċĩėņčė!!]",
  "discipline.AGRICULTURAL_NATURAL_RESOURCES": "[!!Ȁģŕıčŭŀţųŕȁŀ ŋàťųŕȃľ řęšőųřćěŝ!!]",
  "discipline.AGRICULTURAL_PLANT_SCIENCES": "[!!Ąĝŗįċűĺţūřǻŀ ƥļáŉŧ şċĭěŋčȇŝ!!]",
  "discipline.AGRICULTURAL_SOIL_CHEMISTRY_MICROBIOLOGY": "[!!Ǻģřıćŭłţŭŕȃļ śŏĭĺ ćĥȇmıśŧŕɏ mĭċŗơƃįőĺōġȳ!!]",
  "discipline.AGRICULTURAL_SOIL_SCIENCES": "[!!Ȁĝřįĉůĺţūŗȁĺ śőīŀ šćįȇŋċęş!!]",
  "discipline.AGRICULTURAL_WILDLIFE_RANGE_MANAGEMENT": "[!!Ąģŗĭĉūŀťŭřãŀ ŵıĺďŀĭƒĕ ŗȃŉĝě máŉȁģĕmȅŉť!!]",
  "discipline.AGRICULTURAL_WOOD_SCIENCE_AND_PULP_TECHNOLOGY": "[!!Ǻģřıčųŀţųŕãĺ ŵőơď ŝčīěƞčė ȃƞď ƿūľƿ ťěčħńőľőġƴ!!]",
  "discipline.BIOLOGICAL": "[!!ßĩơľőğıčåļ!!]",
  "discipline.BIOLOGICAL_ANATOMY_AND_PHYSIOLOGY": "[!!Ƀįŏłơĝıčȁĺ áņāŧōmȳ ȁŋď ƿĥɏşıŏĺőģŷ!!]",
  "discipline.BIOLOGICAL_CELLULAR_BIOLOGY_AND_HISTOLOGY": "[!!Ƀĩōĺŏĝĩĉàĺ ćēľŀŭŀäŗ ƃıőŀőģŷ ȁńď ĥĭśŧőļőģŷ!!]",
  "discipline.BIOLOGICAL_DEVELOPMENT_BIOLOGY_EMBRYOLOGY": "[!!Ɓīơŀŏģįćåĺ ďęvȇŀőƥmėŋŧ ƅįơļơģɏ ēmƃřɏơĺōĝɏ!!]",
  "discipline.BIOLOGICAL_ECOLOGY": "[!!Ɓĩōļōĝĭćãľ ĕčőŀōġƴ!!]",
  "discipline.BIOLOGICAL_ENVIRONMENTAL_TOXICOLOGY": "[!!ßıơŀŏġįĉȁĺ ěŉvĩŕơňmȅňťǻļ ťőxıčőľőģȳ!!]",
  "discipline.BIOLOGICAL_EVOLUTIONARY_BIOLOGY": "[!!Ɓīơľőģīĉāļ ȅvōľůťıŏňǻŗɏ ƀįŏļőģŷ!!]",
  "discipline.BIOLOGICAL_GENETICS_GENOMICS": "[!!ßīơĺōģĭċăŀ ğęňēťįćş ġėņŏmĩćś!!]",
  "discipline.BIOLOGICAL_MICROBIOLOGY_BACTERIOLOGY_VIROLOGY": "[!!ʙıōĺơģıčâŀ mįċřŏɓĩơŀōğŷ ƃáčťęŕīōłōğɏ vıřőŀőġƴ!!]",
  "discipline.BIOLOGICAL_MOLECULAR_BIOLOGY": "[!!ʙĭơłŏģīċāļ mơļēčũļǻŗ ƀīơļơğŷ!!]",
  "discipline.BIOLOGICAL_NEUROSCIENCES_AND_NEUROBIOLOGY": "[!!Ƀıōľŏğĭčáł ƞȇũŗőśċĭėňċȇś āŋđ ŉėųŗơƄīőľơĝɏ!!]",
  "discipline.BIOLOGICAL_PARASITOLOGY": "[!!ʙĩōłōģĩĉâļ ƥâřäşĭţŏļőĝƴ!!]",
  "discipline.BIOLOGICAL_PATHOLOGY_ANIMAL_PLANT": "[!!Ƀıōľőģıĉął ƥāŧħŏŀŏġȳ ǻƞīmāĺ ƥŀȃņŧ!!]",
  "discipline.BIOLOGICAL_TAXONOMY": "[!!Ƀıŏļōģĩćáł ŧäxơŋơmɏ!!]",
  "discipline.BIOLOGICAL_ZOOLOGY": "[!!Ƀıŏŀōğįċȃŀ ƶōōĺŏģŷ!!]",
  "discipline.HEALTH": "[!!Ħěąĺťħ!!]",
  "discipline.HEALTH_BIOMEDICAL_SCIENCE": "[!!Ĥęáľťħ ɓĭőmȇďĭčáĺ śĉĭȇņĉę!!]",
  "discipline.HEALTH_ENVIRONMENTAL_HEALTH": "[!!Ħėąļţĥ ēńvįŕōňmĕŋŧăľ ĥȇāļŧĥ!!]",
  "discipline.HEALTH_EPIDEMIOLOGY_PUBLIC_HEALTH": "[!!Ĥęąľťĥ ēƿįđęmįőľőģȳ ƿũƀľįć ĥěäĺťĥ!!]",
  "discipline.HEALTH_GENETICS_GENOMICS": "[!!Ħȅâŀŧĥ ĝȇƞěťıċś ģĕņơmĭĉś!!]",
  "discipline.HEALTH_MICROBIOLOGY_BACTERIOLOGY_VIROLOGY": "[!!Ĥȅǻŀţħ mıĉŕŏƅįơŀơģŷ ɓåċťĕŗīơŀőģƴ vįřőļŏģȳ!!]",
  "discipline.HEALTH_NEUROSCIENCES_AND_NEUROBIOLOGY": "[!!Ĥēāłťĥ ńȇůŕōŝčıęńćęş ȁņď ņěůŕơƅįŏŀőğȳ!!]",
  "discipline.HEALTH_NUTRITION_SCIENCES": "[!!Ħėãłŧħ ŋũţŗıťįőŉ śĉīęŋĉėš!!]",
  "discipline.HEALTH_PATHOLOGY_HUMAN": "[!!Ħĕąļţĥ ƥȁťħơĺōğŷ ĥűmąń!!]",
  "discipline.HEALTH_PHARMACEUTICAL_MEDICINAL_SCIENCES": "[!!Ĥęäĺţĥ ƥĥȁřmāċĕųŧīčáł mėđĭćīņȁĺ şčīȇŋĉėŝ!!]",
  "discipline.HEALTH_PHARMACOLOGY_HUMAN_AND_ANIMAL": "[!!Ĥěăľţĥ ƿĥâřmãčơļőġɏ ĥũmǻƞ àƞď ȁŋĩmȁĺ!!]",
  "discipline.HEALTH_TOXICOLOGY": "[!!Ĥęàŀŧħ ťőxīćơłŏğŷ!!]",
  "discipline.HEALTH_VETERINARY_SCIENCES": "[!!Ħēàĺťĥ vėŧěřĭņȃŗƴ šċĭȅŉćēş!!]",
  "discipline.MATERIAL": "[!!Mǻţĕŗĩäł!!]",
  "disciplines": "[!!Ďĩŝčīƿľĭŉȇŝ!!]",
  "additionalNames": "[!!Ãďďĩŧįơńãł ňàmęŝ!!]",
  "foundingDate": "[!!Ƒŏūńđıŉġ ďȃţē!!]",
  "geographicDescription": "[!!Ġėơģřąƥĥįč đĕşćŗīƿŧīŏƞ!!]",
  "taxonomicDescription": "[!!Ťàxŏƞŏmĩć đēŝćŗıƿŧıŏņ!!]",
  "numberSpecimens": "[!!Ńůmƅĕŕ śƿęčımēńŝ!!]",
  "citesPermitNumber": "[!!Ĉıťȇş ƥȇŕmįť ňůmƅėŕ!!]",
  "areaResponsibility": "[!!Ȃřȇå ŕěŝƥŏƞšįƅīŀįŧƴ!!]",
  "researchPursuits": "[!!Ʀėšěâřćĥ ƿűřšūıťś!!]",
  "fax": "[!!Ƒąx!!]",
  "primaryInstitution": "[!!Ƥřımåŗƴ ĩŋŝŧıŧűţĩơƞ!!]",
  "primaryCollection": "[!!Ƥŗĭmǻŗŷ ĉơĺŀȅćţıőŉ!!]",
  "syncDate": "[!!Ŝȳňĉ đȁţė!!]",
  "result": "[!!Ŕėšūŀť!!]",
  "dashboard.lastCreatedAgo": "[[[!Last created {timeAgo}!]]]",
  "dashboard.xInTotal": "[[[!{formattedNumber} in total!]]]",
  "dashboard.xPending": "[[[!{formattedNumber} pending!]]]",
  "dashboard.xWithoutEndpoint": "[[[!{formattedNumber} without {count, plural, zero {endpoints} one {endpoint} other {endpoints}}!]]]",
  "help.organization.nonPublishing": "[!!Őŗğäńīżäŧįŏňś ťħąť ħăvȇ ňơŧ ɏėť ƿũƃļĭŝħěđ àŋȳ đāţąšēťş!!]",
  "help.mailingAddress": "[!!Ŵħėřĕ ŧő śēňď mäĩļ - īƒ ŋō ƥĥƴşıčäľ āďđŗěšš ış ƥřōvıđȅđ ťĥėň ťħĭş īş ȃĺşơ ťħȇ ȃďďřȅśś ťơ ũśē ƒơŕ vįŝįšťš!!]",
  "help.physicalAddress": "[!!Ŵĥĕřę ťơ vıśıť!!]",
  "help.commentContent": "[!!<ƥ>Ćőmmĕńťäřȳ śĥōųĺď Ƅȇ ŵŗĩťťėŋ ŵīţħ ċơņśįďȇŗȃŧĩŏŉ, űşĭňġ ľàŉģūȁģĕ šůįŧäƃľĕ ƒőŕ ȁƞɏ ƥūƀŀįč ƒơŕům ǻňď ņőŧ ćŏńťȃīńīŋĝ śȇņśįŧĩvȅ đēţáıľş.\n<śŧŗőňĝ>Őƞľŷ ūšē ōƒ ƿŀȃĩň ţēxţ ıś şůƥƿőřŧȇď - ŉơ XMĻ, ĵŜƠƝ ēťċ</šŧřōňğ>.</ƥ>\n!!]",
  "help.identifier": "[!!Ŧĥȇ váĺũē ƒőŕ ţĥĕ ĭđēƞţįƒīȅŕ (ę.ğ. ďơĩ://12.123/123).!!]",
  "help.identifierType": "[!!Şėĺĕćŧ ťħė ţɏƥę ŏƒ ţĥȇ įďėŉťīƒĭȇŗ.!!]",
  "help.mtNamespace": "[!!Ŧħė ņǻmēşƿãĉē ĭş ą čäťěĝőřȳ ƒőŕ ţĥė ņămȅ/vàļūȅ ƿäıř ťǻġ. Įŧ màɏ ɓē űšĕď ťơ đıšŧĭŋġųīšĥ ĝřơūƥıņğś (ĕ.ģ. ĉŗäŵŀĩňğ, ƿřőċĕśśĭņģ) ŏŗ ťő ďėċĺáŕĕ å ţŕūē ţěŕm ŉąmȅšƥåćȇ (ē.ğ. đŵĉ)!!]",
  "help.mtName": "[!!Ŧĥē ňąmě ƒơŕ ţĥē ťăġ (ě.ğ. ɓāŝįşŌƒŔēċơŕď, ţŷƥę).!!]",
  "help.mtValue": "[!!Ţħĕ väłűĕ ƒơř ŧħȅ ţåğ (ę.ğ. Ľıvĭŋĝ śƥēĉĭmėň, MÂŅĬŠ).!!]",
  "help.tagValue": "[!!Ţħȅ vȁŀūĕ ƒŏŕ ťħě ŧąġ (ȇ.ġ. Ȁřŧĥŗŏƥōđ ƥĭŧƒãĺľ ťŕâƿ).!!]",
  "help.orgTitle": "[!!Ĕńţȅŕ åŉ ǻčĉũŕåťȅ ōřġǻňıźäťīōƞ ŧįťļě àŝ ıţ ĩš űśēď īņ mãŋŷ ƙēŷ ƥłȃčęş.!!]",
  "help.reportingPurposes": "[!!Ťĥĩś įş ūŝęđ ƒőř řėƿőŕŧĭƞģ ƥŭřƿőŝȇş (ĕ.ĝ. ơčċųŕŕȇňċę ćőųņţş ĭņ ãđ ĥŏć ŕėƥōŕťıńģ)!!]",
  "help.userName": "[!!Ȳōű ĉǻŉ ĺơğ ĭŋ ųŝīńġ ǻ űşĕŕƞâmĕ őř āň ȅmāīĺ áđđŗěśš.!!]",
  "help.primaryCheckboxTip": "[!!İƞđıĉąţęś ţħåţ ŧħę ćŏƞŧàćŧ ĭş ţĥȇ ƥřįmąŕŷ ċŏņťâċŧ ƒōŗ ťĥę ĝīvĕŋ ŧɏƿě!!]",
  "help.tagValueExtra": "[!!Ŧĥę vǻłŭȅ ƒōř ťĥĕ ţąģ (ė.ĝ. Âŗţĥřŏƥōđ ƿıŧƒáłŀ ŧřȁƥ).!!]",
  "help.externalTip": "[!!Īŋďĭĉãťĕŝ ţħȁŧ ţĥȇ ďāťăşȅŧ ĩŝ ƒŏūńď ŧĥŕơūģħ ıňţēģřáŧĩơņ ŵįţħ mėţȃđąťä ŉĕŧŵōŗķš, åņđ ŋŏť řȇĝĭśťęřěđ ďıřȅĉŧłɏ ŵĩťĥ ĞƁĬƑ!!]",
  "help.lockedForAutoUpdateTip": "[!!Ćơŋťřőĺŝ ƥėřmĩšśįōŉş ƒŏŕ ćřãŵĺēřş űƿđǻťĭƞġ męťåďȁŧà, ćőŉťȃčťŝ ęŧĉ!!]",
  "help.publishingOrg": "[!!Ĩţ ĩş ęxƥȅčţȅď ŧĥåţ ťħīś mäȳ ɓę ċĥáƞĝēđ ŏćĉàšįōņäłľŷ, ƅūť ɓė vıġĩłǻńţ ĩņ čħȃŉğȅś ãš ŧĥįŝ ħåš ƿőŧēŉŧīâľ ŧő šƥāŵƞ šīģŉĩƒīċâńť ƿŕơĉēśŝıńġ ƒơŕ ŏċćűŗŗēŋċē ŕěćŏŗđş, mȅťřıċş āņđ mãƥś!!]",
  "help.installation": "[!!İť īş ėxƿĕĉŧěđ ťħâť ťĥīš mȃɏ ɓė ĉĥâņģěď ơćčáŝıōƞǻľľɏ, ƅűţ ƅē vıģīľȁņţ įŋ ćħáƞğēś ȁś ťħĭş ħāş ƿőŧĕƞţıāŀ ŧŏ śƿȁŵŋ śĭĝŋīƒīĉàƞť ƥŗőċėŝśıŉğ ƒōř ŏĉċųŕŗēńćę ŕȅčŏŕďś, mȅŧřĩčş. Ƥŀėȁśē vȅřĭƒɏ ŧĥȅ šėŗvıĉěš äŗē ąŝ ėxƥęčţęď őƞ ćħàƞğė!!]",
  "help.parentDataset": "[!!Ƒőř ŭŝȅ īŉ ďęĉłàŗīňğ ďȃţâşȅţ řęľåţĭōňšĥĩƿś, śūċĥ ǻş ŧĥȅ ćơŋśţĭţŭęńť ƥãŕţş ŏƒ ţĥȇ Čąŧåŀőģųȇ ơƒ Ŀĩƒȇ!!]",
  "help.duplicateDataset": "[!!Ŵĥēŉ ã ďǻťăşēŧ įš ƒōůŋđ ţŏ ƅē ă ďŭƥŀıćáťĕ ŏƒ àŉơŧĥĕŗ, ţħěň ıţ šħơũŀđ ƃĕ ůƿďãŧėď. Ťħīŝ ŵĩľŀ ėƒƒȇčŧįvęŀƴ ţŕıģġęŕ ȁ ďě-įņđēx ŵħįćĥ ıś ŧĥē śämȅ ȃş á ďěłȇŧĩōń. İŧ måŷ ƀȇ ŧħãť ŷőũ ÂĽŚŌ ńěěđ ŧŏ šȅţ ťħę ƥåŗēňŧ đäŧāşėţ īƒ ťħıś ħăś ƅĕėƞ ȁģĝŗěġȃţěď.!!]",
  "help.updateFrequency": "[!!Ťħē ƒŕĕɋũȇƞčŷ ŵĭŧĥ ŵĥĩĉĥ čĥȃńġĕş ãńđ àďđĭţīőŋŝ ȁŕė måďě!!]",
  "help.instTitle": "[!!Ėńţȇŕ ąŋ áććūřäţę ıńŝŧáŀļãťīōņ ťįŧŀȅ ǻş īŧ ĩŝ űşęđ ıň máŉȳ ƙėɏ ƥļȁĉěŝ.!!]",
  "help.instDescription": "[!!Ƥŕơvĭďȅ ą mȅåŋĭƞģƒųļ ďēşĉŗıƿţıơƞ ŏƒ ŧĥē īņŝŧąłļǻťıōŉ, ŝő ã ŭşęŕ ŵīłļ ŭŋđėřŝťáňď ŵħãť ţĥȅ ıƞšŧǻľļãţīōń ĭş.!!]",
  "help.instPublishingOrg": "[!!Įŧ ıś ȇxƿēĉŧĕđ ţĥȃť ţĥīš mȃȳ ƅě ċħȁŉğȅď ōćčąśĩōŉáĺľŷ, ƀůť ƃě vįğĩĺāŋţ įņ ćĥąŉğěŝ ăş ťĥįś ħâŝ ƿōŧēŋŧīȁĺ ţơ śƿåŵŉ ŝįĝńĩƒĭćâƞŧ ƥřŏčěşśĩńģ ƒơŕ ŏćčŭŕŕēŉĉĕ ŗęċőŗďŝ, mĕŧŕĭčş äŉđ mȁƿŝ!!]",
  "help.instType": "[!!Ŵĥȇƞ čĥäŋğīńĝ ţħĩš, vėŗįƒŷ ăĺľ śȅřvĭċȅš ȁŕę ăļşŏ űƥďȃţēđ ƒơř ŧħē ıƞşŧăłŀàţĭŏƞ, ȃňď ȅvȇŕŷ đåŧāšėţ śȇřvȅđ. Mơŝţ ľıķėļȳ ɏŏũ ďō ŉőŧ ŵāņţ ţŏ ċħãŉģē ŧħīś ƒıęĺđ, ƀūŧ ŗäŧħȅř ćřėäţē ä ƞēŵ įŉşťāľļąťĭōņ őƒ ţħȇ ċơřŕĕċť ŧƴƥė, åŋđ mĭġřäţė ďåŧãšěţş. Ŭšě ţĥįš ŵįŧĥ ęxŧřȇmȅ čàūŧįōň!!]",
  "help.disabledCheckboxTip": "[!!Ĩňđĩċāţėš ťĥàŧ ţħē ĭņśţàľłąťĩŏŉ ĭŝ đĭşâƅļēđ ãņď ƞō mĕţàšȳňć őř ċŗāŵľıňĝ ōƒ ăśŝōĉĭāťęď đàţǻšęŧş ŵĭľļ őččŭř!!]",
  "help.orgCommentsInfo": "[!!Čŏmmȇŋŧś ąļłơŵ ȁđmĩńışţŕàťőŕş ţơ ŀĕăvě čōņŧęxŧ àɓŏůŧ ĉōmmūńĩćăŧĭőŉś ŵīťĥ ƿűƂĺĭŝħęŕś ĕŧč.!!]",
  "help.orgMachineTagsInfo": "[!!Mãčħīņȇ ŧăģś ąŕę ıňţěńđĕđ ƒőŗ äƥƥľĩĉȁŧĭơńš ťơ šŧơŗĕ īƞƒŏŕmăťĩōŉ ȃƀŏůţ áƞ ęňťįţɏ. Ǻ mãċĥīņȇ ŧàĝ īş ėŝşēƞŧįàŀłŷ ȃ ŋąmě/vȃŀűę ƿāĭř, ŧĥąť īş čãŧȇģőŕıŝȅď įŉ á ŋåmēšƥāĉȇ. Ťĥȇ 3 ƿăřťŝ māŷ ƀȅ ūśēď âŝ ţħȇ ȁƿƥļįćäŧĭơŋ ŝęėŝ ƒĩť.!!]",
  "help.orgOverviewInfo": "[!!Ŧĥīś ĩńƒőŕmàťĭōƞ ȁƿƥėâŕŝ ōń ťĥē ōřĝąŋĭƶȁŧĩŏƞ ƿŕơƒīľȇ, ŏŗğąƞīźâŧīőŉ ƥâĝȅş, šęȃŕċħ ŗěšųĺťś, ãńď ɓĕƴơŋď.!!]",
  "help.nodeOverviewInfo": "[!!Ťħīś īńƒőřmąťĭơň āƿƿĕâŕś őƞ ţĥė ŋŏďē ƥŕơƒīŀē, őŕğȃŋıƶåţīōņ ƥãģĕŝ, šȅȁŕčĥ ŗȇŝůŀţš, âƞđ Ƃȇȳōńď.!!]",
  "help.language": "[!!Ŧħȇ ļàńğūáģė ųŝęď ƒőŕ ťħȅ ļĩĸȅŝ ơƒ ďēşċřĭƥŧįŏń, ċıťȁťįōń ęŧĉ!!]",
  "help.orgDefaultValuesInfo": "[!!Ɖĕƒȁůĺţ vāľŭęŝ áŕȅ ıņťȅńďĕď ƒŏŕ áƿƿĺĩćåťįōňś ţő šţŏŕė īŉƒōŗmâŧĭőŉ äɓőűţ āň ěŋťĩŧŷ. Ä đėƒâūļť vǻľũȅ ĭş ęşśȇňťĭâļļƴ å ňàmȇ/váłũē ƥãĩř, ťĥàŧ ıŝ ćąţėġőřĩšęď ĭŋ â ňâmęšƥąčė 'ďĕƒāůľŧ-ŧȇŗm.ġɓĭƒ.ơŗġ'. Ţħĕ 2 ƿǻřťś māŷ Ƃě ųşȅď ǻś ťĥȅ ãƿƿĺįčȁţīōň şěěş ƒīť.!!]",
  "help.coordinates": "[!!Ůśȇ màƥ ŧŏ şēļĕĉŧ ŷōūŕ ĉōōřďįƞąţȇŝ màƞŭąľĺȳ!!]",
  "physicalAddress": "[!!Ƥĥɏšĭĉāŀ ąđďřėŝś!!]",
  "mailingAddress": "[!!Mäįļıņğ ąđďŗėšş!!]",
  "important.deleted.organization": "[[[!This organization was deleted {relativeTime} by {name}.!]]]",
  "important.deleted.dataset": "[[[!This dataset was deleted {relativeTime} by {name}.!]]]",
  "important.deleted.installation": "[[[!This installation was deleted {relativeTime} by {name}.!]]]",
  "important.deleted.collection": "[[[!This collection was deleted {relativeTime} by {name}.!]]]",
  "important.deleted.institution": "[[[!This institution was deleted {relativeTime} by {name}.!]]]",
  "important.deleted.person": "[[[!This person was deleted {relativeTime} by {name}.!]]]",
  "important.disabled.installation": "[!!Ŧĥĭś īňşťàłľåŧīŏŋ įś đıšȁƂłēď ăńď ŋơ âūŧō ũƿđăţĕş ŵĩłŀ őččŭŗ!!]",
  "restore.organization": "[!!Ʀěśťőŕě ťħĭš őŗġȁƞıžȁŧĩōń!!]",
  "restore.dataset": "[!!Řȅŝŧơŕę ťħĩş đāţȁşėŧ!!]",
  "restore.installation": "[!!Řěşŧőŗē ţħįŝ īņşţâłľäţĭōņ!!]",
  "restore.collection": "[!!Řėŝťơŕē ťħış ćŏłĺȅćŧĩőŋ!!]",
  "restore.institution": "[!!Ŕēşţơŕę ťĥįś īňşţīťűťĭőŉ!!]",
  "restore.person": "[!!Ʀȅśťơřē ŧħĭś ƿěŕŝōŋ!!]",
  "restore.confirmation": "[!!Ŗěŝťőŗīńĝ â ƿřȅvīŏũşĺȳ ďȇĺęŧȇď ȇŋťĩťɏ ŵīļľ łīƙęĺŷ ťŗĩģğěŗ şīĝńĩƒįćäņť ƿŗōćȅššĭņğ!!]",
  "delete.confirmation.comment": "[!!Ăŕȅ ɏŏŭ şųřę ŧō ďȇłĕťȅ ťĥĩš ćŏmmęňť?!!]",
  "delete.confirmation.contact": "[!!Âřȅ ȳŏů ŝŭřė ŧő đěŀĕťȇ ťħįš ĉőņťăčť?!!]",
  "delete.confirmation.endpoint": "[!!Áŗĕ ȳőū šűŗė ťō đěľĕŧě ťĥĩś ěŋďƥőįńť?!!]",
  "delete.confirmation.identifier": "[!!Ãřė ƴŏŭ ŝűŗě ŧő ďěłȇŧę ŧĥĩś ıđěŋţĩƒıėŕ?!!]",
  "delete.confirmation.machineTag": "[!!Ąŗę ȳōű şűŕę ţơ đěĺȅŧė ťħīŝ măĉħĩƞē ţǻğ?!!]",
  "delete.confirmation.tag": "[!!Àŗě ɏŏū šůřȅ ţơ đēłēťȇ ţħĭş ŧãĝ?!!]",
  "delete.confirmation.organization": "[!!Ȁŕę ŷŏũ ŝūŕĕ ţơ đȇļęŧė ťĥış ơŕģåƞıźǻţįơŋ?!!]",
  "delete.confirmation.dataset": "[!!Ãřė ȳőű šūŕȇ ŧō đėĺĕţĕ ŧħīŝ ďâţâśĕť?!!]",
  "delete.confirmation.installation": "[!!Ǻŗē ŷŏů ŝůŗȇ ťŏ đėļęŧĕ ťħıŝ īŉśţãŀŀåŧĭŏņ?!!]",
  "delete.confirmation.collection": "[!!Ȃŗě ƴőū šŭŕę ŧơ đęŀĕťȅ ţħīś čŏļĺĕčťĭōň?!!]",
  "delete.confirmation.institution": "[!!Åŗě ƴơū śůŗę ţŏ đěľȅţĕ ťĥīś ĩŉšţīŧŭŧĩŏń?!!]",
  "delete.confirmation.person": "[!!Ąŗě ŷơų şūŗē ŧő đēłěŧȇ ŧħĩŝ ƥēŕšŏń?!!]",
  "delete.confirmation.defaultValue": "[!!Ȃŗȇ ŷőŭ šūŕė ťő ďȅļĕţē ŧĥış ďėƒåųĺţ väľűė?!!]",
  "delete.organization": "[!!Ɖȇĺęţē ťĥıŝ ōŗğáňĭžãţĭơŉ!!]",
  "delete.dataset": "[!!Ɖęĺĕţȇ ŧĥįŝ ďâţåšĕţ!!]",
  "delete.installation": "[!!Ɖȅŀęŧę ťĥĩş ıņšťǻŀĺąŧıőŋ!!]",
  "delete.person": "[!!Ďėľėťě ŧħĩŝ ƿėřşōń!!]",
  "delete.collection": "[!!Ɗěļěŧȅ ţĥıŝ ċōļľęćţįőƞ!!]",
  "delete.institution": "[!!Ɗȇłēŧė ŧĥış įņśťĭţŭťĩőƞ!!]",
  "organization.retrievePassword": "[!!Ŗęţŕĩȇvȇ ƿãšśŵőŕď!!]",
  "organization.retrievePassword.message": "[[[!The password is only for use with the IPT (the GBRDS API), registering datasets using new API ({api}) requires a user with {role} permission and an entry in the {table} table. {password}!]]]",
  "notFound": "[!!Ɲōť Ƒŏűňď!!]",
  "search": "[!!Śēȁŕčĥ!!]",
  "searchTable": "[!!Šȅăŕċĥ ťåƄłě!!]",
  "query": "[[[! for '{query}'!]]]",
  "registryMeta": "[!!Ŕȅģĭŝťŗƴ mėţâđȃţă!!]",
  "download": "[!!Ďơŵņľŏǻď!!]",
  "downloads": "[!!Ɗŏŵňļŏāďś!!]",
  "status": "[!!Şţȃťũš!!]",
  "contact": "[!!Ĉōƞŧãčť!!]",
  "copyrights": "[!!Ťħįś şıťę ıš ȃƒƒįłĭȃţȅď ťŏ ĞßİƑ | Ĝľōƅãĺ Ɓıőďıvęřśīŧƴ Įŉƒōřmąťĩōņ Ƒáĉĩľĭťƴ.!!]",
  "cookieAndPolicy": "[!!Ĉőőķīę àņđ ƿřĩvâčŷ ƥơľĭċȳ.!!]",
  "githubRepo": "[!!ĞįŧĦųɓ Řēƥőśįťŏŕŷ!!]",
  "issuesTracker": "[!!İŝŝųėś ťŕȁĉķęŗ!!]",
  "gbifCount": "[!!ĠɃİƑ ċōūńţ!!]",
  "gbifCount.tooltip": "[!!Ōčćųŕŗȅņćęš ıŋ ťħĕ ĜƁĪƑ ıŋđĕx!!]",
  "lastCrawlCount": "[!!Ŀȁśť čŕăŵļ ċōŭŋŧ!!]",
  "offBy": "[!!Ōƒƒ ɓɏ %!!]",
  "lastCrawlId": "[!!Ŀâŝť čŕȃŵļ ĩđ!!]",
  "histogram": "[!!Ħĩŝŧőĝřǻm!!]",
  "ingestionHistory": "[!!Įņġęşťĩŏŋ ħįŝŧŏŕɏ!!]",
  "ingestion": "[!!Ʀűňŋĭŋģ įňĝěšŧıōńş!!]",
  "overingested": "[!!Ŏvęŕ-ĩŋğěśŧēđ ďȃťăśĕťŝ!!]",
  "monitoring": "[!!Mōƞįťőřīńġ!!]",
  "overingested.about": "[!!<ħ1>Äɓōůŧ ŧħĭš ťōōł</ĥ1>\n<ƥ>Ţħę ŏvȅřćŗǻŵĺ mőňĭŧŏř ħĕĺƿš şƿŏţ ďàţáśēťŝ ŧħàť mıġħť ƅě ōvęŕċŗȁŵļȇď. <šťŗōńğ>ßě ąŵãŗē ťħãť ťħė ďãŧà ıƞ ťĥě ťǻƂļė ış ơŉļȳ ųƿđăŧȇđ őņćė â ďȃƴ</śťŕőŉğ> äņď ţħãŧ īš <ŝţŗőŋğ>őņļƴ šħōŵş ĐŵČ-Ă đāţăşēţ ĉŕǻŵľş</šŧŗőŉģ> ċųŕŗēņţłƴ.</ƿ>\n<ĥ2>Ħơŵ įť ŵŏŗĸś</ħ2>\n<ƥ>Ŵĥȅŉ ȁ đǻŧäšěť ĭš čŕåŵŀėď ąŀľ ơčĉųŕřěŋċē ŕęĉōřđş čŗēăţȇď, ůƿďąťęď ōŗ śěěŉ ŧō Ƃę ŵıţĥŏůť ċĥąŋĝȇ ŵīĺļ Ƅē ųƿđåţȇđ ŵĭťħ ţħē ĉųŕŕȇňţ čŗăŵľ ĬĐ. Ŏňčĕ ã ďȁŷ ā śȅŗvįčě įńşƥęčťŝ ŧħĕ įńđȅx ãńđ ıđȇńŧĭƒįěś ďąŧâŝēţš ŵĩŧħ ŕȇĉŏŕďś ŵĩţĥįŋ ťħåť đǻťäşęţ ŵīţĥ á ćŕȁŵŀĪĐ ďįƒƒėřīňġ ťő ťħė mŏšŧ ŕęĉȅńť ċŕåŵĺ. Ůňđėŗ ņōŕmàł ŵơŕķĩńĝ čŏńďĩţĩōňś, ȁĺŀ ŗĕĉơŗđŝ šħơůĺď ħȁvĕ ťĥė mŏşŧ řĕčęŉŧ ćŗâŵľ ĬƊ åņď åņɏ ŕĕmâįŉīŉģ şħōųľď Ƅě đěłȇťęđ. Ţĥīş ŵĩĺļ ħäƿƿėņ äųţōmȁţĭčãļľƴ ŭƿ ŧŏ å ŧħŕĕšĥŏŀđ. Ŧħĕ mōńīţŏŕ şħơŵš ǻļļ ţħơŝȇ ŗěmȃĩńĭŋġ ţĥǻť ăĥvĕ Ƃȇěŉ ĩđėŉŧıƒĩĕď àš ŉōť mėĕťīƞğ ţħȅ čơņđīťīōƞŝ ţō ɓĕ đėĺėŧěď ăŭŧŏmáţĩčǻŀŀȳ ãňď <šţřōŉğ>ƞęȇď ăđmīńĩśťŕåťōŗ ãŧŧęńţĩōň</šťřőńĝ>.\nĪŧ śĥơŭłď ɓĕ ťħė ċâŝė ťħāť ťĥıś ćŏńşōĺě śħőŵš ƞŏ řŏŵš őƒ đâŧá įƒ āļĺ đàţȁśĕţŝ ąřě ĩŋ şȳŋč. <şţřŏŋĝ>Ŧħĭš ış ţħȅ ğŏåľ</šţŗơňğ>.</ƥ>\n<űľ>\n<ļī>ĢßĬƑ čŏũŋŧ: ħơŵ mǻŋɏ ŕȅċōŗđŝ ȃŕė ĭŋ ŧħȇ ĜßĮƑ ıŉđěx ƒŕơm ťħĭš đȃŧǻşėť.</ľĭ>\n<ŀį>Ļȃŝŧ ċřâŵĺ čơůņŧ: ħőŵ måŉȳ řěčơŕďş ŵǻŝ ƥřŏvıďȇď īŋ ţĥȇ ĺȃšŧ čŗȁŵļ ōƒ ţħȇ đäţâşȅŧ.</ŀĭ>\n<łĩ>Őƒƒ Ƅŷ: ħŏŵ mąŉŷ ƿȇŗĉęŋŧǻġȅ őƒ ťěħ đãţāśȅť ŵơŭľď ɓȇ ďėľėţȇđ īƒ ŵě ďȅľěťēď ěvȅřɏţħıƞġ ƅũŧ ţĥĕ ŀãşŧ ĉřȁŵł.</łĭ>\n<ĺĭ>Ľȃŝť ċřäŵľ ıď: ĥŏŵ máņŷ ťīmĕš ĥàvę ťħįŝ đăťǻŝěť ƃĕȅŋ ćŕâŵłėđ.</ļĭ>\n<ĺī>Ħĩšţơĝřąm: ňūmƂĕŕ ơƒ ŏċčųŕŗȅŋčĕŝ ƒơř đĭƒƒęŕėňť čŗǻŵŀ ĪƉş</łī>\n</ůŀ>\n!!]",
  "ingestion.about": "[!!<ĥ1>ǺƂŏųŧ ŧĥę ďāŧáŝĕŧ įńģėšţıŏņ mơŉıťơŗ</ħ1>\n<ƿ>Ţħĭŝ ŧőőĺ ƥřővįđėş ǻň ōvėřvīęŵ ơƒ ŵħĭćħ đãŧăšĕţš āŗȇ čŭŕřȇŉţľȳ ɓĕīƞĝ īŋģėŝťēđ ĭƞŧő ĞɃĨƑ'ŝ đäťȃ ŝťŏŗȅ. İţ ĭś ƥřīmàŕįľƴ īŋţęņďěđ ƒơŕ ŧěċħŋıčãł ůśĕŕś ŧĥäť ŭŋđęŕŝŧǻŉď ťĥė ĞßİƑ ĩŋĝěŝŧĭŏň ƿŕơċęďůŕęş. Ŧőğġļȅ ťĥȅ ħėŀƿ ƒőř àŉ ěxƥľâņãŧĭōň ơƒ ţħȅ čőľűmŋ ĥȇāďįŉġš.</ƥ>\n!!]",
  "declaredCount.full": "[!!Ɖȅćĺäřĕď ċōųńŧ!!]",
  "declaredCount.short": "[!!ĎĆ!!]",
  "pagesCrawled.full": "[!!Ƥąĝȅš ćŕǻŵľēď!!]",
  "pagesCrawled.short": "[!!ƤĊ!!]",
  "pagesFragmentedSuccessful.full": "[!!Ƥąġęš ƒŗåĝmēńţȅď śųćčēŝšƒųļŀƴ!!]",
  "pagesFragmentedSuccessful.short": "[!!ƤƑŜ!!]",
  "pagesFragmentedError.full": "[!!Ƥǻğĕŝ ńōŧ ƒŕąģmȅŋťĕď (ĕřŕőŗ)!!]",
  "pagesFragmentedError.short": "[!!ƤƑĔ!!]",
  "fragmentsEmitted.full": "[!!Ƒřȃğmėƞťš ȅmīťťēď!!]",
  "fragmentsEmitted.short": "[!!ƑĘ!!]",
  "fragmentsReceived.full": "[!!Ƒřåġmȇņťś ŗĕćėĩvėď!!]",
  "fragmentsReceived.short": "[!!ƑŘ!!]",
  "rawOccurrencesPersistedNew.full": "[!!Ŗãŵ őċĉūŕřȅńċėŝ ƿēřşĭŝŧȅđ (ŉȇŵ)!!]",
  "rawOccurrencesPersistedNew.short": "[!!ŘŎŇ!!]",
  "rawOccurrencesPersistedUpdated.full": "[!!Ʀåŵ ơċćũŕřȇƞċȅş ƿěŗśĩśŧȅđ (mŏđīƒīēđ)!!]",
  "rawOccurrencesPersistedUpdated.short": "[!!ŖŌM!!]",
  "rawOccurrencesPersistedUnchanged.full": "[!!Řăŵ őččūřřęŉćěš ƥēřšĩşťēď (ůņčĥåŉġēď)!!]",
  "rawOccurrencesPersistedUnchanged.short": "[!!ŖŐŨ!!]",
  "rawOccurrencesPersistedError.full": "[!!Ŗǻŵ ōċćųŕŕĕŉćĕŝ ƥȅŗşįşţēđ (ęŗŗōř)!!]",
  "rawOccurrencesPersistedError.short": "[!!ŘŎĔ!!]",
  "fragmentsProcessed.full": "[!!Ƒŗâĝmĕŋŧš ƥŕőċĕŝśĕď!!]",
  "fragmentsProcessed.short": "[!!ƑƤ!!]",
  "verbatimOccurrencesPersistedSuccessful.full": "[!!VěŕƂǻŧĭm ōċċŭřŗėňčęş ƿȅŕŝīśťȇđ şűĉčĕšśƒŭļľƴ!!]",
  "verbatimOccurrencesPersistedSuccessful.short": "[!!VŎƤ!!]",
  "verbatimOccurrencesPersistedError.full": "[!!Vęŕƅąťım ōćĉůŗŕĕņčȇś ƥėřśįšţěđ (ęŕřŏŕ)!!]",
  "verbatimOccurrencesPersistedError.short": "[!!VŐȄ!!]",
  "interpretedOccurrencesPersistedSuccessful.full": "[!!Ĭƞţēřƿŕęŧȅď ơĉċųřŕęŋćȇś ƿěŗşĩśťėď ŝŭčċĕŝşƒűĺłȳ!!]",
  "interpretedOccurrencesPersistedSuccessful.short": "[!!ŎĮ!!]",
  "interpretedOccurrencesPersistedError.full": "[!!Ĩƞţȇřƿŕėţėď ŏċćųŕŗēŉċēš ƥęŕśıśţĕď (ĕŗŗőŕ)!!]",
  "interpretedOccurrencesPersistedError.short": "[!!ƠĚ!!]",
  "startedCrawling.full": "[!!Śŧāŗŧ ťīmĕ!!]",
  "startedCrawling.short": "[!!ŠŦ!!]",
  "logs": "[!!Ĺōĝŝ!!]",
  "all": "[!!Äļł!!]",
  "ingestion.checkbox.liveView": "[!!Ľıvė vīėŵ!!]",
  "ingestion.checkbox.showHelp": "[!!Šħơŵ ħėļƥ!!]",
  "ingestion.checkbox.onlySelected": "[!!Ŏŉŀƴ šĥŏŵ śėłĕčťēď!!]",
  "misc": "[!!Mīśč!!]",
  "showOnlySelected": "[!!Őňłȳ śħōŵ şȇłȇċťęđ ĭţēmš!!]",
  "nResultsInTotal": "[[[!{formattedNumber} {count, plural, zero {results} one {result} other {results}} in total!]]]",
  "lastPublished": "[!!Ŀāŝŧ ƥŭƃļįŝĥĕď!!]",
  "source": "[!!Šőůŗčė!!]",
  "iptCount": "[!!ĮƤŢ ĉŏũŉţ!!]",
  "iptCount.tooltip": "[!!Ōċĉŭŕŕȅńċěš ȁĉċōŗđĭƞġ ţō ťĥē İƤŢ!!]",
  "syncState.about": "[!!<ħ1>Āƅőūť ĮƤŦ şȳŉĉ śţāŧęš</ĥ1>\n<ƿ>ĮƤŤš ħåvĕ å ŵâɏ ơƒ ţēŀĺĭŉġ ơŧĥȇŕ mȃćħıŉȅš ĥơŵ mȃňŷ ơćĉůŗřĕƞćĕŝ ŧĥēŷ ħävȇ ƥȇŗ ďąŧȃŝȅţ. ßě ăŵäŕė ŧħâť ŧĥīş mįğĥţ ŗěǭūįřē ɏơũŗ ĬƤŦ ťő ɓě ŭƥđǻťēď. Šėę ȃĺśō <ā ħŕěƒ=\"ħŧŧƿş://ġįťĥūƃ.ćőm/ģƂĭƒ/ıƥť/ĩššũėŝ/1344\">ĪƤŦ Ɓųğ 1344</ã>.\nŤĥĭş ŧōōľ čōmƿāŕȇŝ ţĥĕ İƤŢ ĭŉvēƞţōřɏ ŵįţħ ŧĥĕ ƞūmɓĕŗ ŏƒ ŏċčůŗŕĕńċȅś īŉ ťħę ĜɃĨƑ ĭŋđĕx. Įƒ ŧħē ŧŵő đōƞ'ŧ àľĭĝň ŧħėƞ ƴŏū şĥōūľď ıňvěšŧıĝåťę ŵĥɏ ţĥĕ šɏńćĥŗŏƞįŝáţıőņ ƒāıľš ŏŕ ĝėŧ ĩń ťőŭċħ ŵīţħ ťĥė ĜßĪƑ šȇćřĕţȁŗĩȁŧ.</ƥ>\n<ĥ2>Ĥŏŵ ŧŏ ūŝȅ īť</ħ2>\n<ƿ>Ĕņŧęŕ ţħȅ ŲƦĹ ŏƒ ŷőůř ıƿť (ȇ.ĝ. <ćơďē>ĥŧťƿ://máĕŗųā.ĩīċŧ.ƥţ/ıƥŧ</ċŏđė>). Įƒ ŷōųŗ ĩƿŧ şūƿƥōŗťş ţĥĕ <ĉŏđę>/įŋvěňţőřŷ/ďàťäšēť</ċōđȅ> čàĺĺ ŧĥĕŉ ƴŏű šħŏŭĺđ śȇė à ļĭšţ őƒ đăŧȃŝėţş</ƿ>\n!!]",
  "details.crawling": "[!!Īńģĕšŧīőŋ đěťǻįĺš!!]",
  "recordPersisting": "[!!Ŗĕĉŏŕđ ƥĕŕśīŝťįńĝ!!]",
  "recordNormalization": "[!!Řěćōŗď ƞőŗmąŀīƶȁŧīőň (ȅ.ğ. ƥāŕşĭƞģ XMĽ)!!]",
  "recordInterpretation": "[!!Řěćōŕđ ĭŉťęŕƿŗęţäŧıōŉ (ě.ġ. ǫųâľĩŧɏ, àņđ ƞűƃ ŀơơķųƥ)!!]",
  "duration": "[!!Đūŗäŧīŏŉ!!]",
  "received": "[!!Ŗȅćėīvėď!!]",
  "new": "[!!Ņȅŵ!!]",
  "updated": "[!!Ŭƥđâŧȇđ!!]",
  "unchanged": "[!!Ūňċħàňģěď!!]",
  "failed": "[!!Ƒăĩłėđ!!]",
  "syncState": "[!!Şɏŋċ şţȁŧȇ!!]",
  "crawling": "[!!Ćřāŵļīŋġ!!]",
  "tooltip.fragmentsReceived": "[!!Ŗěčȅıvęđ ƒŗȁģměňţŝ ĕxƿĕĉŧēď ŧŏ ȇɋŭāł Ňěŵ + Űƿđàţȇđ + Ųňćħǻńġēď + Ēŗŕōŕś!!]",
  "occurrencesInGBIF": "[[[!{count} occurrences in the GBIF index!]]]",
  "outOfSync": "[!!Őũť ŏƒ śƴņĉ!!]",
  "outOfSync.tooltip": "[!!Ŀåśţ ŊŐŖMÃĿ ıňģȇŝţıőŋ ƿřőĉęşş ŕȅĉȇıvȅď ĉőųƞť ďŏęŝń'ť ėɋũāļ ŏċćųŗŕęƞċę ĭƞđēx čőũńŧ!!]",
  "coordinates": "[!!Ćōơŗđĭņāťęş!!]",
  "scopes.title": "[!!Şćőƿĕş!!]",
  "scopes.node": "[!!Ňơďȇ şćōƿěś!!]",
  "scopes.organization": "[!!Ŏřĝąƞīžàţĩơƞ ŝĉōƥęŝ!!]"
}